Workbook
Name Clientes: [1]Referencias!$B$7:$C$12
Name Clientes: [2]Referencias!$B$7:$C$50
Name Clientes: [3]Referencias!$B$7:$C$82
Name Clientes: [1]Referencias!$B$7:$C$12
Name Clientes: Referencias!$B$7:$C$154
Name imputacion: #REF!
Name imputacion: #REF!
Name imputacion: #REF!

Sheet Trabajos
B2: Trabajos
G3: Total | H3: =SUBTOTAL(9,H5:H394) -> 57801 | O3: Total | P3: =SUBTOTAL(9,P5:P394) -> 2.2427234e+08
B4: Fecha | C4: Cod. Trabajo | D4: Tipo de trabajo | E4: Cod. Cliente | F4: Cliente | G4: Establecimiento | H4: Superficie | I4: $/Ha | J4: Subtotal | K4: Cod. Vehiculo | L4: Vehiculo | M4: Distancia | N4: $/Km | O4: Movilidad | P4: Importe | R4: Paco | S4: Tomas | T4: Zoom | U4: Personas
B5: 45909 | C5: 1 | D5: =IFERROR(VLOOKUP(Trabajos!C5,Referencias!$E$7:$F$30,2,FALSE),"") -> Muestreo de suelos | E5: 33 | F5: =IFERROR(VLOOKUP(Trabajos!$E5,Clientes,2,FALSE),"") -> Espartina S.A. | G5: El Casalito | H5: 80 | I5: 947.70673 | J5: =IF(H5<>"",H5*I5,"") -> 75816.538 | K5: 1 | L5: =IFERROR(VLOOKUP(K5,Referencias!$H$7:$I$9,2,FALSE),"") -> Tomas | M5: 0 | N5: 576.1 | O5: =IF(M5<>"",M5*N5,"") -> 0 | P5: =IF(J5<>"",J5+O5,"") -> 75816.538 | R5: 0 | S5: 80 | T5: =H5-R5-S5 -> 0
B6: 45909 | C6: 1 | D6: =IFERROR(VLOOKUP(Trabajos!C6,Referencias!$E$7:$F$30,2,FALSE),"") -> Muestreo de suelos | E6: 33 | F6: =IFERROR(VLOOKUP(Trabajos!$E6,Clientes,2,FALSE),"") -> Espartina S.A. | G6: Las Bagualas | H6: 80 | I6: 947.70673 | J6: =IF(H6<>"",H6*I6,"") -> 75816.538 | K6: 1 | L6: =IFERROR(VLOOKUP(K6,Referencias!$H$7:$I$9,2,FALSE),"") -> Tomas | M6: 0 | N6: 576.1 | O6: =IF(M6<>"",M6*N6,"") -> 0 | P6: =IF(J6<>"",J6+O6,"") -> 75816.538 | R6: 0 | S6: 0 | T6: =H6-R6-S6 -> 80
B7: 45909 | C7: 1 | D7: =IFERROR(VLOOKUP(Trabajos!C7,Referencias!$E$7:$F$30,2,FALSE),"") -> Muestreo de suelos | E7: 33 | F7: =IFERROR(VLOOKUP(Trabajos!$E7,Clientes,2,FALSE),"") -> Espartina S.A. | G7: San Marcos | H7: 80 | I7: 947.70673 | J7: =IF(H7<>"",H7*I7,"") -> 75816.538 | K7: 1 | L7: =IFERROR(VLOOKUP(K7,Referencias!$H$7:$I$9,2,FALSE),"") -> Tomas | M7: 0 | N7: 576.1 | O7: =IF(M7<>"",M7*N7,"") -> 0 | P7: =IF(J7<>"",J7+O7,"") -> 75816.538 | R7: 0 | S7: 0 | T7: =H7-R7-S7 -> 80
B8: 45909 | C8: 1 | D8: =IFERROR(VLOOKUP(Trabajos!C8,Referencias!$E$7:$F$30,2,FALSE),"") -> Muestreo de suelos | E8: 33 | F8: =IFERROR(VLOOKUP(Trabajos!$E8,Clientes,2,FALSE),"") -> Espartina S.A. | G8: Los Tulipanes | H8: 80 | I8: 947.70673 | J8: =IF(H8<>"",H8*I8,"") -> 75816.538 | K8: 1 | L8: =IFERROR(VLOOKUP(K8,Referencias!$H$7:$I$9,2,FALSE),"") -> Tomas | M8: 184 | N8: 576.1 | O8: =IF(M8<>"",M8*N8,"") -> 106002.4 | P8: =IF(J8<>"",J8+O8,"") -> 181818.94 | R8: 0 | S8: 0 | T8: =H8-R8-S8 -> 80
B9: 45911 | C9: 1 | D9: =IFERROR(VLOOKUP(Trabajos!C9,Referencias!$E$7:$F$30,2,FALSE),"") -> Muestreo de suelos | E9: 33 | F9: =IFERROR(VLOOKUP(Trabajos!$E9,Clientes,2,FALSE),"") -> Espartina S.A. | G9: La Paz | H9: 80 | I9: 947.70673 | J9: =IF(H9<>"",H9*I9,"") -> 75816.538 | K9: 1 | L9: =IFERROR(VLOOKUP(K9,Referencias!$H$7:$I$9,2,FALSE),"") -> Tomas | M9: 270 | N9: 576.1 | O9: =IF(M9<>"",M9*N9,"") -> 155547 | P9: =IF(J9<>"",J9+O9,"") -> 231363.54 | R9: 0 | S9: 80 | T9: =H9-R9-S9 -> 0
B10: 45911 | C10: 1 | D10: =IFERROR(VLOOKUP(Trabajos!C10,Referencias!$E$7:$F$30,2,FALSE),"") -> Muestreo de suelos | E10: 33 | F10: =IFERROR(VLOOKUP(Trabajos!$E10,Clientes,2,FALSE),"") -> Espartina S.A. | G10: Bella Vista | H10: 80 | I10: 947.70673 | J10: =IF(H10<>"",H10*I10,"") -> 75816.538 | K10: 1 | L10: =IFERROR(VLOOKUP(K10,Referencias!$H$7:$I$9,2,FALSE),"") -> Tomas | M10: 0 | N10: 576.1 | O10: =IF(M10<>"",M10*N10,"") -> 0 | P10: =IF(J10<>"",J10+O10,"") -> 75816.538 | R10: 0 | S10: 0 | T10: =H10-R10-S10 -> 80
B11: 45912 | C11: 10 | D11: =IFERROR(VLOOKUP(Trabajos!C11,Referencias!$E$7:$F$30,2,FALSE),"") -> Mapeo Dron | E11: 122 | F11: =IFERROR(VLOOKUP(Trabajos!$E11,Clientes,2,FALSE),"") -> Martin Juarez | G11: La Juana | H11: 50 | I11: 7625.8 | J11: =IF(H11<>"",H11*I11,"") -> 381290 | K11: 1 | L11: =IFERROR(VLOOKUP(K11,Referencias!$H$7:$I$9,2,FALSE),"") -> Tomas | M11: 0 | N11: 650 | O11: =IF(M11<>"",M11*N11,"") -> 0 | P11: =IF(J11<>"",J11+O11,"") -> 381290 | R11: 0 | S11: 50 | T11: =H11-R11-S11 -> 0
B12: 45913 | C12: 2 | D12: =IFERROR(VLOOKUP(Trabajos!C12,Referencias!$E$7:$F$30,2,FALSE),"") -> Monitoreo de bb y bab | E12: 33 | F12: =IFERROR(VLOOKUP(Trabajos!$E12,Clientes,2,FALSE),"") -> Espartina S.A. | G12: Don Gustavo | H12: 107 | I12: 3318.75 | J12: =IF(H12<>"",H12*I12,"") -> 355106.25 | K12: 1 | L12: =IFERROR(VLOOKUP(K12,Referencias!$H$7:$I$9,2,FALSE),"") -> Tomas | M12: 364 | N12: 576.1 | O12: =IF(M12<>"",M12*N12,"") -> 209700.4 | P12: =IF(J12<>"",J12+O12,"") -> 564806.65 | R12: 0 | S12: 70 | T12: =H12-R12-S12 -> 37
B13: 45913 | C13: 2 | D13: =IFERROR(VLOOKUP(Trabajos!C13,Referencias!$E$7:$F$30,2,FALSE),"") -> Monitoreo de bb y bab | E13: 33 | F13: =IFERROR(VLOOKUP(Trabajos!$E13,Clientes,2,FALSE),"") -> Espartina S.A. | G13: San Luciano | H13: 173 | I13: 3318.75 | J13: =IF(H13<>"",H13*I13,"") -> 574143.75 | K13: 1 | L13: =IFERROR(VLOOKUP(K13,Referencias!$H$7:$I$9,2,FALSE),"") -> Tomas | M13: 340 | N13: 576.1 | O13: =IF(M13<>"",M13*N13,"") -> 195874 | P13: =IF(J13<>"",J13+O13,"") -> 770017.75 | R13: 0 | S13: 0 | T13: =H13-R13-S13 -> 173
B14: 45913 | C14: 1 | D14: =IFERROR(VLOOKUP(Trabajos!C14,Referencias!$E$7:$F$30,2,FALSE),"") -> Muestreo de suelos | E14: 33 | F14: =IFERROR(VLOOKUP(Trabajos!$E14,Clientes,2,FALSE),"") -> Espartina S.A. | G14: Don Gustavo | H14: 80 | I14: 947.70673 | J14: =IF(H14<>"",H14*I14,"") -> 75816.538 | K14: 1 | L14: =IFERROR(VLOOKUP(K14,Referencias!$H$7:$I$9,2,FALSE),"") -> Tomas | M14: 0 | N14: 576.1 | O14: =IF(M14<>"",M14*N14,"") -> 0 | P14: =IF(J14<>"",J14+O14,"") -> 75816.538 | R14: 0 | S14: 0 | T14: =H14-R14-S14 -> 80
B15: 45913 | C15: 1 | D15: =IFERROR(VLOOKUP(Trabajos!C15,Referencias!$E$7:$F$30,2,FALSE),"") -> Muestreo de suelos | E15: 33 | F15: =IFERROR(VLOOKUP(Trabajos!$E15,Clientes,2,FALSE),"") -> Espartina S.A. | G15: San Luciano | H15: 80 | I15: 947.70673 | J15: =IF(H15<>"",H15*I15,"") -> 75816.538 | K15: 1 | L15: =IFERROR(VLOOKUP(K15,Referencias!$H$7:$I$9,2,FALSE),"") -> Tomas | M15: 0 | N15: 576.1 | O15: =IF(M15<>"",M15*N15,"") -> 0 | P15: =IF(J15<>"",J15+O15,"") -> 75816.538 | R15: 0 | S15: 0 | T15: =H15-R15-S15 -> 80
B16: 45914 | C16: 2 | D16: =IFERROR(VLOOKUP(Trabajos!C16,Referencias!$E$7:$F$30,2,FALSE),"") -> Monitoreo de bb y bab | E16: 33 | F16: =IFERROR(VLOOKUP(Trabajos!$E16,Clientes,2,FALSE),"") -> Espartina S.A. | G16: Santa Ana Cobo | H16: 379 | I16: 3318.75 | J16: =IF(H16<>"",H16*I16,"") -> 1257806.2 | K16: 1 | L16: =IFERROR(VLOOKUP(K16,Referencias!$H$7:$I$9,2,FALSE),"") -> Tomas | M16: 172 | N16: 576.1 | O16: =IF(M16<>"",M16*N16,"") -> 99089.2 | P16: =IF(J16<>"",J16+O16,"") -> 1356895.4 | R16: 0 | S16: 95 | T16: =H16-R16-S16 -> 284
... B87: 45940 | C87: 3 | D87: =IFERROR(VLOOKUP(Trabajos!C87,Referencias!$E$7:$F$30,2,FALSE),"") -> Aplicación de cebos | E87: 33 | F87: =IFERROR(VLOOKUP(Trabajos!$E87,Clientes,2,FALSE),"") -> Espartina S.A. | G87: El Moro Viejo | H87: 107 | I87: 7267.5 | J87: =IF(H87<>"",H87*I87,"") -> 777622.5 | K87: 1 | L87: =IFERROR(VLOOKUP(K87,Referencias!$H$7:$I$9,2,FALSE),"") -> Tomas | M87: 156 | N87: 633.85 | O87: =IF(M87<>"",M87*N87,"") -> 98880.6 | P87: =IF(J87<>"",J87+O87,"") -> 876503.1 | R87: 0 | S87: 80 | T87: =H87-R87-S87 -> 27
B88: 45940 | C88: 10 | D88: =IFERROR(VLOOKUP(Trabajos!C88,Referencias!$E$7:$F$30,2,FALSE),"") -> Mapeo Dron | E88: 84 | F88: =IFERROR(VLOOKUP(Trabajos!$E88,Clientes,2,FALSE),"") -> Domingo y Nestor Scioli | G88: La Providencia | H88: 258 | I88: 4360.5 | J88: =IF(H88<>"",H88*I88,"") -> 1125009 | K88: 1 | L88: =IFERROR(VLOOKUP(K88,Referencias!$H$7:$I$9,2,FALSE),"") -> Tomas | M88: 0 | N88: 650 | O88: =IF(M88<>"",M88*N88,"") -> 0 | P88: =IF(J88<>"",J88+O88,"") -> 1125009 | R88: 0 | S88: 80 | T88: 0
B89: 45941 | C89: 2 | D89: =IFERROR(VLOOKUP(Trabajos!C89,Referencias!$E$7:$F$30,2,FALSE),"") -> Monitoreo de bb y bab | E89: 33 | F89: =IFERROR(VLOOKUP(Trabajos!$E89,Clientes,2,FALSE),"") -> Espartina S.A. | G89: Los Tulipanes | H89: 117 | I89: 3035.25 | J89: =IF(H89<>"",H89*I89,"") -> 355124.25 | K89: 3 | L89: =IFERROR(VLOOKUP(K89,Referencias!$H$7:$I$9,2,FALSE),"") -> Zoom | M89: 0 | N89: 588 | O89: =IF(M89<>"",M89*N89,"") -> 0 | P89: =IF(J89<>"",J89+O89,"") -> 355124.25 | R89: 0 | S89: 0 | T89: =H89-R89-S89 -> 117
B90: 45941 | C90: 2 | D90: =IFERROR(VLOOKUP(Trabajos!C90,Referencias!$E$7:$F$30,2,FALSE),"") -> Monitoreo de bb y bab | E90: 33 | F90: =IFERROR(VLOOKUP(Trabajos!$E90,Clientes,2,FALSE),"") -> Espartina S.A. | G90: Las Bagualas | H90: 221 | I90: 3035.25 | J90: =IF(H90<>"",H90*I90,"") -> 670790.25 | K90: 3 | L90: =IFERROR(VLOOKUP(K90,Referencias!$H$7:$I$9,2,FALSE),"") -> Zoom | M90: 176 | N90: 588 | O90: =IF(M90<>"",M90*N90,"") -> 103488 | P90: =IF(J90<>"",J90+O90,"") -> 774278.25 | R90: 0 | S90: 0 | T90: =H90-R90-S90 -> 221
B91: 45941 | C91: 2 | D91: =IFERROR(VLOOKUP(Trabajos!C91,Referencias!$E$7:$F$30,2,FALSE),"") -> Monitoreo de bb y bab | E91: 33 | F91: =IFERROR(VLOOKUP(Trabajos!$E91,Clientes,2,FALSE),"") -> Espartina S.A. | G91: El Casalito | H91: 138 | I91: 3035.25 | J91: =IF(H91<>"",H91*I91,"") -> 418864.5 | K91: 3 | L91: =IFERROR(VLOOKUP(K91,Referencias!$H$7:$I$9,2,FALSE),"") -> Zoom | M91: 152 | N91: 588 | O91: =IF(M91<>"",M91*N91,"") -> 89376 | P91: =IF(J91<>"",J91+O91,"") -> 508240.5 | R91: 0 | S91: 0 | T91: =H91-R91-S91 -> 138
B92: 45941 | C92: 3 | D92: =IFERROR(VLOOKUP(Trabajos!C92,Referencias!$E$7:$F$30,2,FALSE),"") -> Aplicación de cebos | E92: 33 | F92: =IFERROR(VLOOKUP(Trabajos!$E92,Clientes,2,FALSE),"") -> Espartina S.A. | G92: El Moro Viejo | H92: 42 | I92: 7267.5 | J92: =IF(H92<>"",H92*I92,"") -> 305235 | K92: 1 | L92: =IFERROR(VLOOKUP(K92,Referencias!$H$7:$I$9,2,FALSE),"") -> Tomas | M92: 156 | N92: 633.85 | O92: =IF(M92<>"",M92*N92,"") -> 98880.6 | P92: =IF(J92<>"",J92+O92,"") -> 404115.6 | R92: 0 | S92: 0 | T92: =H92-R92-S92 -> 42
B93: 45941 | C93: 3 | D93: =IFERROR(VLOOKUP(Trabajos!C93,Referencias!$E$7:$F$30,2,FALSE),"") -> Aplicación de cebos | E93: 33 | F93: =IFERROR(VLOOKUP(Trabajos!$E93,Clientes,2,FALSE),"") -> Espartina S.A. | G93: San Francisco | H93: 132 | I93: 7267.5 | J93: =IF(H93<>"",H93*I93,"") -> 959310 | K93: 1 | L93: =IFERROR(VLOOKUP(K93,Referencias!$H$7:$I$9,2,FALSE),"") -> Tomas | M93: 90 | N93: 633.85 | O93: =IF(M93<>"",M93*N93,"") -> 57046.5 | P93: =IF(J93<>"",J93+O93,"") -> 1016356.5 | R93: 0 | S93: 80 | T93: =H93-R93-S93 -> 52
B94: 45937 | C94: 1 | D94: =IFERROR(VLOOKUP(Trabajos!C94,Referencias!$E$7:$F$30,2,FALSE),"") -> Muestreo de suelos | E94: 33 | F94: =IFERROR(VLOOKUP(Trabajos!$E94,Clientes,2,FALSE),"") -> Espartina S.A. | G94: San Jose | H94: 80 | I94: 947.70673 | J94: =IF(H94<>"",H94*I94,"") -> 75816.538 | K94: 1 | L94: =IFERROR(VLOOKUP(K94,Referencias!$H$7:$I$9,2,FALSE),"") -> Tomas | M94: 0 | N94: 588 | O94: =IF(M94<>"",M94*N94,"") -> 0 | P94: =IF(J94<>"",J94+O94,"") -> 75816.538 | R94: 0 | S94: 0 | T94: =H94-R94-S94 -> 80
B95: 45944 | C95: 2 | D95: =IFERROR(VLOOKUP(Trabajos!C95,Referencias!$E$7:$F$30,2,FALSE),"") -> Monitoreo de bb y bab | E95: 33 | F95: =IFERROR(VLOOKUP(Trabajos!$E95,Clientes,2,FALSE),"") -> Espartina S.A. | G95: Santa Isabel I | H95: 121 | I95: 3262.5 | J95: =IF(H95<>"",H95*I95,"") -> 394762.5 | K95: 2 | L95: =IFERROR(VLOOKUP(K95,Referencias!$H$7:$I$9,2,FALSE),"") -> Paco | M95: 218 | N95: 633.85 | O95: =IF(M95<>"",M95*N95,"") -> 138179.3 | P95: =IF(J95<>"",J95+O95,"") -> 532941.8 | R95: 70 | S95: 0 | T95: =H95-R95-S95 -> 51
B96: 45944 | C96: 2 | D96: =IFERROR(VLOOKUP(Trabajos!C96,Referencias!$E$7:$F$30,2,FALSE),"") -> Monitoreo de bb y bab | E96: 33 | F96: =IFERROR(VLOOKUP(Trabajos!$E96,Clientes,2,FALSE),"") -> Espartina S.A. | G96: La Susana | H96: 19 | I96: 3262.5 | J96: =IF(H96<>"",H96*I96,"") -> 61987.5 | K96: 2 | L96: =IFERROR(VLOOKUP(K96,Referencias!$H$7:$I$9,2,FALSE),"") -> Paco | M96: 218 | N96: 633.85 | O96: =IF(M96<>"",M96*N96,"") -> 138179.3 | P96: =IF(J96<>"",J96+O96,"") -> 200166.8 | R96: 0 | S96: 0 | T96: =H96-R96-S96 -> 19
B97: 45944 | C97: 10 | D97: =IFERROR(VLOOKUP(Trabajos!C97,Referencias!$E$7:$F$30,2,FALSE),"") -> Mapeo Dron | E97: 84 | F97: =IFERROR(VLOOKUP(Trabajos!$E97,Clientes,2,FALSE),"") -> Domingo y Nestor Scioli | G97: La Providencia | H97: 129 | I97: 4360.5 | J97: =IF(H97<>"",H97*I97,"") -> 562504.5 | K97: 1 | L97: =IFERROR(VLOOKUP(K97,Referencias!$H$7:$I$9,2,FALSE),"") -> Tomas | M97: 0 | N97: 650 | O97: =IF(M97<>"",M97*N97,"") -> 0 | P97: =IF(J97<>"",J97+O97,"") -> 562504.5 | R97: 0 | S97: 80 | T97: 0
B98: 45945 | C98: 2 | D98: =IFERROR(VLOOKUP(Trabajos!C98,Referencias!$E$7:$F$30,2,FALSE),"") -> Monitoreo de bb y bab | E98: 6 | F98: =IFERROR(VLOOKUP(Trabajos!$E98,Clientes,2,FALSE),"") -> La Nany S.A. | G98: La Nany | H98: 242 | I98: 3618.75 | J98: =IF(H98<>"",H98*I98,"") -> 875737.5 | K98: 3 | L98: =IFERROR(VLOOKUP(K98,Referencias!$H$7:$I$9,2,FALSE),"") -> Zoom | M98: 0 | N98: 650 | O98: =IF(M98<>"",M98*N98,"") -> 0 | P98: =IF(J98<>"",J98+O98,"") -> 875737.5 | R98: 0 | S98: 0 | T98: =H98-R98-S98 -> 242
B99: 45945 | C99: 2 | D99: =IFERROR(VLOOKUP(Trabajos!C99,Referencias!$E$7:$F$30,2,FALSE),"") -> Monitoreo de bb y bab | E99: 6 | F99: =IFERROR(VLOOKUP(Trabajos!$E99,Clientes,2,FALSE),"") -> La Nany S.A. | G99: La Adelia | H99: 260 | I99: 3618.75 | J99: =IF(H99<>"",H99*I99,"") -> 940875 | K99: 3 | L99: =IFERROR(VLOOKUP(K99,Referencias!$H$7:$I$9,2,FALSE),"") -> Zoom | M99: 104 | N99: 650 | O99: =IF(M99<>"",M99*N99,"") -> 67600 | P99: =IF(J99<>"",J99+O99,"") -> 1008475 | R99: 0 | S99: 0 | T99: =H99-R99-S99 -> 260
B100: 45945 | C100: 3 | D100: =IFERROR(VLOOKUP(Trabajos!C100,Referencias!$E$7:$F$30,2,FALSE),"") -> Aplicación de cebos | E100: 33 | F100: =IFERROR(VLOOKUP(Trabajos!$E100,Clientes,2,FALSE),"") -> Espartina S.A. | G100: Santa Isabel Cozumel | H100: 115 | I100: 7250 | J100: =IF(H100<>"",H100*I100,"") -> 833750 | K100: 2 | L100: =IFERROR(VLOOKUP(K100,Referencias!$H$7:$I$9,2,FALSE),"") -> Paco | M100: 186 | N100: 633.85 | O100: =IF(M100<>"",M100*N100,"") -> 117896.1 | P100: =IF(J100<>"",J100+O100,"") -> 951646.1 | R100: 80 | S100: 0 | T100: =H100-R100-S100 -> 35
B101: 45945 | C101: 3 | D101: =IFERROR(VLOOKUP(Trabajos!C101,Referencias!$E$7:$F$30,2,FALSE),"") -> Aplicación de cebos | E101: 33 | F101: =IFERROR(VLOOKUP(Trabajos!$E101,Clientes,2,FALSE),"") -> Espartina S.A. | G101: San Francisco | H101: 132 | I101: 7267.5 | J101: =IF(H101<>"",H101*I101,"") -> 959310 | K101: 1 | L101: =IFERROR(VLOOKUP(K101,Referencias!$H$7:$I$9,2,FALSE),"") -> Tomas | M101: 90 | N101: 633.85 | O101: =IF(M101<>"",M101*N101,"") -> 57046.5 | P101: =IF(J101<>"",J101+O101,"") -> 1016356.5 | R101: 0 | S101: 80 | T101: =H101-R101-S101 -> 52
B102: 45945 | C102: 3 | D102: =IFERROR(VLOOKUP(Trabajos!C102,Referencias!$E$7:$F$30,2,FALSE),"") -> Aplicación de cebos | E102: 33 | F102: =IFERROR(VLOOKUP(Trabajos!$E102,Clientes,2,FALSE),"") -> Espartina S.A. | G102: Don Gustavo | H102: 77 | I102: 7267.5 | J102: =IF(H102<>"",H102*I102,"") -> 559597.5 | K102: 3 | L102: =IFERROR(VLOOKUP(K102,Referencias!$H$7:$I$9,2,FALSE),"") -> Zoom | M102: 185 | N102: 633.85 | O102: =IF(M102<>"",M102*N102,"") -> 117262.25 | P102: =IF(J102<>"",J102+O102,"") -> 676859.75 | R102: 0 | S102: 0 | T102: =H102-R102-S102 -> 77
B103: 45945 | C103: 3 | D103: =IFERROR(VLOOKUP(Trabajos!C103,Referencias!$E$7:$F$30,2,FALSE),"") -> Aplicación de cebos | E103: 33 | F103: =IFERROR(VLOOKUP(Trabajos!$E103,Clientes,2,FALSE),"") -> Espartina S.A. | G103: Macedo | H103: 36 | I103: 7267.5 | J103: =IF(H103<>"",H103*I103,"") -> 261630 | K103: 3 | L103: =IFERROR(VLOOKUP(K103,Referencias!$H$7:$I$9,2,FALSE),"") -> Zoom | M103: 185 | N103: 633.85 | O103: =IF(M103<>"",M103*N103,"") -> 117262.25 | P103: =IF(J103<>"",J103+O103,"") -> 378892.25 | R103: 0 | S103: 0 | T103: =H103-R103-S103 -> 36
B104: 45941 | C104: 3 | D104: =IFERROR(VLOOKUP(Trabajos!C104,Referencias!$E$7:$F$30,2,FALSE),"") -> Aplicación de cebos | E104: 4 | F104: =IFERROR(VLOOKUP(Trabajos!$E104,Clientes,2,FALSE),"") -> Purtierra | G104: Ojo de Agua | H104: 122 | I104: 7460 | J104: =IF(H104<>"",H104*I104,"") -> 910120 | K104: 3 | L104: =IFERROR(VLOOKUP(K104,Referencias!$H$7:$I$9,2,FALSE),"") -> Zoom | M104: 92 | N104: 650 | O104: =IF(M104<>"",M104*N104,"") -> 59800 | P104: =IF(J104<>"",J104+O104,"") -> 969920 | R104: 0 | S104: 0 | T104: =H104-R104-S104 -> 122
B105: 45946 | C105: 1 | D105: =IFERROR(VLOOKUP(Trabajos!C105,Referencias!$E$7:$F$30,2,FALSE),"") -> Muestreo de suelos | E105: 33 | F105: =IFERROR(VLOOKUP(Trabajos!$E105,Clientes,2,FALSE),"") -> Espartina S.A. | G105: San Marcos | H105: 80 | I105: 947.70673 | J105: =IF(H105<>"",H105*I105,"") -> 75816.538 | K105: 3 | L105: =IFERROR(VLOOKUP(K105,Referencias!$H$7:$I$9,2,FALSE),"") -> Zoom | M105: 0 | N105: 588 | O105: =IF(M105<>"",M105*N105,"") -> 0 | P105: =IF(J105<>"",J105+O105,"") -> 75816.538 | R105: 0 | S105: 0 | T105: =H105-R105-S105 -> 80
B106: 45946 | C106: 1 | D106: =IFERROR(VLOOKUP(Trabajos!C106,Referencias!$E$7:$F$30,2,FALSE),"") -> Muestreo de suelos | E106: 33 | F106: =IFERROR(VLOOKUP(Trabajos!$E106,Clientes,2,FALSE),"") -> Espartina S.A. | G106: El Casalito | H106: 80 | I106: 947.70673 | J106: =IF(H106<>"",H106*I106,"") -> 75816.538 | K106: 3 | L106: =IFERROR(VLOOKUP(K106,Referencias!$H$7:$I$9,2,FALSE),"") -> Zoom | M106: 0 | N106: 588 | O106: =IF(M106<>"",M106*N106,"") -> 0 | P106: =IF(J106<>"",J106+O106,"") -> 75816.538 | R106: 0 | S106: 0 | T106: =H106-R106-S106 -> 80
B107: 45946 | C107: 1 | D107: =IFERROR(VLOOKUP(Trabajos!C107,Referencias!$E$7:$F$30,2,FALSE),"") -> Muestreo de suelos | E107: 33 | F107: =IFERROR(VLOOKUP(Trabajos!$E107,Clientes,2,FALSE),"") -> Espartina S.A. | G107: Aitona | H107: 80 | I107: 947.70673 | J107: =IF(H107<>"",H107*I107,"") -> 75816.538 | K107: 3 | L107: =IFERROR(VLOOKUP(K107,Referencias!$H$7:$I$9,2,FALSE),"") -> Zoom | M107: 0 | N107: 588 | O107: =IF(M107<>"",M107*N107,"") -> 0 | P107: =IF(J107<>"",J107+O107,"") -> 75816.538 | R107: 0 | S107: 0 | T107: =H107-R107-S107 -> 80
B108: 45946 | C108: 1 | D108: =IFERROR(VLOOKUP(Trabajos!C108,Referencias!$E$7:$F$30,2,FALSE),"") -> Muestreo de suelos | E108: 33 | F108: =IFERROR(VLOOKUP(Trabajos!$E108,Clientes,2,FALSE),"") -> Espartina S.A. | G108: Los Tulipanes | H108: 80 | I108: 947.70673 | J108: =IF(H108<>"",H108*I108,"") -> 75816.538 | K108: 3 | L108: =IFERROR(VLOOKUP(K108,Referencias!$H$7:$I$9,2,FALSE),"") -> Zoom | M108: 0 | N108: 588 | O108: =IF(M108<>"",M108*N108,"") -> 0 | P108: =IF(J108<>"",J108+O108,"") -> 75816.538 | R108: 0 | S108: 0 | T108: =H108-R108-S108 -> 80
B109: 45946 | C109: 2 | D109: =IFERROR(VLOOKUP(Trabajos!C109,Referencias!$E$7:$F$30,2,FALSE),"") -> Monitoreo de bb y bab | E109: 33 | F109: =IFERROR(VLOOKUP(Trabajos!$E109,Clientes,2,FALSE),"") -> Espartina S.A. | G109: El Montiel | H109: 276 | I109: 3262.5 | J109: =IF(H109<>"",H109*I109,"") -> 900450 | K109: 3 | L109: =IFERROR(VLOOKUP(K109,Referencias!$H$7:$I$9,2,FALSE),"") -> Zoom | M109: 398 | N109: 633.85 | O109: =IF(M109<>"",M109*N109,"") -> 252272.3 | P109: =IF(J109<>"",J109+O109,"") -> 1152722.3 | R109: 0 | S109: 0 | T109: =H109-R109-S109 -> 276
... B219: 45969 | C219: 3 | D219: =IFERROR(VLOOKUP(Trabajos!C219,Referencias!$E$7:$F$30,2,FALSE),"") -> Aplicación de cebos | E219: 72 | F219: =IFERROR(VLOOKUP(Trabajos!$E219,Clientes,2,FALSE),"") -> La Mylucha | G219: La Mylucha | H219: 54 | I219: 0 | J219: =IF(H219<>"",H219*I219,"") -> 0 | K219: 3 | L219: =IFERROR(VLOOKUP(K219,Referencias!$H$7:$I$9,2,FALSE),"") -> Zoom | M219: 40 | N219: 0 | O219: =IF(M219<>"",M219*N219,"") -> 0 | P219: =IF(J219<>"",J219+O219,"") -> 0 | R219: 0 | S219: 0 | T219: =H219-R219-S219 -> 54
B220: 45969 | C220: 2 | D220: =IFERROR(VLOOKUP(Trabajos!C220,Referencias!$E$7:$F$30,2,FALSE),"") -> Monitoreo de bb y bab | E220: 84 | F220: =IFERROR(VLOOKUP(Trabajos!$E220,Clientes,2,FALSE),"") -> Domingo y Nestor Scioli | G220: Gugliota | H220: 139 | I220: 3633.75 | J220: =IF(H220<>"",H220*I220,"") -> 505091.25 | K220: 3 | L220: =IFERROR(VLOOKUP(K220,Referencias!$H$7:$I$9,2,FALSE),"") -> Zoom | M220: 50 | N220: 650 | O220: =IF(M220<>"",M220*N220,"") -> 32500 | P220: =IF(J220<>"",J220+O220,"") -> 537591.25 | R220: 0 | S220: 0 | T220: 0
B221: 45969 | C221: 2 | D221: =IFERROR(VLOOKUP(Trabajos!C221,Referencias!$E$7:$F$30,2,FALSE),"") -> Monitoreo de bb y bab | E221: 72 | F221: =IFERROR(VLOOKUP(Trabajos!$E221,Clientes,2,FALSE),"") -> La Mylucha | G221: La Mylucha | H221: 60 | I221: 3628.75 | J221: =IF(H221<>"",H221*I221,"") -> 217725 | K221: 3 | L221: =IFERROR(VLOOKUP(K221,Referencias!$H$7:$I$9,2,FALSE),"") -> Zoom | M221: 40 | N221: 650 | O221: =IF(M221<>"",M221*N221,"") -> 26000 | P221: =IF(J221<>"",J221+O221,"") -> 243725 | R221: 0 | S221: 0 | T221: =H221-R221-S221 -> 60
B222: 45969 | C222: 2 | D222: =IFERROR(VLOOKUP(Trabajos!C222,Referencias!$E$7:$F$30,2,FALSE),"") -> Monitoreo de bb y bab | E222: 37 | F222: =IFERROR(VLOOKUP(Trabajos!$E222,Clientes,2,FALSE),"") -> Sebastian Martos | G222: Fasciglione | H222: 26 | I222: 3628.75 | J222: =IF(H222<>"",H222*I222,"") -> 94347.5 | K222: 3 | L222: =IFERROR(VLOOKUP(K222,Referencias!$H$7:$I$9,2,FALSE),"") -> Zoom | M222: 24 | N222: 650 | O222: =IF(M222<>"",M222*N222,"") -> 15600 | P222: =IF(J222<>"",J222+O222,"") -> 109947.5 | R222: 0 | S222: 0 | T222: =H222-R222-S222 -> 26
B223: 45969 | C223: 2 | D223: =IFERROR(VLOOKUP(Trabajos!C223,Referencias!$E$7:$F$30,2,FALSE),"") -> Monitoreo de bb y bab | E223: 90 | F223: =IFERROR(VLOOKUP(Trabajos!$E223,Clientes,2,FALSE),"") -> Walter Ingenieri | G223: El Rosario | H223: 70 | I223: 3675 | J223: =IF(H223<>"",H223*I223,"") -> 257250 | K223: 3 | L223: =IFERROR(VLOOKUP(K223,Referencias!$H$7:$I$9,2,FALSE),"") -> Zoom | M223: 59 | N223: 650 | O223: =IF(M223<>"",M223*N223,"") -> 38350 | P223: =IF(J223<>"",J223+O223,"") -> 295600 | R223: 0 | S223: 0 | T223: =H223-R223-S223 -> 70
B224: 45969 | C224: 2 | D224: =IFERROR(VLOOKUP(Trabajos!C224,Referencias!$E$7:$F$30,2,FALSE),"") -> Monitoreo de bb y bab | E224: 37 | F224: =IFERROR(VLOOKUP(Trabajos!$E224,Clientes,2,FALSE),"") -> Sebastian Martos | G224: Las Nazarenas | H224: 115 | I224: 3628.75 | J224: =IF(H224<>"",H224*I224,"") -> 417306.25 | K224: 3 | L224: =IFERROR(VLOOKUP(K224,Referencias!$H$7:$I$9,2,FALSE),"") -> Zoom | M224: 64 | N224: 650 | O224: =IF(M224<>"",M224*N224,"") -> 41600 | P224: =IF(J224<>"",J224+O224,"") -> 458906.25 | R224: 0 | S224: 0 | T224: =H224-R224-S224 -> 115
B225: 45969 | C225: 2 | D225: =IFERROR(VLOOKUP(Trabajos!C225,Referencias!$E$7:$F$30,2,FALSE),"") -> Monitoreo de bb y bab | E225: 124 | F225: =IFERROR(VLOOKUP(Trabajos!$E225,Clientes,2,FALSE),"") -> Cristian Perez Maraviglia | G225: San Guillermo | H225: 59 | I225: 3467.5 | J225: =IF(H225<>"",H225*I225,"") -> 204582.5 | K225: 3 | L225: =IFERROR(VLOOKUP(K225,Referencias!$H$7:$I$9,2,FALSE),"") -> Zoom | M225: 90 | N225: 650 | O225: =IF(M225<>"",M225*N225,"") -> 58500 | P225: =IF(J225<>"",J225+O225,"") -> 263082.5 | R225: 0 | S225: 0 | T225: =H225-R225-S225 -> 59
B226: 45970 | C226: 3 | D226: =IFERROR(VLOOKUP(Trabajos!C226,Referencias!$E$7:$F$30,2,FALSE),"") -> Aplicación de cebos | E226: 33 | F226: =IFERROR(VLOOKUP(Trabajos!$E226,Clientes,2,FALSE),"") -> Espartina S.A. | G226: La Cachila | H226: 60 | I226: 7250 | J226: =IF(H226<>"",H226*I226,"") -> 435000 | K226: 2 | L226: =IFERROR(VLOOKUP(K226,Referencias!$H$7:$I$9,2,FALSE),"") -> Paco | M226: 230 | N226: 633.85 | O226: =IF(M226<>"",M226*N226,"") -> 145785.5 | P226: =IF(J226<>"",J226+O226,"") -> 580785.5 | R226: 60 | S226: 0 | T226: =H226-R226-S226 -> 0
B227: 45970 | C227: 3 | D227: =IFERROR(VLOOKUP(Trabajos!C227,Referencias!$E$7:$F$30,2,FALSE),"") -> Aplicación de cebos | E227: 33 | F227: =IFERROR(VLOOKUP(Trabajos!$E227,Clientes,2,FALSE),"") -> Espartina S.A. | G227: Las Overas | H227: 37 | I227: 7250 | J227: =IF(H227<>"",H227*I227,"") -> 268250 | K227: 2 | L227: =IFERROR(VLOOKUP(K227,Referencias!$H$7:$I$9,2,FALSE),"") -> Paco | M227: 236 | N227: 633.85 | O227: =IF(M227<>"",M227*N227,"") -> 149588.6 | P227: =IF(J227<>"",J227+O227,"") -> 417838.6 | R227: 20 | S227: 0 | T227: =H227-R227-S227 -> 17
B228: 45969 | C228: 3 | D228: =IFERROR(VLOOKUP(Trabajos!C228,Referencias!$E$7:$F$30,2,FALSE),"") -> Aplicación de cebos | E228: 33 | F228: =IFERROR(VLOOKUP(Trabajos!$E228,Clientes,2,FALSE),"") -> Espartina S.A. | G228: San Narciso | H228: 100 | I228: 7267.5 | J228: =IF(H228<>"",H228*I228,"") -> 726750 | K228: 1 | L228: =IFERROR(VLOOKUP(K228,Referencias!$H$7:$I$9,2,FALSE),"") -> Tomas | M228: 208 | N228: 633.85 | O228: =IF(M228<>"",M228*N228,"") -> 131840.8 | P228: =IF(J228<>"",J228+O228,"") -> 858590.8 | R228: 0 | S228: 80 | T228: =H228-R228-S228 -> 20
B229: 45970 | C229: 3 | D229: =IFERROR(VLOOKUP(Trabajos!C229,Referencias!$E$7:$F$30,2,FALSE),"") -> Aplicación de cebos | E229: 40 | F229: =IFERROR(VLOOKUP(Trabajos!$E229,Clientes,2,FALSE),"") -> Cía. de Tierras Sud Argentino S.A. | G229: Santa Marta | H229: 40 | I229: 7267.5 | J229: =IF(H229<>"",H229*I229,"") -> 290700 | K229: 3 | L229: =IFERROR(VLOOKUP(K229,Referencias!$H$7:$I$9,2,FALSE),"") -> Zoom | M229: 50 | N229: 650 | O229: =IF(M229<>"",M229*N229,"") -> 32500 | P229: =IF(J229<>"",J229+O229,"") -> 323200 | R229: 0 | S229: 0 | T229: =H229-R229-S229 -> 40
B230: 45970 | C230: 3 | D230: =IFERROR(VLOOKUP(Trabajos!C230,Referencias!$E$7:$F$30,2,FALSE),"") -> Aplicación de cebos | E230: 33 | F230: =IFERROR(VLOOKUP(Trabajos!$E230,Clientes,2,FALSE),"") -> Espartina S.A. | G230: San Narciso | H230: 120 | I230: 7267.5 | J230: =IF(H230<>"",H230*I230,"") -> 872100 | K230: 3 | L230: =IFERROR(VLOOKUP(K230,Referencias!$H$7:$I$9,2,FALSE),"") -> Zoom | M230: 208 | N230: 633.85 | O230: =IF(M230<>"",M230*N230,"") -> 131840.8 | P230: =IF(J230<>"",J230+O230,"") -> 1003940.8 | R230: 0 | S230: 0 | T230: 0
B231: 45970 | C231: 2 | D231: =IFERROR(VLOOKUP(Trabajos!C231,Referencias!$E$7:$F$30,2,FALSE),"") -> Monitoreo de bb y bab | E231: 21 | F231: =IFERROR(VLOOKUP(Trabajos!$E231,Clientes,2,FALSE),"") -> Piray Mini | G231: Las Mercedes | H231: 250 | I231: 3628.75 | J231: =IF(H231<>"",H231*I231,"") -> 907187.5 | K231: 3 | L231: =IFERROR(VLOOKUP(K231,Referencias!$H$7:$I$9,2,FALSE),"") -> Zoom | M231: 72 | N231: 650 | O231: =IF(M231<>"",M231*N231,"") -> 46800 | P231: =IF(J231<>"",J231+O231,"") -> 953987.5 | R231: 0 | S231: 0 | T231: =H231-R231-S231 -> 250
B232: 45971 | C232: 3 | D232: =IFERROR(VLOOKUP(Trabajos!C232,Referencias!$E$7:$F$30,2,FALSE),"") -> Aplicación de cebos | E232: 33 | F232: =IFERROR(VLOOKUP(Trabajos!$E232,Clientes,2,FALSE),"") -> Espartina S.A. | G232: La Trinidad | H232: 110 | I232: 7250 | J232: =IF(H232<>"",H232*I232,"") -> 797500 | K232: 2 | L232: =IFERROR(VLOOKUP(K232,Referencias!$H$7:$I$9,2,FALSE),"") -> Paco | M232: 164 | N232: 633.85 | O232: =IF(M232<>"",M232*N232,"") -> 103951.4 | P232: =IF(J232<>"",J232+O232,"") -> 901451.4 | R232: 80 | S232: 0 | T232: =H232-R232-S232 -> 30
B233: 45971 | C233: 3 | D233: =IFERROR(VLOOKUP(Trabajos!C233,Referencias!$E$7:$F$30,2,FALSE),"") -> Aplicación de cebos | E233: 33 | F233: =IFERROR(VLOOKUP(Trabajos!$E233,Clientes,2,FALSE),"") -> Espartina S.A. | G233: La Magdalena | H233: 121 | I233: 7267.5 | J233: =IF(H233<>"",H233*I233,"") -> 879367.5 | K233: 1 | L233: =IFERROR(VLOOKUP(K233,Referencias!$H$7:$I$9,2,FALSE),"") -> Tomas | M233: 117 | N233: 633.85 | O233: =IF(M233<>"",M233*N233,"") -> 74160.45 | P233: =IF(J233<>"",J233+O233,"") -> 953527.95 | R233: 0 | S233: 80 | T233: =H233-R233-S233 -> 41
B234: 45971 | C234: 2 | D234: =IFERROR(VLOOKUP(Trabajos!C234,Referencias!$E$7:$F$30,2,FALSE),"") -> Monitoreo de bb y bab | E234: 33 | F234: =IFERROR(VLOOKUP(Trabajos!$E234,Clientes,2,FALSE),"") -> Espartina S.A. | G234: Loma Blanca | H234: 220 | I234: 3262.5 | J234: =IF(H234<>"",H234*I234,"") -> 717750 | K234: 3 | L234: =IFERROR(VLOOKUP(K234,Referencias!$H$7:$I$9,2,FALSE),"") -> Zoom | M234: 328 | N234: 633.85 | O234: =IF(M234<>"",M234*N234,"") -> 207902.8 | P234: =IF(J234<>"",J234+O234,"") -> 925652.8 | R234: 0 | S234: 0 | T234: =H234-R234-S234 -> 220
B235: 45971 | C235: 2 | D235: =IFERROR(VLOOKUP(Trabajos!C235,Referencias!$E$7:$F$30,2,FALSE),"") -> Monitoreo de bb y bab | E235: 33 | F235: =IFERROR(VLOOKUP(Trabajos!$E235,Clientes,2,FALSE),"") -> Espartina S.A. | G235: Loma Blanca | H235: 180 | I235: 3262.5 | J235: =IF(H235<>"",H235*I235,"") -> 587250 | K235: 3 | L235: =IFERROR(VLOOKUP(K235,Referencias!$H$7:$I$9,2,FALSE),"") -> Zoom | M235: 328 | N235: 633.85 | O235: =IF(M235<>"",M235*N235,"") -> 207902.8 | P235: =IF(J235<>"",J235+O235,"") -> 795152.8 | R235: 0 | S235: 0 | T235: =H235-R235-S235 -> 180
B236: 45972 | C236: 2 | D236: =IFERROR(VLOOKUP(Trabajos!C236,Referencias!$E$7:$F$30,2,FALSE),"") -> Monitoreo de bb y bab | E236: 33 | F236: =IFERROR(VLOOKUP(Trabajos!$E236,Clientes,2,FALSE),"") -> Espartina S.A. | G236: Mallinco | H236: 108 | I236: 3262.5 | J236: =IF(H236<>"",H236*I236,"") -> 352350 | K236: 2 | L236: =IFERROR(VLOOKUP(K236,Referencias!$H$7:$I$9,2,FALSE),"") -> Paco | M236: 186 | N236: 633.85 | O236: =IF(M236<>"",M236*N236,"") -> 117896.1 | P236: =IF(J236<>"",J236+O236,"") -> 470246.1 | R236: 54 | S236: 0 | T236: =H236-R236-S236 -> 54
B237: 45972 | C237: 3 | D237: =IFERROR(VLOOKUP(Trabajos!C237,Referencias!$E$7:$F$30,2,FALSE),"") -> Aplicación de cebos | E237: 72 | F237: =IFERROR(VLOOKUP(Trabajos!$E237,Clientes,2,FALSE),"") -> La Mylucha | G237: La Mylucha | H237: 22 | I237: 7257.5 | J237: =IF(H237<>"",H237*I237,"") -> 159665 | K237: 1 | L237: =IFERROR(VLOOKUP(K237,Referencias!$H$7:$I$9,2,FALSE),"") -> Tomas | M237: 40 | N237: 650 | O237: =IF(M237<>"",M237*N237,"") -> 26000 | P237: =IF(J237<>"",J237+O237,"") -> 185665 | R237: 0 | S237: 22 | T237: =H237-R237-S237 -> 0
B238: 45972 | C238: 2 | D238: =IFERROR(VLOOKUP(Trabajos!C238,Referencias!$E$7:$F$30,2,FALSE),"") -> Monitoreo de bb y bab | E238: 125 | F238: =IFERROR(VLOOKUP(Trabajos!$E238,Clientes,2,FALSE),"") -> Soledad Gutierrez | G238: El Pensamiento | H238: 96 | I238: 3500 | J238: =IF(H238<>"",H238*I238,"") -> 336000 | K238: 3 | L238: =IFERROR(VLOOKUP(K238,Referencias!$H$7:$I$9,2,FALSE),"") -> Zoom | M238: 104 | N238: 650 | O238: =IF(M238<>"",M238*N238,"") -> 67600 | P238: =IF(J238<>"",J238+O238,"") -> 403600 | R238: 0 | S238: 0 | T238: =H238-R238-S238 -> 96
B239: 45972 | C239: 2 | D239: =IFERROR(VLOOKUP(Trabajos!C239,Referencias!$E$7:$F$30,2,FALSE),"") -> Monitoreo de bb y bab | E239: 125 | F239: =IFERROR(VLOOKUP(Trabajos!$E239,Clientes,2,FALSE),"") -> Soledad Gutierrez | G239: El Verano | H239: 52 | I239: 3500 | J239: =IF(H239<>"",H239*I239,"") -> 182000 | K239: 3 | L239: =IFERROR(VLOOKUP(K239,Referencias!$H$7:$I$9,2,FALSE),"") -> Zoom | M239: 0 | N239: 650 | O239: =IF(M239<>"",M239*N239,"") -> 0 | P239: =IF(J239<>"",J239+O239,"") -> 182000 | R239: 0 | S239: 0 | T239: =H239-R239-S239 -> 52
B240: 45972 | C240: 2 | D240: =IFERROR(VLOOKUP(Trabajos!C240,Referencias!$E$7:$F$30,2,FALSE),"") -> Monitoreo de bb y bab | E240: 37 | F240: =IFERROR(VLOOKUP(Trabajos!$E240,Clientes,2,FALSE),"") -> Sebastian Martos | G240: La Colonia | H240: 73 | I240: 3628.75 | J240: =IF(H240<>"",H240*I240,"") -> 264898.75 | K240: 3 | L240: =IFERROR(VLOOKUP(K240,Referencias!$H$7:$I$9,2,FALSE),"") -> Zoom | M240: 28 | N240: 650 | O240: =IF(M240<>"",M240*N240,"") -> 18200 | P240: =IF(J240<>"",J240+O240,"") -> 283098.75 | R240: 0 | S240: 0 | T240: =H240-R240-S240 -> 73
B241: 45973 | C241: 3 | D241: =IFERROR(VLOOKUP(Trabajos!C241,Referencias!$E$7:$F$30,2,FALSE),"") -> Aplicación de cebos | E241: 119 | F241: =IFERROR(VLOOKUP(Trabajos!$E241,Clientes,2,FALSE),"") -> Juan Rodriguez Rivas | G241: San Agustin | H241: 195 | I241: 7032.5 | J241: =IF(H241<>"",H241*I241,"") -> 1371337.5 | K241: 2 | L241: =IFERROR(VLOOKUP(K241,Referencias!$H$7:$I$9,2,FALSE),"") -> Paco | M241: 246 | N241: 650 | O241: =IF(M241<>"",M241*N241,"") -> 159900 | P241: =IF(J241<>"",J241+O241,"") -> 1531237.5 | R241: 80 | S241: 0 | T241: =H241-R241-S241 -> 115
B242: 45973 | C242: 3 | D242: =IFERROR(VLOOKUP(Trabajos!C242,Referencias!$E$7:$F$30,2,FALSE),"") -> Aplicación de cebos | E242: 37 | F242: =IFERROR(VLOOKUP(Trabajos!$E242,Clientes,2,FALSE),"") -> Sebastian Martos | G242: Fasciglione | H242: 26 | I242: 7257.5 | J242: =IF(H242<>"",H242*I242,"") -> 188695 | K242: 1 | L242: =IFERROR(VLOOKUP(K242,Referencias!$H$7:$I$9,2,FALSE),"") -> Tomas | M242: 24 | N242: 650 | O242: =IF(M242<>"",M242*N242,"") -> 15600 | P242: =IF(J242<>"",J242+O242,"") -> 204295 | R242: 0 | S242: 24 | T242: =H242-R242-S242 -> 2
... B328: 46171 | C328: 1 | D328: =IFERROR(VLOOKUP(Trabajos!C328,Referencias!$E$7:$F$30,2,FALSE),"") -> Muestreo de suelos | E328: 33 | F328: =IFERROR(VLOOKUP(Trabajos!$E328,Clientes,2,FALSE),"") -> Espartina S.A. | G328: Las Overas | H328: 80 | I328: 1854.0556 | J328: =IF(H328<>"",H328*I328,"") -> 148324.44 | K328: 1 | L328: =IFERROR(VLOOKUP(K328,Referencias!$H$7:$I$9,2,FALSE),"") -> Tomas | M328: 0 | N328: 711.6 | O328: =IF(M328<>"",M328*N328,"") -> 0 | P328: =IF(J328<>"",J328+O328,"") -> 148324.44 | R328: 0 | S328: 80 | T328: =H328-R328-S328 -> 0
B329: 46173 | C329: 8 | D329: =IFERROR(VLOOKUP(Trabajos!C329,Referencias!$E$7:$F$30,2,FALSE),"") -> Seguimiento NDVI | E329: 45 | F329: =IFERROR(VLOOKUP(Trabajos!$E329,Clientes,2,FALSE),"") -> Guillermo Pugliese | G329: Varios | H329: 10149 | I329: 422.4 | J329: =IF(H329<>"",H329*I329,"") -> 4286937.6 | K329: 3 | L329: =IFERROR(VLOOKUP(K329,Referencias!$H$7:$I$9,2,FALSE),"") -> Zoom | M329: 0 | N329: 850 | O329: =IF(M329<>"",M329*N329,"") -> 0 | P329: =IF(J329<>"",J329+O329,"") -> 4286937.6 | R329: 0 | S329: 0 | T329: 0
B330: 46175 | C330: 1 | D330: =IFERROR(VLOOKUP(Trabajos!C330,Referencias!$E$7:$F$30,2,FALSE),"") -> Muestreo de suelos | E330: 33 | F330: =IFERROR(VLOOKUP(Trabajos!$E330,Clientes,2,FALSE),"") -> Espartina S.A. | G330: Las Overas | H330: 80 | I330: 1854.0556 | J330: =IF(H330<>"",H330*I330,"") -> 148324.44 | K330: 1 | L330: =IFERROR(VLOOKUP(K330,Referencias!$H$7:$I$9,2,FALSE),"") -> Tomas | M330: 236 | N330: 711.6 | O330: =IF(M330<>"",M330*N330,"") -> 167937.6 | P330: =IF(J330<>"",J330+O330,"") -> 316262.04 | R330: 0 | S330: 80 | T330: =H330-R330-S330 -> 0
B331: 46175 | C331: 1 | D331: =IFERROR(VLOOKUP(Trabajos!C331,Referencias!$E$7:$F$30,2,FALSE),"") -> Muestreo de suelos | E331: 33 | F331: =IFERROR(VLOOKUP(Trabajos!$E331,Clientes,2,FALSE),"") -> Espartina S.A. | G331: Doña Hilda | H331: 80 | I331: 1854.0556 | J331: =IF(H331<>"",H331*I331,"") -> 148324.44 | K331: 1 | L331: =IFERROR(VLOOKUP(K331,Referencias!$H$7:$I$9,2,FALSE),"") -> Tomas | M331: 202 | N331: 711.6 | O331: =IF(M331<>"",M331*N331,"") -> 143743.2 | P331: =IF(J331<>"",J331+O331,"") -> 292067.64 | R331: 0 | S331: 0 | T331: =H331-R331-S331 -> 80
B332: 46175 | C332: 1 | D332: =IFERROR(VLOOKUP(Trabajos!C332,Referencias!$E$7:$F$30,2,FALSE),"") -> Muestreo de suelos | E332: 33 | F332: =IFERROR(VLOOKUP(Trabajos!$E332,Clientes,2,FALSE),"") -> Espartina S.A. | G332: San Lorenzo | H332: 80 | I332: 1854.0556 | J332: =IF(H332<>"",H332*I332,"") -> 148324.44 | K332: 1 | L332: =IFERROR(VLOOKUP(K332,Referencias!$H$7:$I$9,2,FALSE),"") -> Tomas | M332: 0 | N332: 711.6 | O332: =IF(M332<>"",M332*N332,"") -> 0 | P332: =IF(J332<>"",J332+O332,"") -> 148324.44 | R332: 0 | S332: 0 | T332: =H332-R332-S332 -> 80
B333: 46175 | C333: 1 | D333: =IFERROR(VLOOKUP(Trabajos!C333,Referencias!$E$7:$F$30,2,FALSE),"") -> Muestreo de suelos | E333: 33 | F333: =IFERROR(VLOOKUP(Trabajos!$E333,Clientes,2,FALSE),"") -> Espartina S.A. | G333: Mallinco | H333: 80 | I333: 1854.0556 | J333: =IF(H333<>"",H333*I333,"") -> 148324.44 | K333: 2 | L333: =IFERROR(VLOOKUP(K333,Referencias!$H$7:$I$9,2,FALSE),"") -> Paco | M333: 186 | N333: 711.6 | O333: =IF(M333<>"",M333*N333,"") -> 132357.6 | P333: =IF(J333<>"",J333+O333,"") -> 280682.04 | R333: 80 | S333: 0 | T333: =H333-R333-S333 -> 0
B334: 46175 | C334: 1 | D334: =IFERROR(VLOOKUP(Trabajos!C334,Referencias!$E$7:$F$30,2,FALSE),"") -> Muestreo de suelos | E334: 33 | F334: =IFERROR(VLOOKUP(Trabajos!$E334,Clientes,2,FALSE),"") -> Espartina S.A. | G334: Santa Isabel | H334: 80 | I334: 1854.0556 | J334: =IF(H334<>"",H334*I334,"") -> 148324.44 | K334: 2 | L334: =IFERROR(VLOOKUP(K334,Referencias!$H$7:$I$9,2,FALSE),"") -> Paco | M334: 0 | N334: 711.6 | O334: =IF(M334<>"",M334*N334,"") -> 0 | P334: =IF(J334<>"",J334+O334,"") -> 148324.44 | R334: 0 | S334: 0 | T334: =H334-R334-S334 -> 80
B335: 46176 | C335: 1 | D335: =IFERROR(VLOOKUP(Trabajos!C335,Referencias!$E$7:$F$30,2,FALSE),"") -> Muestreo de suelos | E335: 33 | F335: =IFERROR(VLOOKUP(Trabajos!$E335,Clientes,2,FALSE),"") -> Espartina S.A. | G335: Tres Marias | H335: 80 | I335: 1854.0556 | J335: =IF(H335<>"",H335*I335,"") -> 148324.44 | K335: 2 | L335: =IFERROR(VLOOKUP(K335,Referencias!$H$7:$I$9,2,FALSE),"") -> Paco | M335: 210 | N335: 711.6 | O335: =IF(M335<>"",M335*N335,"") -> 149436 | P335: =IF(J335<>"",J335+O335,"") -> 297760.44 | R335: 80 | S335: 0 | T335: =H335-R335-S335 -> 0
B336: 46176 | C336: 1 | D336: =IFERROR(VLOOKUP(Trabajos!C336,Referencias!$E$7:$F$30,2,FALSE),"") -> Muestreo de suelos | E336: 8 | F336: =IFERROR(VLOOKUP(Trabajos!$E336,Clientes,2,FALSE),"") -> Baltan Agropecuaria | G336: Tres Esquinas | H336: 39 | I336: 1440.5 | J336: =IF(H336<>"",H336*I336,"") -> 56179.5 | K336: 1 | L336: =IFERROR(VLOOKUP(K336,Referencias!$H$7:$I$9,2,FALSE),"") -> Tomas | M336: 36 | N336: 850 | O336: =IF(M336<>"",M336*N336,"") -> 30600 | P336: =IF(J336<>"",J336+O336,"") -> 86779.5 | R336: 0 | S336: 39 | T336: =H336-R336-S336 -> 0
B337: 46167 | C337: 1 | D337: =IFERROR(VLOOKUP(Trabajos!C337,Referencias!$E$7:$F$30,2,FALSE),"") -> Muestreo de suelos | E337: 69 | F337: =IFERROR(VLOOKUP(Trabajos!$E337,Clientes,2,FALSE),"") -> Alejandro Massigoge | G337: La Chacra | H337: 214 | I337: 1446.5 | J337: =IF(H337<>"",H337*I337,"") -> 309551 | K337: 2 | L337: =IFERROR(VLOOKUP(K337,Referencias!$H$7:$I$9,2,FALSE),"") -> Paco | M337: 0 | N337: 850 | O337: =IF(M337<>"",M337*N337,"") -> 0 | P337: =IF(J337<>"",J337+O337,"") -> 309551 | R337: 80 | S337: 0 | T337: =H337-R337-S337 -> 134
B338: 46184 | C338: 10 | D338: =IFERROR(VLOOKUP(Trabajos!C338,Referencias!$E$7:$F$30,2,FALSE),"") -> Mapeo Dron | E338: 4 | F338: =IFERROR(VLOOKUP(Trabajos!$E338,Clientes,2,FALSE),"") -> Purtierra | G338: Ojo de Agua | H338: 137 | I338: 4431 | J338: =IF(H338<>"",H338*I338,"") -> 607047 | K338: 1 | L338: =IFERROR(VLOOKUP(K338,Referencias!$H$7:$I$9,2,FALSE),"") -> Tomas | M338: 92 | N338: 850 | O338: =IF(M338<>"",M338*N338,"") -> 78200 | P338: =IF(J338<>"",J338+O338,"") -> 685247 | R338: 0 | S338: 80 | T338: =H338-R338-S338 -> 57
B339: 46185 | C339: 1 | D339: =IFERROR(VLOOKUP(Trabajos!C339,Referencias!$E$7:$F$30,2,FALSE),"") -> Muestreo de suelos | E339: 24 | F339: =IFERROR(VLOOKUP(Trabajos!$E339,Clientes,2,FALSE),"") -> Nugas S.A. | G339: La Alborada | H339: 124 | I339: 1786.2 | J339: =IF(H339<>"",H339*I339,"") -> 221488.8 | K339: 1 | L339: =IFERROR(VLOOKUP(K339,Referencias!$H$7:$I$9,2,FALSE),"") -> Tomas | M339: 160 | N339: 850 | O339: =IF(M339<>"",M339*N339,"") -> 136000 | P339: =IF(J339<>"",J339+O339,"") -> 357488.8 | R339: 0 | S339: 80 | T339: =H339-R339-S339 -> 44
B340: 46185 | C340: 1 | D340: =IFERROR(VLOOKUP(Trabajos!C340,Referencias!$E$7:$F$30,2,FALSE),"") -> Muestreo de suelos | E340: 24 | F340: =IFERROR(VLOOKUP(Trabajos!$E340,Clientes,2,FALSE),"") -> Nugas S.A. | G340: La Alborada | H340: 105 | I340: 1190.8 | J340: =IF(H340<>"",H340*I340,"") -> 125034 | K340: 1 | L340: =IFERROR(VLOOKUP(K340,Referencias!$H$7:$I$9,2,FALSE),"") -> Tomas | M340: 0 | N340: 850 | O340: =IF(M340<>"",M340*N340,"") -> 0 | P340: =IF(J340<>"",J340+O340,"") -> 125034 | R340: 0 | S340: 0 | T340: =H340-R340-S340 -> 105
B341: 46185 | C341: 1 | D341: =IFERROR(VLOOKUP(Trabajos!C341,Referencias!$E$7:$F$30,2,FALSE),"") -> Muestreo de suelos | E341: 91 | F341: =IFERROR(VLOOKUP(Trabajos!$E341,Clientes,2,FALSE),"") -> Alfredo Hitce | G341: Tres Lomas | H341: 99 | I341: 1488 | J341: =IF(H341<>"",H341*I341,"") -> 147312 | K341: 1 | L341: =IFERROR(VLOOKUP(K341,Referencias!$H$7:$I$9,2,FALSE),"") -> Tomas | M341: 136 | N341: 850 | O341: =IF(M341<>"",M341*N341,"") -> 115600 | P341: =IF(J341<>"",J341+O341,"") -> 262912 | R341: 0 | S341: 0 | T341: =H341-R341-S341 -> 99
... B363: 46213 | C363: 1 | D363: =IFERROR(VLOOKUP(Trabajos!C363,Referencias!$E$7:$F$30,2,FALSE),"") -> Muestreo de suelos | E363: 132 | F363: =IFERROR(VLOOKUP(Trabajos!$E363,Clientes,2,FALSE),"") -> Tres Mil Tres S.A. | G363: Tres Mil Tres | H363: 225 | I363: 1482 | J363: =IF(H363<>"",H363*I363,"") -> 333450 | K363: 1 | L363: =IFERROR(VLOOKUP(K363,Referencias!$H$7:$I$9,2,FALSE),"") -> Tomas | M363: 31 | N363: 850 | O363: =IF(M363<>"",M363*N363,"") -> 26350 | P363: =IF(J363<>"",J363+O363,"") -> 359800 | R363: 0 | S363: 80 | T363: =H363-R363-S363 -> 145
B364: 46225 | C364: 8 | D364: =IFERROR(VLOOKUP(Trabajos!C364,Referencias!$E$7:$F$30,2,FALSE),"") -> Seguimiento NDVI | E364: 82 | F364: =IFERROR(VLOOKUP(Trabajos!$E364,Clientes,2,FALSE),"") -> Cristian Rybner | G364: Varios | H364: 650 | I364: 729.19 | J364: =IF(H364<>"",H364*I364,"") -> 473973.5 | K364: 3 | L364: =IFERROR(VLOOKUP(K364,Referencias!$H$7:$I$9,2,FALSE),"") -> Zoom | M364: 0 | N364: 850 | O364: =IF(M364<>"",M364*N364,"") -> 0 | P364: =IF(J364<>"",J364+O364,"") -> 473973.5 | R364: 0 | S364: 0 | T364: 0
B365: 46225 | C365: 1 | D365: =IFERROR(VLOOKUP(Trabajos!C365,Referencias!$E$7:$F$30,2,FALSE),"") -> Muestreo de suelos | E365: 33 | F365: =IFERROR(VLOOKUP(Trabajos!$E365,Clientes,2,FALSE),"") -> Espartina S.A. | G365: Trauco | H365: 80 | I365: 0 | J365: =IF(H365<>"",H365*I365,"") -> 0 | K365: 1 | L365: =IFERROR(VLOOKUP(K365,Referencias!$H$7:$I$9,2,FALSE),"") -> Tomas | M365: 180 | N365: 716.7 | O365: =IF(M365<>"",M365*N365,"") -> 129006 | P365: =IF(J365<>"",J365+O365,"") -> 129006 | R365: 0 | S365: 80 | T365: =H365-R365-S365 -> 0
B366: 46226 | C366: 1 | D366: =IFERROR(VLOOKUP(Trabajos!C366,Referencias!$E$7:$F$30,2,FALSE),"") -> Muestreo de suelos | E366: 33 | F366: =IFERROR(VLOOKUP(Trabajos!$E366,Clientes,2,FALSE),"") -> Espartina S.A. | G366: Doña Hilda | H366: 80 | I366: 0 | J366: =IF(H366<>"",H366*I366,"") -> 0 | K366: 1 | L366: =IFERROR(VLOOKUP(K366,Referencias!$H$7:$I$9,2,FALSE),"") -> Tomas | M366: 260 | N366: 716.7 | O366: =IF(M366<>"",M366*N366,"") -> 186342 | P366: =IF(J366<>"",J366+O366,"") -> 186342 | R366: 0 | S366: 0 | T366: =H366-R366-S366 -> 80
B367: 46226 | C367: 1 | D367: =IFERROR(VLOOKUP(Trabajos!C367,Referencias!$E$7:$F$30,2,FALSE),"") -> Muestreo de suelos | E367: 33 | F367: =IFERROR(VLOOKUP(Trabajos!$E367,Clientes,2,FALSE),"") -> Espartina S.A. | G367: Las Overas | H367: 80 | I367: 0 | J367: =IF(H367<>"",H367*I367,"") -> 0 | K367: 1 | L367: =IFERROR(VLOOKUP(K367,Referencias!$H$7:$I$9,2,FALSE),"") -> Tomas | M367: 0 | N367: 716.7 | O367: =IF(M367<>"",M367*N367,"") -> 0 | P367: =IF(J367<>"",J367+O367,"") -> 0 | R367: 0 | S367: 0 | T367: =H367-R367-S367 -> 80
D368: =IFERROR(VLOOKUP(Trabajos!C368,Referencias!$E$7:$F$30,2,FALSE),"") | F368: =IFERROR(VLOOKUP(Trabajos!$E368,Clientes,2,FALSE),"") | J368: =IF(H368<>"",H368*I368,"") | L368: =IFERROR(VLOOKUP(K368,Referencias!$H$7:$I$9,2,FALSE),"") | O368: =IF(M368<>"",M368*N368,"") | P368: =IF(J368<>"",J368+O368,"")
D369: =IFERROR(VLOOKUP(Trabajos!C369,Referencias!$E$7:$F$30,2,FALSE),"") | F369: =IFERROR(VLOOKUP(Trabajos!$E369,Clientes,2,FALSE),"") | J369: =IF(H369<>"",H369*I369,"") | L369: =IFERROR(VLOOKUP(K369,Referencias!$H$7:$I$9,2,FALSE),"") | O369: =IF(M369<>"",M369*N369,"") | P369: =IF(J369<>"",J369+O369,"")
D370: =IFERROR(VLOOKUP(Trabajos!C370,Referencias!$E$7:$F$30,2,FALSE),"") | F370: =IFERROR(VLOOKUP(Trabajos!$E370,Clientes,2,FALSE),"") | J370: =IF(H370<>"",H370*I370,"") | L370: =IFERROR(VLOOKUP(K370,Referencias!$H$7:$I$9,2,FALSE),"") | O370: =IF(M370<>"",M370*N370,"") | P370: =IF(J370<>"",J370+O370,"")
D371: =IFERROR(VLOOKUP(Trabajos!C371,Referencias!$E$7:$F$30,2,FALSE),"") | F371: =IFERROR(VLOOKUP(Trabajos!$E371,Clientes,2,FALSE),"") | J371: =IF(H371<>"",H371*I371,"") | L371: =IFERROR(VLOOKUP(K371,Referencias!$H$7:$I$9,2,FALSE),"") | O371: =IF(M371<>"",M371*N371,"") | P371: =IF(J371<>"",J371+O371,"")
D372: =IFERROR(VLOOKUP(Trabajos!C372,Referencias!$E$7:$F$30,2,FALSE),"") | F372: =IFERROR(VLOOKUP(Trabajos!$E372,Clientes,2,FALSE),"") | J372: =IF(H372<>"",H372*I372,"") | L372: =IFERROR(VLOOKUP(K372,Referencias!$H$7:$I$9,2,FALSE),"") | O372: =IF(M372<>"",M372*N372,"") | P372: =IF(J372<>"",J372+O372,"")
D373: =IFERROR(VLOOKUP(Trabajos!C373,Referencias!$E$7:$F$30,2,FALSE),"") | F373: =IFERROR(VLOOKUP(Trabajos!$E373,Clientes,2,FALSE),"") | J373: =IF(H373<>"",H373*I373,"") | L373: =IFERROR(VLOOKUP(K373,Referencias!$H$7:$I$9,2,FALSE),"") | O373: =IF(M373<>"",M373*N373,"") | P373: =IF(J373<>"",J373+O373,"")
D374: =IFERROR(VLOOKUP(Trabajos!C374,Referencias!$E$7:$F$30,2,FALSE),"") | F374: =IFERROR(VLOOKUP(Trabajos!$E374,Clientes,2,FALSE),"") | J374: =IF(H374<>"",H374*I374,"") | L374: =IFERROR(VLOOKUP(K374,Referencias!$H$7:$I$9,2,FALSE),"") | O374: =IF(M374<>"",M374*N374,"") | P374: =IF(J374<>"",J374+O374,"")
D375: =IFERROR(VLOOKUP(Trabajos!C375,Referencias!$E$7:$F$30,2,FALSE),"") | F375: =IFERROR(VLOOKUP(Trabajos!$E375,Clientes,2,FALSE),"") | J375: =IF(H375<>"",H375*I375,"") | L375: =IFERROR(VLOOKUP(K375,Referencias!$H$7:$I$9,2,FALSE),"") | O375: =IF(M375<>"",M375*N375,"") | P375: =IF(J375<>"",J375+O375,"")
D376: =IFERROR(VLOOKUP(Trabajos!C376,Referencias!$E$7:$F$30,2,FALSE),"") | F376: =IFERROR(VLOOKUP(Trabajos!$E376,Clientes,2,FALSE),"") | J376: =IF(H376<>"",H376*I376,"") | L376: =IFERROR(VLOOKUP(K376,Referencias!$H$7:$I$9,2,FALSE),"") | O376: =IF(M376<>"",M376*N376,"") | P376: =IF(J376<>"",J376+O376,"")
D377: =IFERROR(VLOOKUP(Trabajos!C377,Referencias!$E$7:$F$30,2,FALSE),"") | F377: =IFERROR(VLOOKUP(Trabajos!$E377,Clientes,2,FALSE),"") | J377: =IF(H377<>"",H377*I377,"") | L377: =IFERROR(VLOOKUP(K377,Referencias!$H$7:$I$9,2,FALSE),"") | O377: =IF(M377<>"",M377*N377,"") | P377: =IF(J377<>"",J377+O377,"")
D378: =IFERROR(VLOOKUP(Trabajos!C378,Referencias!$E$7:$F$30,2,FALSE),"") | F378: =IFERROR(VLOOKUP(Trabajos!$E378,Clientes,2,FALSE),"") | J378: =IF(H378<>"",H378*I378,"") | L378: =IFERROR(VLOOKUP(K378,Referencias!$H$7:$I$9,2,FALSE),"") | O378: =IF(M378<>"",M378*N378,"") | P378: =IF(J378<>"",J378+O378,"")
D379: =IFERROR(VLOOKUP(Trabajos!C379,Referencias!$E$7:$F$30,2,FALSE),"") | F379: =IFERROR(VLOOKUP(Trabajos!$E379,Clientes,2,FALSE),"") | J379: =IF(H379<>"",H379*I379,"") | L379: =IFERROR(VLOOKUP(K379,Referencias!$H$7:$I$9,2,FALSE),"") | O379: =IF(M379<>"",M379*N379,"") | P379: =IF(J379<>"",J379+O379,"")
... D392: =IFERROR(VLOOKUP(Trabajos!C392,Referencias!$E$7:$F$30,2,FALSE),"") | F392: =IFERROR(VLOOKUP(Trabajos!$E392,Clientes,2,FALSE),"") | J392: =IF(H392<>"",H392*I392,"") | L392: =IFERROR(VLOOKUP(K392,Referencias!$H$7:$I$9,2,FALSE),"") | O392: =IF(M392<>"",M392*N392,"") | P392: =IF(J392<>"",J392+O392,"")
D393: =IFERROR(VLOOKUP(Trabajos!C393,Referencias!$E$7:$F$30,2,FALSE),"") | F393: =IFERROR(VLOOKUP(Trabajos!$E393,Clientes,2,FALSE),"") | J393: =IF(H393<>"",H393*I393,"") | L393: =IFERROR(VLOOKUP(K393,Referencias!$H$7:$I$9,2,FALSE),"") | O393: =IF(M393<>"",M393*N393,"") | P393: =IF(J393<>"",J393+O393,"") | T393: =H393-R393-S393 -> 0
D394: =IFERROR(VLOOKUP(Trabajos!C394,Referencias!$E$7:$F$30,2,FALSE),"") | F394: =IFERROR(VLOOKUP(Trabajos!$E394,Clientes,2,FALSE),"") | J394: =IF(H394<>"",H394*I394,"") | L394: =IFERROR(VLOOKUP(K394,Referencias!$H$7:$I$9,2,FALSE),"") | O394: =IF(M394<>"",M394*N394,"") | P394: =IF(J394<>"",J394+O394,"") | T394: =H394-R394-S394 -> 0
B395: Total | H395: =SUM(H5:H394) -> 57801 | J395: =SUM(J5:J394) -> 1.947755e+08 | O395: =SUM(O5:O394) -> 29496847 | P395: =SUM(P5:P394) -> 2.2427234e+08 | R395: =SUM(R5:R394) -> 3704 | S395: =SUM(S5:S394) -> 5738 | T395: =SUM(T5:T394) -> 37074

Sheet Trabajos 2
B2: Trabajos
G3: Total | H3: =SUBTOTAL(9,H5:H156) -> 80.3 | O3: Total | P3: =SUBTOTAL(9,P5:P156) -> 26437243
B4: Fecha | C4: Cod. Trabajo | D4: Tipo de trabajo | E4: Cod. Cliente | F4: Cliente | G4: Establecimiento | H4: Dia | I4: $/dia | J4: Subtotal | K4: Cod. Vehiculo | L4: Vehiculo | M4: Distancia | N4: $/Km | O4: Movilidad | P4: Importe | R4: Paco | S4: Tomas | T4: Zoom
B5: 45908 | C5: 4 | D5: =IFERROR(VLOOKUP(C5,Referencias!$E$7:$F$30,2,FALSE),"") -> Seguimiento de cultivos | E5: 11 | F5: =IFERROR(VLOOKUP(E5,Clientes,2,FALSE),"") -> Carlos Fernando Fuertes | G5: La Tolderia | H5: 0.5 | I5: 200000 | J5: =IF(H5<>"",H5*I5,"") -> 100000 | K5: 1 | L5: =IFERROR(VLOOKUP(K5,Referencias!$H$7:$I$9,2,FALSE),"") -> Tomas | M5: 120 | N5: 650 | O5: =IF(M5<>"",M5*N5,"") -> 78000 | P5: =IF(J5<>"",J5+O5,"") -> 178000 | R5: 0 | S5: 0.5 | T5: =H5-R5-S5 -> 0
B6: 45912 | C6: 4 | D6: =IFERROR(VLOOKUP(C6,Referencias!$E$7:$F$30,2,FALSE),"") -> Seguimiento de cultivos | E6: 107 | F6: =IFERROR(VLOOKUP(E6,Clientes,2,FALSE),"") -> Omar Piaggio | G6: Costa del Moro | H6: 1 | I6: 150000 | J6: =IF(H6<>"",H6*I6,"") -> 150000 | K6: 1 | L6: =IFERROR(VLOOKUP(K6,Referencias!$H$7:$I$9,2,FALSE),"") -> Tomas | M6: 225 | N6: 650 | O6: =IF(M6<>"",M6*N6,"") -> 146250 | P6: =IF(J6<>"",J6+O6,"") -> 296250 | R6: 0 | S6: 1 | T6: =H6-R6-S6 -> 0
B7: 45917 | C7: 4 | D7: =IFERROR(VLOOKUP(C7,Referencias!$E$7:$F$30,2,FALSE),"") -> Seguimiento de cultivos | E7: 107 | F7: =IFERROR(VLOOKUP(E7,Clientes,2,FALSE),"") -> Omar Piaggio | G7: Costa del Moro | H7: 0 | I7: 150000 | J7: =IF(H7<>"",H7*I7,"") -> 0 | K7: 1 | L7: =IFERROR(VLOOKUP(K7,Referencias!$H$7:$I$9,2,FALSE),"") -> Tomas | M7: 225 | N7: 650 | O7: =IF(M7<>"",M7*N7,"") -> 146250 | P7: =IF(J7<>"",J7+O7,"") -> 146250 | R7: 0 | S7: 0 | T7: =H7-R7-S7 -> 0
B8: 45926 | C8: 4 | D8: =IFERROR(VLOOKUP(C8,Referencias!$E$7:$F$30,2,FALSE),"") -> Seguimiento de cultivos | E8: 24 | F8: =IFERROR(VLOOKUP(E8,Clientes,2,FALSE),"") -> Nugas S.A. | G8: La Alborada | H8: 0.5 | I8: 200000 | J8: =IF(H8<>"",H8*I8,"") -> 100000 | K8: 1 | L8: =IFERROR(VLOOKUP(K8,Referencias!$H$7:$I$9,2,FALSE),"") -> Tomas | M8: 160 | N8: 650 | O8: =IF(M8<>"",M8*N8,"") -> 104000 | P8: =IF(J8<>"",J8+O8,"") -> 204000 | R8: 0 | S8: 0.5 | T8: =H8-R8-S8 -> 0
B9: 45933 | C9: 4 | D9: =IFERROR(VLOOKUP(C9,Referencias!$E$7:$F$30,2,FALSE),"") -> Seguimiento de cultivos | E9: 24 | F9: =IFERROR(VLOOKUP(E9,Clientes,2,FALSE),"") -> Nugas S.A. | G9: La Alborada | H9: 0.5 | I9: 200000 | J9: =IF(H9<>"",H9*I9,"") -> 100000 | K9: 3 | L9: =IFERROR(VLOOKUP(K9,Referencias!$H$7:$I$9,2,FALSE),"") -> Zoom | M9: 160 | N9: 650 | O9: =IF(M9<>"",M9*N9,"") -> 104000 | P9: =IF(J9<>"",J9+O9,"") -> 204000 | R9: 0 | S9: 0 | T9: =H9-R9-S9 -> 0.5
B10: 45934 | C10: 4 | D10: =IFERROR(VLOOKUP(C10,Referencias!$E$7:$F$30,2,FALSE),"") -> Seguimiento de cultivos | E10: 107 | F10: =IFERROR(VLOOKUP(E10,Clientes,2,FALSE),"") -> Omar Piaggio | G10: Costa del Moro | H10: 1 | I10: 150000 | J10: =IF(H10<>"",H10*I10,"") -> 150000 | K10: 1 | L10: =IFERROR(VLOOKUP(K10,Referencias!$H$7:$I$9,2,FALSE),"") -> Tomas | M10: 225 | N10: 650 | O10: =IF(M10<>"",M10*N10,"") -> 146250 | P10: =IF(J10<>"",J10+O10,"") -> 296250 | R10: 0 | S10: 1 | T10: =H10-R10-S10 -> 0
B11: 45939 | C11: 4 | D11: =IFERROR(VLOOKUP(C11,Referencias!$E$7:$F$30,2,FALSE),"") -> Seguimiento de cultivos | E11: 11 | F11: =IFERROR(VLOOKUP(E11,Clientes,2,FALSE),"") -> Carlos Fernando Fuertes | G11: La Tolderia | H11: 0.5 | I11: 200000 | J11: =IF(H11<>"",H11*I11,"") -> 100000 | K11: 1 | L11: =IFERROR(VLOOKUP(K11,Referencias!$H$7:$I$9,2,FALSE),"") -> Tomas | M11: 120 | N11: 650 | O11: =IF(M11<>"",M11*N11,"") -> 78000 | P11: =IF(J11<>"",J11+O11,"") -> 178000 | R11: 0 | S11: 0.5 | T11: =H11-R11-S11 -> 0
B12: 45940 | C12: 4 | D12: =IFERROR(VLOOKUP(C12,Referencias!$E$7:$F$30,2,FALSE),"") -> Seguimiento de cultivos | E12: 24 | F12: =IFERROR(VLOOKUP(E12,Clientes,2,FALSE),"") -> Nugas S.A. | G12: La Alborada | H12: 0.5 | I12: 200000 | J12: =IF(H12<>"",H12*I12,"") -> 100000 | K12: 3 | L12: =IFERROR(VLOOKUP(K12,Referencias!$H$7:$I$9,2,FALSE),"") -> Zoom | M12: 160 | N12: 650 | O12: =IF(M12<>"",M12*N12,"") -> 104000 | P12: =IF(J12<>"",J12+O12,"") -> 204000 | R12: 0 | S12: 0 | T12: =H12-R12-S12 -> 0.5
B13: 45948 | C13: 4 | D13: =IFERROR(VLOOKUP(C13,Referencias!$E$7:$F$30,2,FALSE),"") -> Seguimiento de cultivos | E13: 107 | F13: =IFERROR(VLOOKUP(E13,Clientes,2,FALSE),"") -> Omar Piaggio | G13: Costa del Moro | H13: 1 | I13: 150000 | J13: =IF(H13<>"",H13*I13,"") -> 150000 | K13: 1 | L13: =IFERROR(VLOOKUP(K13,Referencias!$H$7:$I$9,2,FALSE),"") -> Tomas | M13: 225 | N13: 650 | O13: =IF(M13<>"",M13*N13,"") -> 146250 | P13: =IF(J13<>"",J13+O13,"") -> 296250 | R13: 0 | S13: 1 | T13: =H13-R13-S13 -> 0
B14: 45950 | C14: 4 | D14: =IFERROR(VLOOKUP(C14,Referencias!$E$7:$F$30,2,FALSE),"") -> Seguimiento de cultivos | E14: 107 | F14: =IFERROR(VLOOKUP(E14,Clientes,2,FALSE),"") -> Omar Piaggio | G14: Costa del Moro | H14: 1 | I14: 150000 | J14: =IF(H14<>"",H14*I14,"") -> 150000 | K14: 1 | L14: =IFERROR(VLOOKUP(K14,Referencias!$H$7:$I$9,2,FALSE),"") -> Tomas | M14: 225 | N14: 650 | O14: =IF(M14<>"",M14*N14,"") -> 146250 | P14: =IF(J14<>"",J14+O14,"") -> 296250 | R14: 0 | S14: 1 | T14: =H14-R14-S14 -> 0
B15: 45950 | C15: 4 | D15: =IFERROR(VLOOKUP(C15,Referencias!$E$7:$F$30,2,FALSE),"") -> Seguimiento de cultivos | E15: 24 | F15: =IFERROR(VLOOKUP(E15,Clientes,2,FALSE),"") -> Nugas S.A. | G15: La Alborada | H15: 0.5 | I15: 200000 | J15: =IF(H15<>"",H15*I15,"") -> 100000 | K15: 3 | L15: =IFERROR(VLOOKUP(K15,Referencias!$H$7:$I$9,2,FALSE),"") -> Zoom | M15: 160 | N15: 650 | O15: =IF(M15<>"",M15*N15,"") -> 104000 | P15: =IF(J15<>"",J15+O15,"") -> 204000 | R15: 0 | S15: 0 | T15: =H15-R15-S15 -> 0.5
B16: 45959 | C16: 4 | D16: =IFERROR(VLOOKUP(C16,Referencias!$E$7:$F$30,2,FALSE),"") -> Seguimiento de cultivos | E16: 24 | F16: =IFERROR(VLOOKUP(E16,Clientes,2,FALSE),"") -> Nugas S.A. | G16: La Alborada | H16: 0.5 | I16: 200000 | J16: =IF(H16<>"",H16*I16,"") -> 100000 | K16: 3 | L16: =IFERROR(VLOOKUP(K16,Referencias!$H$7:$I$9,2,FALSE),"") -> Zoom | M16: 160 | N16: 650 | O16: =IF(M16<>"",M16*N16,"") -> 104000 | P16: =IF(J16<>"",J16+O16,"") -> 204000 | R16: 0 | S16: 0 | T16: =H16-R16-S16 -> 0.5
... B99: 46219 | C99: 4 | D99: =IFERROR(VLOOKUP(C99,Referencias!$E$7:$F$30,2,FALSE),"") -> Seguimiento de cultivos | E99: 107 | F99: =IFERROR(VLOOKUP(E99,Clientes,2,FALSE),"") -> Omar Piaggio | G99: Costa del Moro | H99: 1 | I99: 150000 | J99: =IF(H99<>"",H99*I99,"") -> 150000 | K99: 1 | L99: =IFERROR(VLOOKUP(K99,Referencias!$H$7:$I$9,2,FALSE),"") -> Tomas | M99: 225 | N99: 850 | O99: =IF(M99<>"",M99*N99,"") -> 191250 | P99: =IF(J99<>"",J99+O99,"") -> 341250 | R99: 0 | S99: 1 | T99: =H99-R99-S99 -> 0
D100: =IFERROR(VLOOKUP(C100,Referencias!$E$7:$F$30,2,FALSE),"") | F100: =IFERROR(VLOOKUP(E100,Clientes,2,FALSE),"") | J100: =IF(H100<>"",H100*I100,"") | L100: =IFERROR(VLOOKUP(K100,Referencias!$H$7:$I$9,2,FALSE),"") | O100: =IF(M100<>"",M100*N100,"") | P100: =IF(J100<>"",J100+O100,"")
D101: =IFERROR(VLOOKUP(C101,Referencias!$E$7:$F$30,2,FALSE),"") | F101: =IFERROR(VLOOKUP(E101,Clientes,2,FALSE),"") | J101: =IF(H101<>"",H101*I101,"") | L101: =IFERROR(VLOOKUP(K101,Referencias!$H$7:$I$9,2,FALSE),"") | O101: =IF(M101<>"",M101*N101,"") | P101: =IF(J101<>"",J101+O101,"")
D102: =IFERROR(VLOOKUP(C102,Referencias!$E$7:$F$30,2,FALSE),"") | F102: =IFERROR(VLOOKUP(E102,Clientes,2,FALSE),"") | J102: =IF(H102<>"",H102*I102,"") | L102: =IFERROR(VLOOKUP(K102,Referencias!$H$7:$I$9,2,FALSE),"") | O102: =IF(M102<>"",M102*N102,"") | P102: =IF(J102<>"",J102+O102,"")
D103: =IFERROR(VLOOKUP(C103,Referencias!$E$7:$F$30,2,FALSE),"") | F103: =IFERROR(VLOOKUP(E103,Clientes,2,FALSE),"") | J103: =IF(H103<>"",H103*I103,"") | L103: =IFERROR(VLOOKUP(K103,Referencias!$H$7:$I$9,2,FALSE),"") | O103: =IF(M103<>"",M103*N103,"") | P103: =IF(J103<>"",J103+O103,"")
D104: =IFERROR(VLOOKUP(C104,Referencias!$E$7:$F$30,2,FALSE),"") | F104: =IFERROR(VLOOKUP(E104,Clientes,2,FALSE),"") | J104: =IF(H104<>"",H104*I104,"") | L104: =IFERROR(VLOOKUP(K104,Referencias!$H$7:$I$9,2,FALSE),"") | O104: =IF(M104<>"",M104*N104,"") | P104: =IF(J104<>"",J104+O104,"")
D105: =IFERROR(VLOOKUP(C105,Referencias!$E$7:$F$30,2,FALSE),"") | F105: =IFERROR(VLOOKUP(E105,Clientes,2,FALSE),"") | J105: =IF(H105<>"",H105*I105,"") | L105: =IFERROR(VLOOKUP(K105,Referencias!$H$7:$I$9,2,FALSE),"") | O105: =IF(M105<>"",M105*N105,"") | P105: =IF(J105<>"",J105+O105,"")
D106: =IFERROR(VLOOKUP(C106,Referencias!$E$7:$F$30,2,FALSE),"") | F106: =IFERROR(VLOOKUP(E106,Clientes,2,FALSE),"") | J106: =IF(H106<>"",H106*I106,"") | L106: =IFERROR(VLOOKUP(K106,Referencias!$H$7:$I$9,2,FALSE),"") | O106: =IF(M106<>"",M106*N106,"") | P106: =IF(J106<>"",J106+O106,"")
D107: =IFERROR(VLOOKUP(C107,Referencias!$E$7:$F$30,2,FALSE),"") | F107: =IFERROR(VLOOKUP(E107,Clientes,2,FALSE),"") | J107: =IF(H107<>"",H107*I107,"") | L107: =IFERROR(VLOOKUP(K107,Referencias!$H$7:$I$9,2,FALSE),"") | O107: =IF(M107<>"",M107*N107,"") | P107: =IF(J107<>"",J107+O107,"")
D108: =IFERROR(VLOOKUP(C108,Referencias!$E$7:$F$30,2,FALSE),"") | F108: =IFERROR(VLOOKUP(E108,Clientes,2,FALSE),"") | J108: =IF(H108<>"",H108*I108,"") | L108: =IFERROR(VLOOKUP(K108,Referencias!$H$7:$I$9,2,FALSE),"") | O108: =IF(M108<>"",M108*N108,"") | P108: =IF(J108<>"",J108+O108,"")
D109: =IFERROR(VLOOKUP(C109,Referencias!$E$7:$F$30,2,FALSE),"") | F109: =IFERROR(VLOOKUP(E109,Clientes,2,FALSE),"") | J109: =IF(H109<>"",H109*I109,"") | L109: =IFERROR(VLOOKUP(K109,Referencias!$H$7:$I$9,2,FALSE),"") | O109: =IF(M109<>"",M109*N109,"") | P109: =IF(J109<>"",J109+O109,"")
D110: =IFERROR(VLOOKUP(C110,Referencias!$E$7:$F$30,2,FALSE),"") | F110: =IFERROR(VLOOKUP(E110,Clientes,2,FALSE),"") | J110: =IF(H110<>"",H110*I110,"") | L110: =IFERROR(VLOOKUP(K110,Referencias!$H$7:$I$9,2,FALSE),"") | O110: =IF(M110<>"",M110*N110,"") | P110: =IF(J110<>"",J110+O110,"")
D111: =IFERROR(VLOOKUP(C111,Referencias!$E$7:$F$30,2,FALSE),"") | F111: =IFERROR(VLOOKUP(E111,Clientes,2,FALSE),"") | J111: =IF(H111<>"",H111*I111,"") | L111: =IFERROR(VLOOKUP(K111,Referencias!$H$7:$I$9,2,FALSE),"") | O111: =IF(M111<>"",M111*N111,"") | P111: =IF(J111<>"",J111+O111,"")
... D156: =IFERROR(VLOOKUP(C156,Referencias!$E$7:$F$30,2,FALSE),"") | F156: =IFERROR(VLOOKUP(E156,Clientes,2,FALSE),"") | J156: =IF(H156<>"",H156*I156,"") | L156: =IFERROR(VLOOKUP(K156,Referencias!$H$7:$I$9,2,FALSE),"") | O156: =IF(M156<>"",M156*N156,"") | P156: =IF(J156<>"",J156+O156,"")
B157: Total | H157: =SUM(H5:H156) -> 80.3 | J157: =SUM(J5:J156) -> 12789680 | O157: =SUM(O5:O156) -> 13647563 | P157: =SUM(P5:P156) -> 26437243 | R157: =SUM(R5:R156) -> 0 | S157: =SUM(S5:S156) -> 47 | T157: =SUM(T5:T156) -> 33.3

Sheet Viajes
B2: Viajes
K3: Suma de km recorridos | O3: Saldo en km | S3: Saldo en $
J4: Periodo | K4: Tomas | L4: Paco | N4: Periodo | O4: Tomas | P4: Paco | R4: Periodo | S4: Tomas | T4: Paco
B5: Fecha | C5: Cliente-Establecimiento | D5: Auto | E5: Km recorridos | F5: Km cobrados | G5: Km cobr. correg. | H5: Diferencia | J5: 1-09 al 31-08 | K5: =SUMIF(D6:D309,K4,E6:E309) -> 33904 | L5: =SUMIF(D6:D309,L4,E6:E309) -> 21297 | N5: 1-09 al 31-08 | O5: =SUMIF(D6:D309,O4,H6:H309) -> -10289.156 | P5: =SUMIF(D6:D309,P4,H6:H309) -> -9288.0119 | R5: 1-09 al 31-08 | S5: =-(O5*650) -> 6687951.2 | T5: =-(P5*650) -> 6037207.7
B6: 45908 | C6: La Tolderia | D6: Tomas | E6: 152 | F6: 120 | G6: 120 | H6: =G6-E6 -> -32
B7: 45909 | C7: Cobo Espartina | D7: Tomas | E7: 129 | F7: 184 | G7: =F7*0.88630769 -> 163.08061 | H7: =G7-E7 -> 34.080615
B8: 45910 | C8: Escuri | D8: Paco | E8: 100 | F8: 0 | G8: 0 | H8: =G8-E8 -> -100
B9: 45911 | C9: La Paz-Bella Vista | D9: Tomas | E9: 290 | F9: 270 | G9: =F9*0.88630769 -> 239.30308 | H9: =G9-E9 -> -50.696924
B10: 45912 | C10: La Juana-Costa del Moro | D10: Tomas | E10: 281 | F10: 92 | G10: 92 | H10: =G10-E10 -> -189
B11: 45913 | C11: San Luciano-Don Gustavo | D11: Tomas | E11: 378 | F11: 704 | G11: =F11*0.88630769 -> 623.96061 | H11: =G11-E11 -> 245.96061
B12: 45914 | C12: Santa Ana Cobo | D12: Tomas | E12: 133 | F12: 172 | G12: =F12*0.88630769 -> 152.44492 | H12: =G12-E12 -> 19.444923
B13: 45915 | C13: Macedo | D13: Tomas | E13: 352 | F13: 328 | G13: =F13*0.88630769 -> 290.70892 | H13: =G13-E13 -> -61.291078
B14: 45916 | C14: La Florida | D14: Tomas | E14: 313 | F14: 370 | G14: =F14*0.88630769 -> 327.93385 | H14: =G14-E14 -> 14.933845
B15: 45916 | C15: El Basural | D15: Paco | E15: 295 | F15: 212 | G15: =F15*0.88630769 -> 187.89723 | H15: =G15-E15 -> -107.10277
B16: 45917 | C16: San Narciso | D16: Tomas | E16: 134 | F16: 208 | G16: =F16*0.904615 -> 188.15992 | H16: =G16-E16 -> 54.15992
B17: 45917 | C17: Costa del Moro | D17: Tomas | E17: 133 | F17: 92 | G17: 92 | H17: =G17-E17 -> -41
B18: 45917 | C18: La Cachila-Doña Hilda | D18: Paco | E18: 302 | F18: 230 | G18: =F18*0.88630769 -> 203.85077 | H18: =G18-E18 -> -98.149231
B19: 45918 | C19: San Francisco-Santa Barbara | D19: Tomas | E19: 195 | F19: 90 | G19: =F19*0.88630769 -> 79.767692 | H19: =G19-E19 -> -115.23231
B20: 45918 | C20: Follaneras-San Lorenzo | D20: Paco | E20: 339 | F20: 180 | G20: =F20*0.88630769 -> 159.53538 | H20: =G20-E20 -> -179.46462
B21: 45922 | C21: Tandil Ranger | D21: Paco | E21: 1089 | F21: 1089 | G21: =F21*0.88630769 -> 965.18907 | H21: =G21-E21 -> -123.81093
B22: 45922 | C22: Tandil Strada | D22: Paco | E22: 952 | F22: 499 | G22: =F22*0.88630769 -> 442.26754 | H22: =G22-E22 -> -509.73246
B23: 45923 | C23: Santa Maria del Moro-San Narciso | D23: Tomas | E23: 255 | F23: 206 | G23: =F23*0.904615 -> 186.35069 | H23: =G23-E23 -> -68.64931
B24: 45924 | C24: San Narciso-Las Overas | D24: Tomas | E24: 275 | F24: 208 | G24: =F24*0.904615 -> 188.15992 | H24: =G24-E24 -> -86.84008
B25: 45925 | C25: La Baguala-La Juanita | D25: Tomas | E25: 239 | F25: 156 | G25: =F25*0.904615 -> 141.11994 | H25: =G25-E25 -> -97.88006
B26: 45926 | C26: La Alborada | D26: Tomas | E26: 236 | F26: 160 | G26: 160 | H26: =G26-E26 -> -76
B27: 45929 | C27: Tres Marias | D27: Paco | E27: 1391 | F27: 210 | G27: =F27*0.904615384615384 -> 189.96923 | H27: =G27-E27 -> -1201.0308
B28: 45929 | C28: Santa Marta | D28: Tomas | E28: 151 | F28: 50 | G28: 50 | H28: =G28-E28 -> -101
B29: 45930 | C29: Tres Marias-Santa Isabel Cozumel | D29: Paco | E29: 0 | F29: 186 | G29: =F29*0.904615384615384 -> 168.25846 | H29: =G29-E29 -> 168.25846
B30: 45930 | C30: Santa Marta | D30: Tomas | E30: 121 | F30: 50 | G30: 50 | H30: =G30-E30 -> -71
B31: 45931 | C31: Cerro Guacho | D31: Paco | E31: 0 | F31: 262 | G31: 262 | H31: =G31-E31 -> 262
B32: 45932 | C32: La Azucena | D32: Paco | E32: 0 | F32: 274 | G32: =F32*0.904615384615384 -> 247.86462 | H32: =G32-E32 -> 247.86462
B33: 45932 | C33: El Moro Viejo | D33: Tomas | E33: 201 | F33: 156 | G33: =F33*0.904615384615384 -> 141.12 | H33: =G33-E33 -> -59.88
B34: 45933 | C34: La Azucena | D34: Paco | E34: 0 | F34: 0 | G34: 0 | H34: =G34-E34 -> 0
B35: 45933 | C35: El Moro Viejo-La Guadalupe | D35: Tomas | E35: 228 | F35: 220 | G35: 220 | H35: =G35-E35 -> -8
B36: 45934 | C36: Santa Isabel Cozumel | D36: Paco | E36: 0 | F36: 0 | G36: 0 | H36: =G36-E36 -> 0
B37: 45934 | C37: Las Overas | D37: Tomas | E37: 265 | F37: 236 | G37: =F37*0.904615384615384 -> 213.48923 | H37: =G37-E37 -> -51.510769
B38: 46299 | C38: Costa del Moro | D38: Tomas | E38: 0 | F38: 225 | G38: 225 | H38: =G38-E38 -> 225
B39: 45937 | C39: San Jose | D39: Tomas | E39: 300 | F39: 370 | G39: =F39*0.904615384615384 -> 334.70769 | H39: =G39-E39 -> 34.707692
B40: 45938 | C40: El Ceibo 2 | D40: Paco | E40: 1050 | F40: 208 | G40: =F40*0.904615384615384 -> 188.16 | H40: =G40-E40 -> -861.84
B41: 45938 | C41: El Moro Viejo | D41: Tomas | E41: 263 | F41: 156 | G41: =F41*0.975153846153846 -> 152.124 | H41: =G41-E41 -> -110.876
B42: 45939 | C42: La Trinidad | D42: Paco | E42: 0 | F42: 164 | G42: =F42*0.904615384615384 -> 148.35692 | H42: =G42-E42 -> 148.35692
B43: 45939 | C43: La Tolderia | D43: Tomas | E43: 240 | F43: 120 | G43: 120 | H43: =G43-E43 -> -120
B44: 45940 | C44: La Trinidad | D44: Paco | E44: 0 | F44: 164 | G44: =F44*0.904615384615384 -> 148.35692 | H44: =G44-E44 -> 148.35692
B45: 45940 | C45: El Moro Viejo | D45: Tomas | E45: 155 | F45: 156 | G45: =F45*0.975153846153846 -> 152.124 | H45: =G45-E45 -> -2.876
B46: 45940 | C46: La Providencia | D46: Tomas | E46: 294 | F46: 0 | G46: 0 | H46: =G46-E46 -> -294
B47: 45941 | C47: El Moro Viejo-San Francisco | D47: Tomas | E47: 559 | F47: 246 | G47: =F47*0.975153846153846 -> 239.88785 | H47: =G47-E47 -> -319.11215
B48: 45944 | C48: Santa Isabel I - La Susana | D48: Paco | E48: 1691 | F48: 436 | G48: =F48*0.975153846153846 -> 425.16708 | H48: =G48-E48 -> -1265.8329
B49: 45944 | C49: La Providencia | D49: Tomas | E49: 326 | F49: 0 | G49: 0 | H49: =G49-E49 -> -326
B50: 45945 | C50: Santa Isabel Cozumel | D50: Paco | E50: 1387 | F50: 186 | G50: =F50*0.975153846153846 -> 181.37862 | H50: =G50-E50 -> -1205.6214
B51: 45945 | C51: San Francisco | D51: Tomas | E51: =205+145 -> 350 | F51: 90 | G51: =F51*0.975153846153846 -> 87.763846 | H51: =G51-E51 -> -262.23615
B52: 45946 | C52: El Volcan | D52: Tomas | E52: =148+117 -> 265 | F52: 0 | G52: 0 | H52: =G52-E52 -> -265
B53: 45947 | C53: Santa Isabel Cozumel | D53: Paco | E53: 0 | F53: 186 | G53: =F53*0.975153846153846 -> 181.37862 | H53: =G53-E53 -> 181.37862
B54: 45947 | C54: San Lorenzo-La Cachila | D54: Paco | E54: 0 | F54: 230 | G54: =F54*0.975153846153846 -> 224.28538 | H54: =G54-E54 -> 224.28538
B55: 45947 | C55: Santa Barbara | D55: Tomas | E55: =119+96 -> 215 | F55: 36 | G55: =F55*0.975153846153846 -> 35.105538 | H55: =G55-E55 -> -179.89446
B56: 45948 | C56: La Cachila | D56: Paco | E56: 0 | F56: 230 | G56: =F56*0.975153846153846 -> 224.28538 | H56: =G56-E56 -> 224.28538
B57: 45948 | C57: El Moro Viejo | D57: Tomas | E57: 253 | F57: 156 | G57: =F57*0.975153846153846 -> 152.124 | H57: =G57-E57 -> -100.876
B58: 45948 | C58: Costa del Moro | D58: Tomas | E58: 92 | F58: 225 | G58: 225 | H58: =G58-E58 -> 133
B59: 45949 | C59: San Jose-El Moro Viejo | D59: Tomas | E59: =306+365 -> 671 | F59: 341 | G59: =F59*0.975153846153846 -> 332.52746 | H59: =G59-E59 -> -338.47254
B60: 45949 | C60: Cerro Destino | D60: Paco | E60: 0 | F60: 294 | G60: =F60*0.975153846153846 -> 286.69523 | H60: =G60-E60 -> 286.69523
B61: 45950 | C61: Los Charitos | D61: Paco | E61: 0 | F61: 588 | G61: =F61*0.975153846153846 -> 573.39046 | H61: =G61-E61 -> 573.39046
B62: 46315 | C62: Cerro Guacho | D62: Paco | E62: 0 | F62: 262 | G62: 262 | H62: =G62-E62 -> 262
B63: 45950 | C63: Costa del Moro | D63: Tomas | E63: 300 | F63: 225 | G63: 225 | H63: =G63-E63 -> -75
B64: 45951 | C64: El Montiel - La Azucena | D64: Paco | E64: 0 | F64: 274 | G64: =F64*0.975153846153846 -> 267.19215 | H64: =G64-E64 -> 267.19215
B65: 45951 | C65: Santa Marta | D65: Tomas | E65: =240+150 -> 390 | F65: 50 | G65: 50 | H65: =G65-E65 -> -340
B66: 45957 | C66: Cerro Guacho | D66: Paco | E66: 2042 | F66: 262 | G66: 262 | H66: =G66-E66 -> -1780
B67: 45957 | C67: La Adelia | D67: Tomas | E67: =241+146 -> 387 | F67: 104 | G67: 104 | H67: =G67-E67 -> -283
B68: 45958 | C68: El Ceibo 2 | D68: Paco | E68: 1915 | F68: 208 | G68: =F68*0.975153846153846 -> 202.832 | H68: =G68-E68 -> -1712.168
B69: 45958 | C69: Santa Maria del Moro | D69: Tomas | E69: =295+224 -> 519 | F69: 164 | G69: =F69*0.975153846153846 -> 159.92523 | H69: =G69-E69 -> -359.07477
B70: 45959 | C70: El Alivio-Santa Isabel Cozumel | D70: Paco | E70: 0 | F70: 394 | G70: =F70*0.975153846153846 -> 384.21062 | H70: =G70-E70 -> 384.21062
B71: 45959 | C71: Villa Laura-Los Cardos | D71: Tomas | E71: =93+137 -> 230 | F71: 52 | G71: 52 | H71: =G71-E71 -> -178
B72: 45960 | C72: La Azucena | D72: Paco | E72: 0 | F72: 274 | G72: =F72*0.975153846153846 -> 267.19215 | H72: =G72-E72 -> 267.19215
B73: 45960 | C73: Santa Marta | D73: Tomas | E73: 127 | F73: 50 | G73: 50 | H73: =G73-E73 -> -77
B74: 45961 | C74: La Azucena | D74: Paco | E74: 0 | F74: 274 | G74: =F74*0.975153846153846 -> 267.19215 | H74: =G74-E74 -> 267.19215
B75: 45961 | C75: Santa Marta | D75: Tomas | E75: =120+231 -> 351 | F75: 50 | G75: 50 | H75: =G75-E75 -> -301
B76: 45962 | C76: Dos Hermanas | D76: Paco | E76: 0 | F76: 112 | G76: =F76*0.975153846153846 -> 109.21723 | H76: =G76-E76 -> 109.21723
B77: 45962 | C77: Los Pinos - Santa Maria del Moro | D77: Tomas | E77: 574 | F77: 190 | G77: =F77*0.975153846153846 -> 185.27923 | H77: =G77-E77 -> -388.72077
B78: 45963 | C78: Dos Hermanas | D78: Paco | E78: 0 | F78: 240 | G78: =F78*0.975153846153846 -> 234.03692 | H78: =G78-E78 -> 234.03692
B79: 45963 | C79: Tres Esquinas-Santa Marta | D79: Tomas | E79: =228+100 -> 328 | F79: 86 | G79: 86 | H79: =G79-E79 -> -242
B80: 45964 | C80: Santa Isabel Cozumel | D80: Paco | E80: 0 | F80: 186 | G80: =F80*0.975153846153846 -> 181.37862 | H80: =G80-E80 -> 181.37862
B81: 45967 | C81: La Tolderia | D81: Tomas | E81: 180 | F81: 120 | G81: 120 | H81: =G81-E81 -> -60
B82: 45967 | C82: La Azucena | D82: Paco | E82: 2219 | F82: 137 | G82: =F82*0.975153846153846 -> 133.59608 | H82: =G82-E82 -> -2085.4039
B83: 45968 | C83: La Azucena | D83: Paco | E83: 1388 | F83: 274 | G83: =F83*0.975153846153846 -> 267.19215 | H83: =G83-E83 -> -1120.8078
B84: 45968 | C84: La Colonia-El Volcan | D84: Tomas | E84: 176 | F84: 54 | G84: 54 | H84: =G84-E84 -> -122
B85: 45968 | C85: La Tolderia | D85: Tomas | E85: 382 | F85: 120 | G85: 120 | H85: =G85-E85 -> -262
B86: 45969 | C86: La Cachila | D86: Paco | E86: 0 | F86: 230 | G86: =F86*0.975153846153846 -> 224.28538 | H86: =G86-E86 -> 224.28538
B87: 45969 | C87: La Nany | D87: Tomas | E87: =127+172 -> 299 | F87: 88 | G87: 88 | H87: =G87-E87 -> -211
B88: 45970 | C88: La Cachila-Las Overas | D88: Paco | E88: 0 | F88: 466 | G88: =F88*0.975153846153846 -> 454.42169 | H88: =G88-E88 -> 454.42169
B89: 45970 | C89: San Narciso | D89: Tomas | E89: 279 | F89: 208 | G89: =F89*0.975153846153846 -> 202.832 | H89: =G89-E89 -> -76.168
B90: 45970 | C90: Costa del Moro | D90: Tomas | E90: 304 | F90: 225 | G90: 225 | H90: =G90-E90 -> -79
B91: 45971 | C91: La Trinidad | D91: Paco | E91: 0 | F91: 164 | G91: =F91*0.975153846153846 -> 159.92523 | H91: =G91-E91 -> 159.92523
B92: 45971 | C92: La Magdalena | D92: Tomas | E92: 208 | F92: 117 | G92: =F92*0.975153846153846 -> 114.093 | H92: =G92-E92 -> -93.907
B93: 45971 | C93: La Tolderia | D93: Tomas | E93: 327 | F93: 120 | G93: 120 | H93: =G93-E93 -> -207
B94: 45972 | C94: Mallinco | D94: Paco | E94: 0 | F94: 186 | G94: =F94*0.975153846153846 -> 181.37862 | H94: =G94-E94 -> 181.37862
B95: 45972 | C95: La Mylucha | D95: Tomas | E95: 64 | F95: 40 | G95: 40 | H95: =G95-E95 -> -24
B96: 45973 | C96: San Agustin | D96: Paco | E96: 990 | F96: 246 | G96: 246 | H96: =G96-E96 -> -744
B97: 45973 | C97: San Agustin | D97: Tomas | E97: 1129 | F97: 96 | G97: 96 | H97: =G97-E97 -> -1033
B98: 45973 | C98: Fasciglione-Las Mercedes | D98: Tomas | E98: 213 | F98: 0 | G98: 0 | H98: =G98-E98 -> -213
B99: 45973 | C99: Costa del Moro | D99: Tomas | E99: 348 | F99: 225 | G99: 225 | H99: =G99-E99 -> -123
B100: 45974 | C100: Los Charitos | D100: Paco | E100: 0 | F100: 294 | G100: =F100*0.975153846153846 -> 286.69523 | H100: =G100-E100 -> 286.69523
B101: 45974 | C101: La Cantera | D101: Tomas | E101: =187+160 -> 347 | F101: 50 | G101: =F101*0.975153846153846 -> 48.757692 | H101: =G101-E101 -> -298.24231
...

Sheet Gastos
B2: Gastos
H3: GASTO ACTUAL | L3: GASTO REAL | P3: SALDO
H4: Tomas | I4: Paco | L4: Tomas | M4: Paco | P4: Tomas | Q4: Paco
D5: Comun | G5: Total | H5: =SUMIF(E7:E220,H4,D7:D220) -> 66853917 | I5: =SUMIF(E7:E220,I4,D7:D220) -> 45765586 | K5: Total | L5: =D221*Referencias!U7 -> 56309751 | M5: =D221*Referencias!T7 -> 56309751 | O5: Total | P5: =(H5-L5) -> 10544166 | Q5: =(I5-M5) -> -10544166
B6: Fecha | C6: Concepto | D6: Importe | E6: Aporte
C7: Movilidad no cobrada | D7: =Viajes!S5 -> 6687951.2 | E7: Tomas
C8: Movilidad no cobrada | D8: =Viajes!T5 -> 6037207.7 | E8: Paco
B9: 45912 | C9: Impresión folletos | D9: 20000 | E9: Paco
B10: 45912 | C10: Clavos y platos | D10: 19000 | E10: Tomas
B11: 45916 | C11: Pago Facundo Kaplun | D11: 120000 | E11: Tomas
B12: 45917 | C12: Pago Agustin Acosta | D12: 150000 | E12: Tomas
B13: 45918 | C13: Pago Alexis Marsico | D13: 150000 | E13: Paco
B14: 45919 | C14: Impresión planillas | D14: 14200 | E14: Tomas
B15: 45919 | C15: Aros monitoreo | D15: 11500 | E15: Tomas
B16: 45922 | C16: Alojamiento Tandil | D16: 442500 | E16: Paco
B17: 45922 | C17: Alojamiento Tandil | D17: 73700 | E17: Paco
B18: 45922 | C18: Super Tandil | D18: 35692.26 | E18: Paco
B19: 45923 | C19: Super Tandil | D19: 44113.6 | E19: Paco
B20: 45923 | C20: Pago Facundo Kaplun | D20: 150000 | E20: Tomas
... B145: 46040 | C145: Pago Melanie Verkuyl | D145: 233376 | E145: Tomas
C146: Monotributo 09 | D146: 391400.62 | E146: Tomas
C147: Monotributo 09 | D147: 49435.58 | E147: Tomas
C148: Monotributo 09 | D148: 391400.62 | E148: Paco
C149: Monotributo 10 | D149: 391400.62 | E149: Tomas
C150: Monotributo 10 | D150: 49435.58 | E150: Tomas
C151: Monotributo 10 | D151: 391400.62 | E151: Paco
C152: Monotributo 11 | D152: 391400.62 | E152: Tomas
C153: Monotributo 11 | D153: 49435.58 | E153: Tomas
C154: Monotributo 11 | D154: 391400.62 | E154: Paco
C155: Monotributo 12 | D155: 172457.38 | E155: Tomas
C156: Monotributo 12 | D156: 49435.58 | E156: Tomas
C157: Monotributo 12 | D157: 391400.62 | E157: Paco
... C161: Monotributo 01 | D161: 391400.62 | E161: Paco
B162: 46041 | C162: Honorarios Kaspar (sep) | D162: 57000 | E162: Tomas
B163: 46041 | C163: Honorarios Kaspar (oct) | D163: 58000 | E163: Tomas
B164: 46041 | C164: Honorarios Kaspar (nov) | D164: 59000 | E164: Tomas
B165: 46041 | C165: Honorarios Kaspar (dic) | D165: 60400 | E165: Tomas
C166: Monotributo 02 | D166: 999007.65 | E166: Tomas
C167: Monotributo 02 | D167: 447346.93 | E167: Tomas
C168: Monotributo 02 | D168: 447346.93 | E168: Paco
C169: Monotributo 03 | D169: 999007.65 | E169: Tomas
C170: Monotributo 03 | D170: 447346.93 | E170: Tomas
C171: Monotributo 03 | D171: 447346.93 | E171: Paco
C172: Monotributo 04 | D172: 999007.65 | E172: Tomas
C173: Monotributo 04 | D173: 447346.93 | E173: Tomas
C174: Monotributo 04 | D174: 447346.93 | E174: Paco
C175: Monotributo 05 | D175: 999007.65 | E175: Tomas
C176: Monotributo 05 | D176: 447346.93 | E176: Tomas
C177: Monotributo 05 | D177: 447346.93 | E177: Paco
... C186: Monotributo 08 | D186: 447346.93 | E186: Paco
B187: 46049 | C187: Pago Pablo Flesborg | D187: 2096000 | E187: Tomas
B188: 46051 | C188: Pago Colo Moser | D188: 952723.51 | E188: Tomas
B189: 46051 | C189: Pago Colo Moser | D189: 952723.51 | E189: Paco
B190: 46057 | C190: Pago Colo Moser | D190: 145776.5 | E190: Tomas
B191: 46057 | C191: Pago Colo Moser | D191: 145776.5 | E191: Paco
B192: 46057 | C192: Pago Nicolas Gabriel | D192: 427800 | E192: Tomas
B193: 46057 | C193: Pago Pablo Flesborg | D193: 2377980 | E193: Paco
B194: 46064 | C194: Pago Colo Moser | D194: 537560.34 | E194: Tomas
B195: 46064 | C195: Pago Colo Moser | D195: 537560.34 | E195: Paco
B196: 46083 | C196: Pago Nicolas Gabriel | D196: 300000 | E196: Tomas
B197: 46091 | C197: Pago Nicolas Gabriel | D197: 341700 | E197: Tomas
B198: 46102 | C198: Pago Colo Moser | D198: 314452.16 | E198: Tomas
... B213: 46208 | C213: Pago Miguel Rybar | D213: 962500 | E213: Tomas
B221: Total | D221: =SUM(D7:D220) -> 1.126195e+08

Sheet Saldos
B2: Saldos
B4: Cod. Cliente | C4: Cliente | D4: Total | E4: Cobrado | F4: Saldo | G4: Detalle enviado | H4: Facturado | I4: Cobrado
B5: 1 | C5: =IFERROR(VLOOKUP(B5,Referencias!$B$7:$C$154,2,FALSE),"") -> Daniel Lanz | D5: =SUMIF(Trabajos!$E$5:$E$394,B5,Trabajos!$P$5:$P$394)+SUMIF('Trabajos 2'!$E$5:$E$156,B5,'Trabajos 2'!$P$5:$P$156) -> 0 | E5: =SUMIF(Ingresos!$C$6:$C$115,B5,Ingresos!$E$6:$E$115) -> 0 | F5: =E5-D5 -> 0
B6: 2 | C6: =IFERROR(VLOOKUP(B6,Referencias!$B$7:$C$154,2,FALSE),"") -> Land Management | D6: =SUMIF(Trabajos!$E$5:$E$394,B6,Trabajos!$P$5:$P$394)+SUMIF('Trabajos 2'!$E$5:$E$156,B6,'Trabajos 2'!$P$5:$P$156) -> 0 | E6: =SUMIF(Ingresos!$C$6:$C$115,B6,Ingresos!$E$6:$E$115) -> 0 | F6: =E6-D6 -> 0
B7: 3 | C7: =IFERROR(VLOOKUP(B7,Referencias!$B$7:$C$154,2,FALSE),"") -> Martin Santamaria | D7: =SUMIF(Trabajos!$E$5:$E$394,B7,Trabajos!$P$5:$P$394)+SUMIF('Trabajos 2'!$E$5:$E$156,B7,'Trabajos 2'!$P$5:$P$156) -> 0 | E7: =SUMIF(Ingresos!$C$6:$C$115,B7,Ingresos!$E$6:$E$115) -> 0 | F7: =E7-D7 -> 0
B8: 4 | C8: =IFERROR(VLOOKUP(B8,Referencias!$B$7:$C$154,2,FALSE),"") -> Purtierra | D8: =SUMIF(Trabajos!$E$5:$E$394,B8,Trabajos!$P$5:$P$394)+SUMIF('Trabajos 2'!$E$5:$E$156,B8,'Trabajos 2'!$P$5:$P$156) -> 3324804 | E8: =SUMIF(Ingresos!$C$6:$C$115,B8,Ingresos!$E$6:$E$115) -> 3324804 | F8: =E8-D8 -> 0
B9: 5 | C9: =IFERROR(VLOOKUP(B9,Referencias!$B$7:$C$154,2,FALSE),"") -> Cofina Agro | D9: =SUMIF(Trabajos!$E$5:$E$394,B9,Trabajos!$P$5:$P$394)+SUMIF('Trabajos 2'!$E$5:$E$156,B9,'Trabajos 2'!$P$5:$P$156) -> 1704025 | E9: =SUMIF(Ingresos!$C$6:$C$115,B9,Ingresos!$E$6:$E$115) -> 1704025 | F9: =E9-D9 -> 0
B10: 6 | C10: =IFERROR(VLOOKUP(B10,Referencias!$B$7:$C$154,2,FALSE),"") -> La Nany S.A. | D10: =SUMIF(Trabajos!$E$5:$E$394,B10,Trabajos!$P$5:$P$394)+SUMIF('Trabajos 2'!$E$5:$E$156,B10,'Trabajos 2'!$P$5:$P$156) -> 6135499.8 | E10: =SUMIF(Ingresos!$C$6:$C$115,B10,Ingresos!$E$6:$E$115) -> 6135499.8 | F10: =E10-D10 -> 0
B11: 7 | C11: =IFERROR(VLOOKUP(B11,Referencias!$B$7:$C$154,2,FALSE),"") -> Agrar del Sur | D11: =SUMIF(Trabajos!$E$5:$E$394,B11,Trabajos!$P$5:$P$394)+SUMIF('Trabajos 2'!$E$5:$E$156,B11,'Trabajos 2'!$P$5:$P$156) -> 0 | E11: =SUMIF(Ingresos!$C$6:$C$115,B11,Ingresos!$E$6:$E$115) -> 0 | F11: =E11-D11 -> 0
B12: 8 | C12: =IFERROR(VLOOKUP(B12,Referencias!$B$7:$C$154,2,FALSE),"") -> Baltan Agropecuaria | D12: =SUMIF(Trabajos!$E$5:$E$394,B12,Trabajos!$P$5:$P$394)+SUMIF('Trabajos 2'!$E$5:$E$156,B12,'Trabajos 2'!$P$5:$P$156) -> 556973.25 | E12: =SUMIF(Ingresos!$C$6:$C$115,B12,Ingresos!$E$6:$E$115) -> 556973.25 | F12: =E12-D12 -> 0
B13: 9 | C13: =IFERROR(VLOOKUP(B13,Referencias!$B$7:$C$154,2,FALSE),"") -> Alberto Oscar Moran | D13: =SUMIF(Trabajos!$E$5:$E$394,B13,Trabajos!$P$5:$P$394)+SUMIF('Trabajos 2'!$E$5:$E$156,B13,'Trabajos 2'!$P$5:$P$156) -> 0 | E13: =SUMIF(Ingresos!$C$6:$C$115,B13,Ingresos!$E$6:$E$115) -> 0 | F13: =E13-D13 -> 0
B14: 10 | C14: =IFERROR(VLOOKUP(B14,Referencias!$B$7:$C$154,2,FALSE),"") -> Tibus S.A. | D14: =SUMIF(Trabajos!$E$5:$E$394,B14,Trabajos!$P$5:$P$394)+SUMIF('Trabajos 2'!$E$5:$E$156,B14,'Trabajos 2'!$P$5:$P$156) -> 0 | E14: =SUMIF(Ingresos!$C$6:$C$115,B14,Ingresos!$E$6:$E$115) -> 0 | F14: =E14-D14 -> 0
B15: 11 | C15: =IFERROR(VLOOKUP(B15,Referencias!$B$7:$C$154,2,FALSE),"") -> Carlos Fernando Fuertes | D15: =SUMIF(Trabajos!$E$5:$E$394,B15,Trabajos!$P$5:$P$394)+SUMIF('Trabajos 2'!$E$5:$E$156,B15,'Trabajos 2'!$P$5:$P$156) -> 6095260 | E15: =SUMIF(Ingresos!$C$6:$C$115,B15,Ingresos!$E$6:$E$115) -> 5033260 | F15: =E15-D15 -> -1062000
B16: 12 | C16: =IFERROR(VLOOKUP(B16,Referencias!$B$7:$C$154,2,FALSE),"") -> Miron y Alfonso/Iocco Palladino | D16: =SUMIF(Trabajos!$E$5:$E$394,B16,Trabajos!$P$5:$P$394)+SUMIF('Trabajos 2'!$E$5:$E$156,B16,'Trabajos 2'!$P$5:$P$156) -> 0 | E16: =SUMIF(Ingresos!$C$6:$C$115,B16,Ingresos!$E$6:$E$115) -> 0 | F16: =E16-D16 -> 0
... B27: 23 | C27: =IFERROR(VLOOKUP(B27,Referencias!$B$7:$C$154,2,FALSE),"") -> Esteban Dominguez | D27: =SUMIF(Trabajos!$E$5:$E$394,B27,Trabajos!$P$5:$P$394)+SUMIF('Trabajos 2'!$E$5:$E$156,B27,'Trabajos 2'!$P$5:$P$156) -> 0 | E27: =SUMIF(Ingresos!$C$6:$C$115,B27,Ingresos!$E$6:$E$115) -> 0 | F27: =E27-D27 -> 0
B28: 24 | C28: =IFERROR(VLOOKUP(B28,Referencias!$B$7:$C$154,2,FALSE),"") -> Nugas S.A. | D28: =SUMIF(Trabajos!$E$5:$E$394,B28,Trabajos!$P$5:$P$394)+SUMIF('Trabajos 2'!$E$5:$E$156,B28,'Trabajos 2'!$P$5:$P$156) -> 9539896.2 | E28: =SUMIF(Ingresos!$C$6:$C$115,B28,Ingresos!$E$6:$E$115) -> 8855343.2 | F28: =E28-D28 -> -684553 | G28: Si | H28: Si
B29: 25 | C29: =IFERROR(VLOOKUP(B29,Referencias!$B$7:$C$154,2,FALSE),"") -> Hugo Pascual | D29: =SUMIF(Trabajos!$E$5:$E$394,B29,Trabajos!$P$5:$P$394)+SUMIF('Trabajos 2'!$E$5:$E$156,B29,'Trabajos 2'!$P$5:$P$156) -> 0 | E29: =SUMIF(Ingresos!$C$6:$C$115,B29,Ingresos!$E$6:$E$115) -> 0 | F29: =E29-D29 -> 0
B30: 26 | C30: =IFERROR(VLOOKUP(B30,Referencias!$B$7:$C$154,2,FALSE),"") -> Oxagro S.A. | D30: =SUMIF(Trabajos!$E$5:$E$394,B30,Trabajos!$P$5:$P$394)+SUMIF('Trabajos 2'!$E$5:$E$156,B30,'Trabajos 2'!$P$5:$P$156) -> 0 | E30: =SUMIF(Ingresos!$C$6:$C$115,B30,Ingresos!$E$6:$E$115) -> 0 | F30: =E30-D30 -> 0
B31: 27 | C31: =IFERROR(VLOOKUP(B31,Referencias!$B$7:$C$154,2,FALSE),"") -> Biocrop S.A. | D31: =SUMIF(Trabajos!$E$5:$E$394,B31,Trabajos!$P$5:$P$394)+SUMIF('Trabajos 2'!$E$5:$E$156,B31,'Trabajos 2'!$P$5:$P$156) -> 0 | E31: =SUMIF(Ingresos!$C$6:$C$115,B31,Ingresos!$E$6:$E$115) -> 0 | F31: =E31-D31 -> 0
B32: 28 | C32: =IFERROR(VLOOKUP(B32,Referencias!$B$7:$C$154,2,FALSE),"") -> Agroproductos | D32: =SUMIF(Trabajos!$E$5:$E$394,B32,Trabajos!$P$5:$P$394)+SUMIF('Trabajos 2'!$E$5:$E$156,B32,'Trabajos 2'!$P$5:$P$156) -> 0 | E32: =SUMIF(Ingresos!$C$6:$C$115,B32,Ingresos!$E$6:$E$115) -> 0 | F32: =E32-D32 -> 0
B33: 29 | C33: =IFERROR(VLOOKUP(B33,Referencias!$B$7:$C$154,2,FALSE),"") -> Parceiros Sul America S.A. | D33: =SUMIF(Trabajos!$E$5:$E$394,B33,Trabajos!$P$5:$P$394)+SUMIF('Trabajos 2'!$E$5:$E$156,B33,'Trabajos 2'!$P$5:$P$156) -> 0 | E33: =SUMIF(Ingresos!$C$6:$C$115,B33,Ingresos!$E$6:$E$115) -> 0 | F33: =E33-D33 -> 0
B34: 30 | C34: =IFERROR(VLOOKUP(B34,Referencias!$B$7:$C$154,2,FALSE),"") -> Estancia San Pedro S.A. | D34: =SUMIF(Trabajos!$E$5:$E$394,B34,Trabajos!$P$5:$P$394)+SUMIF('Trabajos 2'!$E$5:$E$156,B34,'Trabajos 2'!$P$5:$P$156) -> 0 | E34: =SUMIF(Ingresos!$C$6:$C$115,B34,Ingresos!$E$6:$E$115) -> 0 | F34: =E34-D34 -> 0
B35: 31 | C35: =IFERROR(VLOOKUP(B35,Referencias!$B$7:$C$154,2,FALSE),"") -> La Gloriosa S.A. | D35: =SUMIF(Trabajos!$E$5:$E$394,B35,Trabajos!$P$5:$P$394)+SUMIF('Trabajos 2'!$E$5:$E$156,B35,'Trabajos 2'!$P$5:$P$156) -> 4355350.3 | E35: =SUMIF(Ingresos!$C$6:$C$115,B35,Ingresos!$E$6:$E$115) -> 3316863.9 | F35: =E35-D35 -> -1038486.4 | G35: Si | H35: Si
B36: 32 | C36: =IFERROR(VLOOKUP(B36,Referencias!$B$7:$C$154,2,FALSE),"") -> Sebastian Pascualini | D36: =SUMIF(Trabajos!$E$5:$E$394,B36,Trabajos!$P$5:$P$394)+SUMIF('Trabajos 2'!$E$5:$E$156,B36,'Trabajos 2'!$P$5:$P$156) -> 0 | E36: =SUMIF(Ingresos!$C$6:$C$115,B36,Ingresos!$E$6:$E$115) -> 0 | F36: =E36-D36 -> 0
B37: 33 | C37: =IFERROR(VLOOKUP(B37,Referencias!$B$7:$C$154,2,FALSE),"") -> Espartina S.A. | D37: =SUMIF(Trabajos!$E$5:$E$394,B37,Trabajos!$P$5:$P$394)+SUMIF('Trabajos 2'!$E$5:$E$156,B37,'Trabajos 2'!$P$5:$P$156) -> 1.4754476e+08 | E37: =SUMIF(Ingresos!$C$6:$C$115,B37,Ingresos!$E$6:$E$115) -> 1.4722941e+08 | F37: =E37-D37 -> -315348 | G37: No | H37: No
B38: 34 | C38: =IFERROR(VLOOKUP(B38,Referencias!$B$7:$C$154,2,FALSE),"") -> Garfin Agro S.A. | D38: =SUMIF(Trabajos!$E$5:$E$394,B38,Trabajos!$P$5:$P$394)+SUMIF('Trabajos 2'!$E$5:$E$156,B38,'Trabajos 2'!$P$5:$P$156) -> 0 | E38: =SUMIF(Ingresos!$C$6:$C$115,B38,Ingresos!$E$6:$E$115) -> 0 | F38: =E38-D38 -> 0
B39: 35 | C39: =IFERROR(VLOOKUP(B39,Referencias!$B$7:$C$154,2,FALSE),"") -> Federico Sturla | D39: =SUMIF(Trabajos!$E$5:$E$394,B39,Trabajos!$P$5:$P$394)+SUMIF('Trabajos 2'!$E$5:$E$156,B39,'Trabajos 2'!$P$5:$P$156) -> 0 | E39: =SUMIF(Ingresos!$C$6:$C$115,B39,Ingresos!$E$6:$E$115) -> 0 | F39: =E39-D39 -> 0
B40: 36 | C40: =IFERROR(VLOOKUP(B40,Referencias!$B$7:$C$154,2,FALSE),"") -> Don Balbino | D40: =SUMIF(Trabajos!$E$5:$E$394,B40,Trabajos!$P$5:$P$394)+SUMIF('Trabajos 2'!$E$5:$E$156,B40,'Trabajos 2'!$P$5:$P$156) -> 0 | E40: =SUMIF(Ingresos!$C$6:$C$115,B40,Ingresos!$E$6:$E$115) -> 0 | F40: =E40-D40 -> 0
B41: 37 | C41: =IFERROR(VLOOKUP(B41,Referencias!$B$7:$C$154,2,FALSE),"") -> Sebastian Martos | D41: =SUMIF(Trabajos!$E$5:$E$394,B41,Trabajos!$P$5:$P$394)+SUMIF('Trabajos 2'!$E$5:$E$156,B41,'Trabajos 2'!$P$5:$P$156) -> 2136755 | E41: =SUMIF(Ingresos!$C$6:$C$115,B41,Ingresos!$E$6:$E$115) -> 2136755 | F41: =E41-D41 -> 0
B42: 38 | C42: =IFERROR(VLOOKUP(B42,Referencias!$B$7:$C$154,2,FALSE),"") -> Julio Bertoloto | D42: =SUMIF(Trabajos!$E$5:$E$394,B42,Trabajos!$P$5:$P$394)+SUMIF('Trabajos 2'!$E$5:$E$156,B42,'Trabajos 2'!$P$5:$P$156) -> 0 | E42: =SUMIF(Ingresos!$C$6:$C$115,B42,Ingresos!$E$6:$E$115) -> 0 | F42: =E42-D42 -> 0
B43: 39 | C43: =IFERROR(VLOOKUP(B43,Referencias!$B$7:$C$154,2,FALSE),"") -> Fabian Trama | D43: =SUMIF(Trabajos!$E$5:$E$394,B43,Trabajos!$P$5:$P$394)+SUMIF('Trabajos 2'!$E$5:$E$156,B43,'Trabajos 2'!$P$5:$P$156) -> 0 | E43: =SUMIF(Ingresos!$C$6:$C$115,B43,Ingresos!$E$6:$E$115) -> 0 | F43: =E43-D43 -> 0
B44: 40 | C44: =IFERROR(VLOOKUP(B44,Referencias!$B$7:$C$154,2,FALSE),"") -> Cía. de Tierras Sud Argentino S.A. | D44: =SUMIF(Trabajos!$E$5:$E$394,B44,Trabajos!$P$5:$P$394)+SUMIF('Trabajos 2'!$E$5:$E$156,B44,'Trabajos 2'!$P$5:$P$156) -> 17307389 | E44: =SUMIF(Ingresos!$C$6:$C$115,B44,Ingresos!$E$6:$E$115) -> 17307389 | F44: =E44-D44 -> 0
B45: 41 | C45: =IFERROR(VLOOKUP(B45,Referencias!$B$7:$C$154,2,FALSE),"") -> Cresud S.A.C.I.F y A | D45: =SUMIF(Trabajos!$E$5:$E$394,B45,Trabajos!$P$5:$P$394)+SUMIF('Trabajos 2'!$E$5:$E$156,B45,'Trabajos 2'!$P$5:$P$156) -> 0 | E45: =SUMIF(Ingresos!$C$6:$C$115,B45,Ingresos!$E$6:$E$115) -> 0 | F45: =E45-D45 -> 0
B46: 42 | C46: =IFERROR(VLOOKUP(B46,Referencias!$B$7:$C$154,2,FALSE),"") -> Juan Carlos Naveira | D46: =SUMIF(Trabajos!$E$5:$E$394,B46,Trabajos!$P$5:$P$394)+SUMIF('Trabajos 2'!$E$5:$E$156,B46,'Trabajos 2'!$P$5:$P$156) -> 0 | E46: =SUMIF(Ingresos!$C$6:$C$115,B46,Ingresos!$E$6:$E$115) -> 0 | F46: =E46-D46 -> 0
B47: 43 | C47: =IFERROR(VLOOKUP(B47,Referencias!$B$7:$C$154,2,FALSE),"") -> Anuitt S.R.L | D47: =SUMIF(Trabajos!$E$5:$E$394,B47,Trabajos!$P$5:$P$394)+SUMIF('Trabajos 2'!$E$5:$E$156,B47,'Trabajos 2'!$P$5:$P$156) -> 0 | E47: =SUMIF(Ingresos!$C$6:$C$115,B47,Ingresos!$E$6:$E$115) -> 0 | F47: =E47-D47 -> 0
B48: 44 | C48: =IFERROR(VLOOKUP(B48,Referencias!$B$7:$C$154,2,FALSE),"") -> Francisco Hernandez | D48: =SUMIF(Trabajos!$E$5:$E$394,B48,Trabajos!$P$5:$P$394)+SUMIF('Trabajos 2'!$E$5:$E$156,B48,'Trabajos 2'!$P$5:$P$156) -> 0 | E48: =SUMIF(Ingresos!$C$6:$C$115,B48,Ingresos!$E$6:$E$115) -> 0 | F48: =E48-D48 -> 0
B49: 45 | C49: =IFERROR(VLOOKUP(B49,Referencias!$B$7:$C$154,2,FALSE),"") -> Guillermo Pugliese | D49: =SUMIF(Trabajos!$E$5:$E$394,B49,Trabajos!$P$5:$P$394)+SUMIF('Trabajos 2'!$E$5:$E$156,B49,'Trabajos 2'!$P$5:$P$156) -> 4286937.6 | E49: =SUMIF(Ingresos!$C$6:$C$115,B49,Ingresos!$E$6:$E$115) -> 4286937.6 | F49: =E49-D49 -> 0
... B85: 81 | C85: =IFERROR(VLOOKUP(B85,Referencias!$B$7:$C$154,2,FALSE),"") -> Santiago Chevalier | D85: =SUMIF(Trabajos!$E$5:$E$394,B85,Trabajos!$P$5:$P$394)+SUMIF('Trabajos 2'!$E$5:$E$156,B85,'Trabajos 2'!$P$5:$P$156) -> 0 | E85: =SUMIF(Ingresos!$C$6:$C$115,B85,Ingresos!$E$6:$E$115) -> 0 | F85: =E85-D85 -> 0
B86: 82 | C86: =IFERROR(VLOOKUP(B86,Referencias!$B$7:$C$154,2,FALSE),"") -> Cristian Rybner | D86: =SUMIF(Trabajos!$E$5:$E$394,B86,Trabajos!$P$5:$P$394)+SUMIF('Trabajos 2'!$E$5:$E$156,B86,'Trabajos 2'!$P$5:$P$156) -> 473973.5 | E86: =SUMIF(Ingresos!$C$6:$C$115,B86,Ingresos!$E$6:$E$115) -> 0 | F86: =E86-D86 -> -473973.5 | G86: Si | H86: Si
B87: 83 | C87: =IFERROR(VLOOKUP(B87,Referencias!$B$7:$C$154,2,FALSE),"") -> Eduardo Nasurdi | D87: =SUMIF(Trabajos!$E$5:$E$394,B87,Trabajos!$P$5:$P$394)+SUMIF('Trabajos 2'!$E$5:$E$156,B87,'Trabajos 2'!$P$5:$P$156) -> 0 | E87: =SUMIF(Ingresos!$C$6:$C$115,B87,Ingresos!$E$6:$E$115) -> 0 | F87: =E87-D87 -> 0
B88: 84 | C88: =IFERROR(VLOOKUP(B88,Referencias!$B$7:$C$154,2,FALSE),"") -> Domingo y Nestor Scioli | D88: =SUMIF(Trabajos!$E$5:$E$394,B88,Trabajos!$P$5:$P$394)+SUMIF('Trabajos 2'!$E$5:$E$156,B88,'Trabajos 2'!$P$5:$P$156) -> 4033019.8 | E88: =SUMIF(Ingresos!$C$6:$C$115,B88,Ingresos!$E$6:$E$115) -> 4033019.8 | F88: =E88-D88 -> 0
B89: 85 | C89: =IFERROR(VLOOKUP(B89,Referencias!$B$7:$C$154,2,FALSE),"") -> Austral Store | D89: =SUMIF(Trabajos!$E$5:$E$394,B89,Trabajos!$P$5:$P$394)+SUMIF('Trabajos 2'!$E$5:$E$156,B89,'Trabajos 2'!$P$5:$P$156) -> 0 | E89: =SUMIF(Ingresos!$C$6:$C$115,B89,Ingresos!$E$6:$E$115) -> 0 | F89: =E89-D89 -> 0
B90: 86 | C90: =IFERROR(VLOOKUP(B90,Referencias!$B$7:$C$154,2,FALSE),"") -> Horacio Farengo | D90: =SUMIF(Trabajos!$E$5:$E$394,B90,Trabajos!$P$5:$P$394)+SUMIF('Trabajos 2'!$E$5:$E$156,B90,'Trabajos 2'!$P$5:$P$156) -> 0 | E90: =SUMIF(Ingresos!$C$6:$C$115,B90,Ingresos!$E$6:$E$115) -> 0 | F90: =E90-D90 -> 0
B91: 87 | C91: =IFERROR(VLOOKUP(B91,Referencias!$B$7:$C$154,2,FALSE),"") -> La Mezquita-La Mostaza | D91: =SUMIF(Trabajos!$E$5:$E$394,B91,Trabajos!$P$5:$P$394)+SUMIF('Trabajos 2'!$E$5:$E$156,B91,'Trabajos 2'!$P$5:$P$156) -> 706531.25 | E91: =SUMIF(Ingresos!$C$6:$C$115,B91,Ingresos!$E$6:$E$115) -> 706531.25 | F91: =E91-D91 -> 0
B92: 88 | C92: =IFERROR(VLOOKUP(B92,Referencias!$B$7:$C$154,2,FALSE),"") -> Ignacio Ridao | D92: =SUMIF(Trabajos!$E$5:$E$394,B92,Trabajos!$P$5:$P$394)+SUMIF('Trabajos 2'!$E$5:$E$156,B92,'Trabajos 2'!$P$5:$P$156) -> 328271.25 | E92: =SUMIF(Ingresos!$C$6:$C$115,B92,Ingresos!$E$6:$E$115) -> 328271.25 | F92: =E92-D92 -> 0
B93: 89 | C93: =IFERROR(VLOOKUP(B93,Referencias!$B$7:$C$154,2,FALSE),"") -> Jose Echeverria e Hijos | D93: =SUMIF(Trabajos!$E$5:$E$394,B93,Trabajos!$P$5:$P$394)+SUMIF('Trabajos 2'!$E$5:$E$156,B93,'Trabajos 2'!$P$5:$P$156) -> 42600 | E93: =SUMIF(Ingresos!$C$6:$C$115,B93,Ingresos!$E$6:$E$115) -> 42600 | F93: =E93-D93 -> 0
B94: 90 | C94: =IFERROR(VLOOKUP(B94,Referencias!$B$7:$C$154,2,FALSE),"") -> Walter Ingenieri | D94: =SUMIF(Trabajos!$E$5:$E$394,B94,Trabajos!$P$5:$P$394)+SUMIF('Trabajos 2'!$E$5:$E$156,B94,'Trabajos 2'!$P$5:$P$156) -> 295600 | E94: =SUMIF(Ingresos!$C$6:$C$115,B94,Ingresos!$E$6:$E$115) -> 295600 | F94: =E94-D94 -> 0
B95: 91 | C95: =IFERROR(VLOOKUP(B95,Referencias!$B$7:$C$154,2,FALSE),"") -> Alfredo Hitce | D95: =SUMIF(Trabajos!$E$5:$E$394,B95,Trabajos!$P$5:$P$394)+SUMIF('Trabajos 2'!$E$5:$E$156,B95,'Trabajos 2'!$P$5:$P$156) -> 427204 | E95: =SUMIF(Ingresos!$C$6:$C$115,B95,Ingresos!$E$6:$E$115) -> 0 | F95: =E95-D95 -> -427204 | G95: Si | H95: Si
B96: 92 | C96: =IFERROR(VLOOKUP(B96,Referencias!$B$7:$C$154,2,FALSE),"") -> Carlos Riccillo | D96: =SUMIF(Trabajos!$E$5:$E$394,B96,Trabajos!$P$5:$P$394)+SUMIF('Trabajos 2'!$E$5:$E$156,B96,'Trabajos 2'!$P$5:$P$156) -> 0 | E96: =SUMIF(Ingresos!$C$6:$C$115,B96,Ingresos!$E$6:$E$115) -> 0 | F96: =E96-D96 -> 0
B97: 93 | C97: =IFERROR(VLOOKUP(B97,Referencias!$B$7:$C$154,2,FALSE),"") -> Javier Vidaguren | D97: =SUMIF(Trabajos!$E$5:$E$394,B97,Trabajos!$P$5:$P$394)+SUMIF('Trabajos 2'!$E$5:$E$156,B97,'Trabajos 2'!$P$5:$P$156) -> 0 | E97: =SUMIF(Ingresos!$C$6:$C$115,B97,Ingresos!$E$6:$E$115) -> 0 | F97: =E97-D97 -> 0
B98: 94 | C98: =IFERROR(VLOOKUP(B98,Referencias!$B$7:$C$154,2,FALSE),"") -> Pomme de Terre SRL | D98: =SUMIF(Trabajos!$E$5:$E$394,B98,Trabajos!$P$5:$P$394)+SUMIF('Trabajos 2'!$E$5:$E$156,B98,'Trabajos 2'!$P$5:$P$156) -> 0 | E98: =SUMIF(Ingresos!$C$6:$C$115,B98,Ingresos!$E$6:$E$115) -> 0 | F98: =E98-D98 -> 0
B99: 95 | C99: =IFERROR(VLOOKUP(B99,Referencias!$B$7:$C$154,2,FALSE),"") -> Florimond Desprez | D99: =SUMIF(Trabajos!$E$5:$E$394,B99,Trabajos!$P$5:$P$394)+SUMIF('Trabajos 2'!$E$5:$E$156,B99,'Trabajos 2'!$P$5:$P$156) -> 183750 | E99: =SUMIF(Ingresos!$C$6:$C$115,B99,Ingresos!$E$6:$E$115) -> 183750 | F99: =E99-D99 -> 0
B100: 96 | C100: =IFERROR(VLOOKUP(B100,Referencias!$B$7:$C$154,2,FALSE),"") -> Daniel Arriegue | D100: =SUMIF(Trabajos!$E$5:$E$394,B100,Trabajos!$P$5:$P$394)+SUMIF('Trabajos 2'!$E$5:$E$156,B100,'Trabajos 2'!$P$5:$P$156) -> 0 | E100: =SUMIF(Ingresos!$C$6:$C$115,B100,Ingresos!$E$6:$E$115) -> 0 | F100: =E100-D100 -> 0
B101: 97 | C101: =IFERROR(VLOOKUP(B101,Referencias!$B$7:$C$154,2,FALSE),"") -> Vistaguay | D101: =SUMIF(Trabajos!$E$5:$E$394,B101,Trabajos!$P$5:$P$394)+SUMIF('Trabajos 2'!$E$5:$E$156,B101,'Trabajos 2'!$P$5:$P$156) -> 0 | E101: =SUMIF(Ingresos!$C$6:$C$115,B101,Ingresos!$E$6:$E$115) -> 0 | F101: =E101-D101 -> 0
B102: 98 | C102: =IFERROR(VLOOKUP(B102,Referencias!$B$7:$C$154,2,FALSE),"") -> Inalco | D102: =SUMIF(Trabajos!$E$5:$E$394,B102,Trabajos!$P$5:$P$394)+SUMIF('Trabajos 2'!$E$5:$E$156,B102,'Trabajos 2'!$P$5:$P$156) -> 2739165 | E102: =SUMIF(Ingresos!$C$6:$C$115,B102,Ingresos!$E$6:$E$115) -> 2739165 | F102: =E102-D102 -> 0
B103: 99 | C103: =IFERROR(VLOOKUP(B103,Referencias!$B$7:$C$154,2,FALSE),"") -> San Vicente | D103: =SUMIF(Trabajos!$E$5:$E$394,B103,Trabajos!$P$5:$P$394)+SUMIF('Trabajos 2'!$E$5:$E$156,B103,'Trabajos 2'!$P$5:$P$156) -> 1426157.5 | E103: =SUMIF(Ingresos!$C$6:$C$115,B103,Ingresos!$E$6:$E$115) -> 1426157.5 | F103: =E103-D103 -> 0
B104: 100 | C104: =IFERROR(VLOOKUP(B104,Referencias!$B$7:$C$154,2,FALSE),"") -> Roza Hnos | D104: =SUMIF(Trabajos!$E$5:$E$394,B104,Trabajos!$P$5:$P$394)+SUMIF('Trabajos 2'!$E$5:$E$156,B104,'Trabajos 2'!$P$5:$P$156) -> 0 | E104: =SUMIF(Ingresos!$C$6:$C$115,B104,Ingresos!$E$6:$E$115) -> 0 | F104: =E104-D104 -> 0
B105: 101 | C105: =IFERROR(VLOOKUP(B105,Referencias!$B$7:$C$154,2,FALSE),"") -> Agustin Galeano | D105: =SUMIF(Trabajos!$E$5:$E$394,B105,Trabajos!$P$5:$P$394)+SUMIF('Trabajos 2'!$E$5:$E$156,B105,'Trabajos 2'!$P$5:$P$156) -> 493880 | E105: =SUMIF(Ingresos!$C$6:$C$115,B105,Ingresos!$E$6:$E$115) -> 493880 | F105: =E105-D105 -> 0
B106: 102 | C106: =IFERROR(VLOOKUP(B106,Referencias!$B$7:$C$154,2,FALSE),"") -> Eduardo Dam Sonderup | D106: =SUMIF(Trabajos!$E$5:$E$394,B106,Trabajos!$P$5:$P$394)+SUMIF('Trabajos 2'!$E$5:$E$156,B106,'Trabajos 2'!$P$5:$P$156) -> 0 | E106: =SUMIF(Ingresos!$C$6:$C$115,B106,Ingresos!$E$6:$E$115) -> 0 | F106: =E106-D106 -> 0
B107: 103 | C107: =IFERROR(VLOOKUP(B107,Referencias!$B$7:$C$154,2,FALSE),"") -> AgroFranVis SRL | D107: =SUMIF(Trabajos!$E$5:$E$394,B107,Trabajos!$P$5:$P$394)+SUMIF('Trabajos 2'!$E$5:$E$156,B107,'Trabajos 2'!$P$5:$P$156) -> 1213680 | E107: =SUMIF(Ingresos!$C$6:$C$115,B107,Ingresos!$E$6:$E$115) -> 1213680 | F107: =E107-D107 -> 0
... B135: 131 | C135: =IFERROR(VLOOKUP(B135,Referencias!$B$7:$C$154,2,FALSE),"") -> Fernando Pili | D135: =SUMIF(Trabajos!$E$5:$E$394,B135,Trabajos!$P$5:$P$394)+SUMIF('Trabajos 2'!$E$5:$E$156,B135,'Trabajos 2'!$P$5:$P$156) -> 1056090.8 | E135: =SUMIF(Ingresos!$C$6:$C$115,B135,Ingresos!$E$6:$E$115) -> 1056090.8 | F135: =E135-D135 -> 0
B136: 132 | C136: =IFERROR(VLOOKUP(B136,Referencias!$B$7:$C$154,2,FALSE),"") -> Tres Mil Tres S.A. | D136: =SUMIF(Trabajos!$E$5:$E$394,B136,Trabajos!$P$5:$P$394)+SUMIF('Trabajos 2'!$E$5:$E$156,B136,'Trabajos 2'!$P$5:$P$156) -> 359800 | E136: =SUMIF(Ingresos!$C$6:$C$115,B136,Ingresos!$E$6:$E$115) -> 0 | F136: =E136-D136 -> -359800 | G136: Si | H136: Si
C137: =IFERROR(VLOOKUP(B137,Referencias!$B$7:$C$154,2,FALSE),"") | D137: =SUMIF(Trabajos!$E$5:$E$394,B137,Trabajos!$P$5:$P$394)+SUMIF('Trabajos 2'!$E$5:$E$156,B137,'Trabajos 2'!$P$5:$P$156) -> 0 | E137: =SUMIF(Ingresos!$C$6:$C$115,B137,Ingresos!$E$6:$E$115) -> 0 | F137: =E137-D137 -> 0
C138: =IFERROR(VLOOKUP(B138,Referencias!$B$7:$C$154,2,FALSE),"") | D138: =SUMIF(Trabajos!$E$5:$E$394,B138,Trabajos!$P$5:$P$394)+SUMIF('Trabajos 2'!$E$5:$E$156,B138,'Trabajos 2'!$P$5:$P$156) -> 0 | E138: =SUMIF(Ingresos!$C$6:$C$115,B138,Ingresos!$E$6:$E$115) -> 0 | F138: =E138-D138 -> 0
C139: =IFERROR(VLOOKUP(B139,Referencias!$B$7:$C$154,2,FALSE),"") | D139: =SUMIF(Trabajos!$E$5:$E$394,B139,Trabajos!$P$5:$P$394)+SUMIF('Trabajos 2'!$E$5:$E$156,B139,'Trabajos 2'!$P$5:$P$156) -> 0 | E139: =SUMIF(Ingresos!$C$6:$C$115,B139,Ingresos!$E$6:$E$115) -> 0 | F139: =E139-D139 -> 0
C140: =IFERROR(VLOOKUP(B140,Referencias!$B$7:$C$154,2,FALSE),"") | D140: =SUMIF(Trabajos!$E$5:$E$394,B140,Trabajos!$P$5:$P$394)+SUMIF('Trabajos 2'!$E$5:$E$156,B140,'Trabajos 2'!$P$5:$P$156) -> 0 | E140: =SUMIF(Ingresos!$C$6:$C$115,B140,Ingresos!$E$6:$E$115) -> 0 | F140: =E140-D140 -> 0
B141: Total | D141: =SUM(D5:D130) -> 2.476214e+08 | E141: =SUM(E5:E130) -> 2.4468884e+08 | F141: =SUM(F5:F130) -> -2932564.9

Sheet Ingresos
B2: Ingresos | K2: Movimientos
P3: Ingreso por facturacion | S3: Saldo movimientos | V3: Ingreso percibido | Y3: Ingreso total a percibir | AB3: Gastos | AE3: Saldo ingreso
P4: Paco | Q4: Tomas | S4: Paco | T4: Tomas | V4: Paco | W4: Tomas | Y4: Paco | Z4: Tomas | AB4: Paco | AC4: Tomas | AE4: Paco | AF4: Tomas
B5: Fecha | C5: Cod. Cliente | D5: Cliente | E5: Importe | F5: IVA | G5: Impuestos | H5: Total | I5: Cobrado | K5: Fecha | L5: De | M5: Para | N5: Importe | P5: =SUMIF(I6:I115,P4,H6:H115) -> 79185150 | Q5: =SUMIF(I6:I115,Q4,H6:H115) -> 1.6823207e+08 | S5: =(SUMIF(M6:M116,S4,N6:N116)-SUMIF(L6:L116,S4,N6:N116)) -> 25300000 | T5: =(SUMIF(M6:M116,T4,N6:N116)-SUMIF(L6:L116,T4,N6:N116)) -> -25300000 | V5: =P5+S5 -> 1.0448515e+08 | W5: =Q5+T5 -> 1.4293207e+08 | Y5: =IFERROR(Asignación!O8+'Asignación 2'!O8,"") -> 1.1064992e+08 | Z5: =IFERROR(Asignación!P8+'Asignación 2'!P8,"") -> 1.2553274e+08 | AB5: =Gastos!Q5 -> -10544166 | AC5: =Gastos!P5 -> 10544166 | AE5: =Y5-V5+AB5 -> -4379393.4 | AF5: =Z5-W5+AC5 -> -6855169.1
B6: 45947 | C6: 76 | D6: =IFERROR(VLOOKUP(C6,Referencias!$B$7:$C$154,2,FALSE),"") -> Bruno Fioriti | E6: 734290 | H6: =IF(E6<>"",E6-E6*G6,"") -> 734290 | I6: Tomas | K6: 45946 | L6: Paco | M6: Tomas | N6: 200000
B7: 45954 | C7: 50 | D7: =IFERROR(VLOOKUP(C7,Referencias!$B$7:$C$154,2,FALSE),"") -> Mackrey Agropecuaria | E7: 153100 | H7: =IF(E7<>"",E7-E7*G7,"") -> 153100 | I7: Tomas | K7: 46016 | L7: Tomas | M7: Paco | N7: 700000 | AE7: =1-(AE5/Y5) -> 1.0395788 | AF7: =1-(AF5/Z5) -> 1.0546086
B8: 45954 | C8: 33 | D8: =IFERROR(VLOOKUP(C8,Referencias!$B$7:$C$154,2,FALSE),"") -> Espartina S.A. | E8: 4313044.7 | H8: =IF(E8<>"",E8-E8*G8,"") -> 4313044.7 | I8: Tomas | K8: 46383 | L8: Tomas | M8: Paco | N8: 800000
B9: 45961 | C9: 17 | D9: =IFERROR(VLOOKUP(C9,Referencias!$B$7:$C$154,2,FALSE),"") -> Campo Maipu S.A. | E9: 1428485 | H9: =IF(E9<>"",E9-E9*G9,"") -> 1428485 | I9: Tomas | K9: 46024 | L9: Tomas | M9: Paco | N9: 1500000
B10: 45979 | C10: 98 | D10: =IFERROR(VLOOKUP(C10,Referencias!$B$7:$C$154,2,FALSE),"") -> Inalco | E10: 1118625 | H10: =IF(E10<>"",E10-E10*G10,"") -> 1118625 | I10: Paco | K10: 46024 | L10: Tomas | M10: Paco | N10: 1500000
B11: 45952 | C11: 33 | D11: =IFERROR(VLOOKUP(C11,Referencias!$B$7:$C$154,2,FALSE),"") -> Espartina S.A. | E11: 2488971.7 | H11: =IF(E11<>"",E11-E11*G11,"") -> 2488971.7 | I11: Paco | K11: 46027 | L11: Tomas | M11: Paco | N11: 2000000
B12: 45967 | C12: 33 | D12: =IFERROR(VLOOKUP(C12,Referencias!$B$7:$C$154,2,FALSE),"") -> Espartina S.A. | E12: 4687421.8 | H12: =IF(E12<>"",E12-E12*G12,"") -> 4687421.8 | I12: Paco | K12: 46027 | L12: Tomas | M12: Paco | N12: 2000000
B13: 45983 | C13: 33 | D13: =IFERROR(VLOOKUP(C13,Referencias!$B$7:$C$154,2,FALSE),"") -> Espartina S.A. | E13: 6095843.2 | H13: =IF(E13<>"",E13-E13*G13,"") -> 6095843.2 | I13: Paco | K13: 46043 | L13: Tomas | M13: Paco | N13: 15500000
B14: 45952 | C14: 33 | D14: =IFERROR(VLOOKUP(C14,Referencias!$B$7:$C$154,2,FALSE),"") -> Espartina S.A. | E14: 6284493.5 | H14: =IF(E14<>"",E14-E14*G14,"") -> 6284493.5 | I14: Tomas | K14: 46225 | L14: Tomas | M14: Paco | N14: 1500000
B15: 45962 | C15: 40 | D15: =IFERROR(VLOOKUP(C15,Referencias!$B$7:$C$154,2,FALSE),"") -> Cía. de Tierras Sud Argentino S.A. | E15: 4628250 | H15: =IF(E15<>"",E15-E15*G15,"") -> 4628250 | I15: Tomas
B16: 45980 | C16: 118 | D16: =IFERROR(VLOOKUP(C16,Referencias!$B$7:$C$154,2,FALSE),"") -> Juan Ignacio Franco | E16: 668347.5 | H16: =IF(E16<>"",E16-E16*G16,"") -> 668347.5 | I16: Tomas
B17: 45989 | C17: 4 | D17: =IFERROR(VLOOKUP(C17,Referencias!$B$7:$C$154,2,FALSE),"") -> Purtierra | E17: 955000 | H17: =IF(E17<>"",E17-E17*G17,"") -> 955000 | I17: Tomas
B18: 45989 | C18: 4 | D18: =IFERROR(VLOOKUP(C18,Referencias!$B$7:$C$154,2,FALSE),"") -> Purtierra | E18: 955000 | H18: =IF(E18<>"",E18-E18*G18,"") -> 955000 | I18: Paco
B19: 45989 | C19: 124 | D19: =IFERROR(VLOOKUP(C19,Referencias!$B$7:$C$154,2,FALSE),"") -> Cristian Perez Maraviglia | E19: 131541.25 | H19: =IF(E19<>"",E19-E19*G19,"") -> 131541.25 | I19: Tomas
B20: 45989 | C20: 124 | D20: =IFERROR(VLOOKUP(C20,Referencias!$B$7:$C$154,2,FALSE),"") -> Cristian Perez Maraviglia | E20: 131541.25 | H20: =IF(E20<>"",E20-E20*G20,"") -> 131541.25 | I20: Paco
B21: 45989 | C21: 6 | D21: =IFERROR(VLOOKUP(C21,Referencias!$B$7:$C$154,2,FALSE),"") -> La Nany S.A. | E21: 2000000 | H21: =IF(E21<>"",E21-E21*G21,"") -> 2000000 | I21: Tomas
B22: 45992 | C22: 122 | D22: =IFERROR(VLOOKUP(C22,Referencias!$B$7:$C$154,2,FALSE),"") -> Martin Juarez | E22: 133830 | H22: =IF(E22<>"",E22-E22*G22,"") -> 133830 | I22: Paco
B23: 45992 | C23: 122 | D23: =IFERROR(VLOOKUP(C23,Referencias!$B$7:$C$154,2,FALSE),"") -> Martin Juarez | E23: 646642 | H23: =IF(E23<>"",E23-E23*G23,"") -> 646642 | I23: Paco
B24: 45992 | C24: 125 | D24: =IFERROR(VLOOKUP(C24,Referencias!$B$7:$C$154,2,FALSE),"") -> Soledad Gutierrez | E24: 585600 | H24: =IF(E24<>"",E24-E24*G24,"") -> 585600 | I24: Tomas
B25: 45993 | C25: 126 | D25: =IFERROR(VLOOKUP(C25,Referencias!$B$7:$C$154,2,FALSE),"") -> Patricia Ricci | E25: 509662.5 | H25: =IF(E25<>"",E25-E25*G25,"") -> 509662.5 | I25: Tomas
B26: 45994 | C26: 6 | D26: =IFERROR(VLOOKUP(C26,Referencias!$B$7:$C$154,2,FALSE),"") -> La Nany S.A. | E26: 3395993.8 | H26: =IF(E26<>"",E26-E26*G26,"") -> 3395993.8 | I26: Tomas
... B104: 46227 | C104: 33 | D104: =IFERROR(VLOOKUP(C104,Referencias!$B$7:$C$154,2,FALSE),"") -> Espartina S.A. | E104: 1780952.4 | H104: =IF(E104<>"",E104-E104*G104,"") -> 1780952.4 | I104: Tomas
D105: =IFERROR(VLOOKUP(C105,Referencias!$B$7:$C$154,2,FALSE),"") | H105: =IF(E105<>"",E105-E105*G105,"")
D106: =IFERROR(VLOOKUP(C106,Referencias!$B$7:$C$154,2,FALSE),"") | H106: =IF(E106<>"",E106-E106*G106,"")
D107: =IFERROR(VLOOKUP(C107,Referencias!$B$7:$C$154,2,FALSE),"") | H107: =IF(E107<>"",E107-E107*G107,"")
D108: =IFERROR(VLOOKUP(C108,Referencias!$B$7:$C$154,2,FALSE),"") | H108: =IF(E108<>"",E108-E108*G108,"")
D109: =IFERROR(VLOOKUP(C109,Referencias!$B$7:$C$154,2,FALSE),"") | H109: =IF(E109<>"",E109-E109*G109,"")
D110: =IFERROR(VLOOKUP(C110,Referencias!$B$7:$C$154,2,FALSE),"") | H110: =IF(E110<>"",E110-E110*G110,"")
D111: =IFERROR(VLOOKUP(C111,Referencias!$B$7:$C$154,2,FALSE),"") | H111: =IF(E111<>"",E111-E111*G111,"")
D112: =IFERROR(VLOOKUP(C112,Referencias!$B$7:$C$154,2,FALSE),"") | H112: =IF(E112<>"",E112-E112*G112,"")
D113: =IFERROR(VLOOKUP(C113,Referencias!$B$7:$C$154,2,FALSE),"") | H113: =IF(E113<>"",E113-E113*G113,"")
D114: =IFERROR(VLOOKUP(C114,Referencias!$B$7:$C$154,2,FALSE),"") | H114: =IF(E114<>"",E114-E114*G114,"")
D115: =IFERROR(VLOOKUP(C115,Referencias!$B$7:$C$154,2,FALSE),"") | H115: =IF(E115<>"",E115-E115*G115,"")
B116: Total | E116: =SUM(E6:E115) -> 2.4741722e+08 | H116: =SUM(H6:H115) -> 2.4741722e+08

Sheet Empleados
B2: Empleados
H3: =SUBTOTAL(9,H5:H415) -> 38775952
B4: Fecha | C4: Nombre | D4: Jornada | E4: Valor | F4: Km | G4: Valor | H4: Total | J4: Empleado | K4: Ingreso
B5: 45912 | C5: Agustin Acosta | D5: 1 | E5: 50000 | F5: 291 | G5: 543.3 | H5: =D5*E5+F5*G5 -> 208100.3 | J5: Ezequiel Villar | K5: =SUMIF(C5:C415,J5,H5:H415) -> 300000
B6: 45913 | C6: Juan Manuel Mateos | D6: 1 | E6: 65000 | H6: =D6*E6+F6*G6 -> 65000 | J6: Juan Manuel Mateos | K6: =SUMIF(C5:C415,J6,H5:H415) -> 1870000
B7: 45913 | C7: Facundo Kaplun | D7: 1 | E7: 65000 | F7: 183 | G7: 557.7 | H7: =D7*E7+F7*G7 -> 167059.1 | J7: Martin De Luca | K7: =SUMIF(C5:C415,J7,H5:H415) -> 664521.5
B8: 45913 | C8: Ezequiel Villar | D8: 1 | E8: 50000 | H8: =D8*E8+F8*G8 -> 50000 | J8: Denis Moler | K8: =SUMIF(C5:C415,J8,H5:H415) -> 400000
B9: 45914 | C9: Facundo Kaplun | D9: 1 | E9: 50000 | F9: 14 | G9: 557.7 | H9: =D9*E9+F9*G9 -> 57807.8 | J9: Miguel Rybar | K9: =SUMIF(C5:C415,J9,H5:H415) -> 3242500
B10: 45914 | C10: Denis Moler | D10: 1 | E10: 50000 | H10: =D10*E10+F10*G10 -> 50000 | J10: Damian Diez | K10: =SUMIF(C5:C415,J10,H5:H415) -> 1413487.4
B11: 45914 | C11: Damian Diez | D11: 1 | E11: 65000 | F11: 145 | G11: 633.85 | H11: =D11*E11+F11*G11 -> 156908.25 | J11: Laureano Camino | K11: =SUMIF(C5:C415,J11,H5:H415) -> 150000
B12: 45915 | C12: Facundo Kaplun | D12: 1 | E12: 80000 | F12: 168 | G12: 557.7 | H12: =D12*E12+F12*G12 -> 173693.6 | J12: Pilar Amendola | K12: =SUMIF(C5:C415,J12,H5:H415) -> 465000
B13: 45915 | C13: Juan Manuel Mateos | D13: 1 | E13: 80000 | H13: =D13*E13+F13*G13 -> 80000 | J13: Abelardo Hansen | K13: =SUMIF(C5:C415,J13,H5:H415) -> 1157500
B14: 45915 | C14: Abelardo Hansen | D14: 1 | E14: 80000 | H14: =D14*E14+F14*G14 -> 80000 | J14: Facundo Kaplun | K14: =SUMIF(C5:C415,J14,H5:H415) -> 6572632.1
B15: 45916 | C15: Facundo Kaplun | D15: 1 | E15: 65000 | F15: 395 | G15: 557.7 | H15: =D15*E15+F15*G15 -> 285291.5 | J15: Alexis Marsico | K15: =SUMIF(C5:C415,J15,H5:H415) -> 1975000
B16: 45916 | C16: Juan Manuel Mateos | D16: 1 | E16: 65000 | H16: =D16*E16+F16*G16 -> 65000 | J16: Cecilia Aristemuño | K16: =SUMIF(C5:C415,J16,H5:H415) -> 800000
B17: 45916 | C17: Abelardo Hansen | D17: 1 | E17: 65000 | H17: =D17*E17+F17*G17 -> 65000 | J17: Roberto Cabrera | K17: =SUMIF(C5:C415,J17,H5:H415) -> 150000
B18: 45916 | C18: Alexis Marsico | D18: 1 | E18: 50000 | H18: =D18*E18+F18*G18 -> 50000 | J18: Mateo Mesa | K18: =SUMIF(C5:C415,J18,H5:H415) -> 125000
B19: 45916 | C19: Cecilia Aristemuño | D19: 1 | E19: 50000 | H19: =D19*E19+F19*G19 -> 50000 | J19: Agustin Acosta | K19: =SUMIF(C5:C415,J19,H5:H415) -> 2191918.2
B20: 45916 | C20: Pilar Amendola | D20: 1 | E20: 50000 | F20: 1 | G20: 65000 | H20: =D20*E20+F20*G20 -> 115000 | J20: Nicolas Gabriel | K20: =SUMIF(C5:C415,J20,H5:H415) -> 13139850
B21: 45917 | C21: Facundo Kaplun | D21: 1 | E21: 50000 | F21: 0 | G21: 557.7 | H21: =D21*E21+F21*G21 -> 50000 | J21: Martin Paci Palmas | K21: =SUMIF(C5:C415,J21,H5:H415) -> 50000
B22: 45917 | C22: Juan Manuel Mateos | D22: 1 | E22: 50000 | H22: =D22*E22+F22*G22 -> 50000 | J22: Federico Martinez | K22: =SUMIF(C6:C416,J22,H6:H416) -> 428624
B23: 45917 | C23: Denis Moler | D23: 1 | E23: 50000 | H23: =D23*E23+F23*G23 -> 50000 | J23: Martin Saffarano | K23: =SUMIF(C7:C417,J23,H7:H417) -> 1429918.6
B24: 45917 | C24: Alexis Marsico | D24: 1 | E24: 50000 | H24: =D24*E24+F24*G24 -> 50000 | J24: Mariano Rodriguez | K24: =SUMIF(C8:C418,J24,H8:H418) -> 300000
B25: 45917 | C25: Cecilia Aristemuño | D25: 1 | E25: 50000 | H25: =D25*E25+F25*G25 -> 50000 | J25: Francisco Llanos | K25: =SUMIF(C9:C419,J25,H9:H419) -> 125000
B26: 45917 | C26: Pilar Amendola | D26: 1 | E26: 50000 | H26: =D26*E26+F26*G26 -> 50000 | J26: Matias Lamorte | K26: =SUMIF(C5:C415,J26,H5:H415) -> 550000
B27: 45918 | C27: Facundo Kaplun | D27: 0.5 | E27: 50000 | F27: 35 | G27: 557.7 | H27: =D27*E27+F27*G27 -> 44519.5 | J27: Nicolas Avellaneda | K27: =SUMIF(C5:C415,J27,H5:H415) -> 725000
B28: 45918 | C28: Juan Manuel Mateos | D28: 1 | E28: 50000 | H28: =D28*E28+F28*G28 -> 50000 | J28: Alejandro Tur | K28: =SUMIF(C5:C415,J28,H5:H415) -> 250000
B29: 45918 | C29: Denis Moler | D29: 1 | E29: 50000 | H29: =D29*E29+F29*G29 -> 50000
B30: 45918 | C30: Alexis Marsico | D30: 1 | E30: 50000 | H30: =D30*E30+F30*G30 -> 50000
B31: 45918 | C31: Cecilia Aristemuño | D31: 1 | E31: 50000 | H31: =D31*E31+F31*G31 -> 50000
B32: 45918 | C32: Pilar Amendola | D32: 1 | E32: 50000 | H32: =D32*E32+F32*G32 -> 50000
B33: 45918 | C33: Martin De Luca | D33: 1 | E33: 50000 | F33: 240 | G33: 543.3 | H33: =D33*E33+F33*G33 -> 180392
B34: 45922 | C34: Alexis Marsico | D34: 1 | E34: 50000 | H34: =D34*E34+F34*G34 -> 50000
B35: 45922 | C35: Cecilia Aristemuño | D35: 1 | E35: 50000 | H35: =D35*E35+F35*G35 -> 50000
B36: 45922 | C36: Pilar Amendola | D36: 1 | E36: 50000 | H36: =D36*E36+F36*G36 -> 50000
B37: 45922 | C37: Mateo Mesa | D37: 0.5 | E37: 50000 | H37: =D37*E37+F37*G37 -> 25000
B38: 45922 | C38: Francisco Llanos | D38: 0.5 | E38: 50000 | H38: =D38*E38+F38*G38 -> 25000
B39: 45923 | C39: Alexis Marsico | D39: 1 | E39: 50000 | H39: =D39*E39+F39*G39 -> 50000
B40: 45923 | C40: Cecilia Aristemuño | D40: 1 | E40: 50000 | H40: =D40*E40+F40*G40 -> 50000
B41: 45923 | C41: Pilar Amendola | D41: 1 | E41: 50000 | H41: =D41*E41+F41*G41 -> 50000
B42: 45923 | C42: Mateo Mesa | D42: 1 | E42: 50000 | H42: =D42*E42+F42*G42 -> 50000
B43: 45923 | C43: Francisco Llanos | D43: 1 | E43: 50000 | H43: =D43*E43+F43*G43 -> 50000
B44: 45923 | C44: Facundo Kaplun | D44: 1 | E44: 50000 | F44: 0 | G44: 557.7 | H44: =D44*E44+F44*G44 -> 50000
B45: 45923 | C45: Juan Manuel Mateos | D45: 1 | E45: 50000 | H45: =D45*E45+F45*G45 -> 50000
B46: 45923 | C46: Abelardo Hansen | D46: 1 | E46: 50000 | H46: =D46*E46+F46*G46 -> 50000
B47: 45924 | C47: Facundo Kaplun | D47: 1 | E47: 50000 | F47: 385 | G47: 557.7 | H47: =D47*E47+F47*G47 -> 264714.5
B48: 45924 | C48: Juan Manuel Mateos | D48: 1 | E48: 50000 | H48: =D48*E48+F48*G48 -> 50000
B49: 45924 | C49: Abelardo Hansen | D49: 1 | E49: 50000 | H49: =D49*E49+F49*G49 -> 50000
B50: 45924 | C50: Alexis Marsico | D50: 1 | E50: 50000 | H50: =D50*E50+F50*G50 -> 50000
B51: 45924 | C51: Cecilia Aristemuño | D51: 1 | E51: 50000 | H51: =D51*E51+F51*G51 -> 50000
B52: 45924 | C52: Pilar Amendola | D52: 1 | E52: 50000 | H52: =D52*E52+F52*G52 -> 50000
B53: 45924 | C53: Mateo Mesa | D53: 1 | E53: 50000 | H53: =D53*E53+F53*G53 -> 50000
B54: 45924 | C54: Francisco Llanos | D54: 1 | E54: 50000 | H54: =D54*E54+F54*G54 -> 50000
B55: 45925 | C55: Martin De Luca | D55: 1 | E55: 50000 | F55: 230 | G55: 543.3 | H55: =D55*E55+F55*G55 -> 174959
B56: 45925 | C56: Agustin Acosta | D56: 1 | E56: 50000 | F56: 88 | G56: 543.3 | H56: =D56*E56+F56*G56 -> 97810.4
B57: 45925 | C57: Facundo Kaplun | D57: 1 | E57: 65000 | F57: 0 | G57: 557.7 | H57: =D57*E57+F57*G57 -> 65000
B58: 45925 | C58: Abelardo Hansen | D58: 1 | E58: 70000 | H58: =D58*E58+F58*G58 -> 70000
B59: 45925 | C59: Roberto Cabrera | D59: 1 | E59: 50000 | H59: =D59*E59+F59*G59 -> 50000
B60: 45925 | C60: Federico Martinez | D60: 1 | E60: 50000 | H60: =D60*E60+F60*G60 -> 50000
B61: 45925 | C61: Juan Manuel Mateos | D61: 1 | E61: 50000 | H61: =D61*E61+F61*G61 -> 50000
B62: 45925 | C62: Alexis Marsico | D62: 1 | E62: 50000 | H62: =D62*E62+F62*G62 -> 50000
B63: 45925 | C63: Cecilia Aristemuño | D63: 1 | E63: 50000 | H63: =D63*E63+F63*G63 -> 50000
B64: 45925 | C64: Pilar Amendola | D64: 1 | E64: 50000 | H64: =D64*E64+F64*G64 -> 50000
B65: 45926 | C65: Alexis Marsico | D65: 1 | E65: 50000 | H65: =D65*E65+F65*G65 -> 50000
B66: 45926 | C66: Cecilia Aristemuño | D66: 1 | E66: 50000 | H66: =D66*E66+F66*G66 -> 50000
B67: 45926 | C67: Pilar Amendola | D67: 1 | E67: 50000 | H67: =D67*E67+F67*G67 -> 50000
B68: 45926 | C68: Damian Diez | D68: 1 | E68: 65000 | F68: 90 | G68: 633.85 | H68: =D68*E68+F68*G68 -> 122046.5
B69: 45926 | C69: Juan Manuel Mateos | D69: 1 | E69: 65000 | H69: =D69*E69+F69*G69 -> 65000
B70: 45926 | C70: Denis Moler | D70: 1 | E70: 50000 | H70: =D70*E70+F70*G70 -> 50000
B71: 45926 | C71: Federico Martinez | D71: 1 | E71: 50000 | H71: =D71*E71+F71*G71 -> 50000
B72: 45926 | C72: Agustin Acosta | D72: 1 | E72: 50000 | F72: 0 | G72: 543.3 | H72: =D72*E72+F72*G72 -> 50000
B73: 45929 | C73: Alexis Marsico | D73: 1 | E73: 50000 | H73: =D73*E73+F73*G73 -> 50000
B74: 45929 | C74: Cecilia Aristemuño | D74: 1 | E74: 50000 | H74: =D74*E74+F74*G74 -> 50000
B75: 45929 | C75: Facundo Kaplun | D75: 1 | E75: 50000 | F75: 0 | G75: 557.7 | H75: =D75*E75+F75*G75 -> 50000
B76: 45929 | C76: Abelardo Hansen | D76: 1 | E76: 50000 | H76: =D76*E76+F76*G76 -> 50000
B77: 45929 | C77: Federico Martinez | D77: 1 | E77: 50000 | H77: =D77*E77+F77*G77 -> 50000
B78: 45929 | C78: Juan Manuel Mateos | D78: 1 | E78: 50000 | H78: =D78*E78+F78*G78 -> 50000
B79: 45930 | C79: Alexis Marsico | D79: 1 | E79: 50000 | H79: =D79*E79+F79*G79 -> 50000
B80: 45930 | C80: Cecilia Aristemuño | D80: 1 | E80: 50000 | H80: =D80*E80+F80*G80 -> 50000
B81: 45930 | C81: Roberto Cabrera | D81: 1 | E81: 50000 | H81: =D81*E81+F81*G81 -> 50000
B82: 45930 | C82: Federico Martinez | D82: 1 | E82: 50000 | H82: =D82*E82+F82*G82 -> 50000
B83: 45930 | C83: Abelardo Hansen | D83: 1 | E83: 62500 | H83: =D83*E83+F83*G83 -> 62500
B84: 45930 | C84: Facundo Kaplun | D84: 1 | E84: 65000 | F84: 276 | G84: 557.7 | H84: =D84*E84+F84*G84 -> 218925.2
B85: 45930 | C85: Denis Moler | D85: 1 | E85: 50000 | H85: =D85*E85+F85*G85 -> 50000
B86: 45930 | C86: Nicolas Gabriel | D86: 1 | E86: 50000 | H86: =D86*E86+F86*G86 -> 50000
B87: 45931 | C87: Alexis Marsico | D87: 1 | E87: 50000 | H87: =D87*E87+F87*G87 -> 50000
B88: 45931 | C88: Nicolas Gabriel | D88: 1 | E88: 50000 | F88: 300 | G88: 543.3 | H88: =D88*E88+F88*G88 -> 212990
B89: 45931 | C89: Abelardo Hansen | D89: 1 | E89: 65000 | H89: =D89*E89+F89*G89 -> 65000
B90: 45931 | C90: Federico Martinez | D90: 1 | E90: 50000 | F90: 156 | G90: 504 | H90: =D90*E90+F90*G90 -> 128624
B91: 45931 | C91: Facundo Kaplun | D91: 1 | E91: 65000 | F91: 0 | G91: 557.7 | H91: =D91*E91+F91*G91 -> 65000
B92: 45931 | C92: Juan Manuel Mateos | D92: 1 | E92: 65000 | H92: =D92*E92+F92*G92 -> 65000
B93: 45931 | C93: Denis Moler | D93: 1 | E93: 50000 | H93: =D93*E93+F93*G93 -> 50000
B94: 45932 | C94: Alexis Marsico | D94: 1 | E94: 50000 | H94: =D94*E94+F94*G94 -> 50000
B95: 45932 | C95: Nicolas Gabriel | D95: 1 | E95: 50000 | H95: =D95*E95+F95*G95 -> 50000
B96: 45932 | C96: Facundo Kaplun | D96: 1 | E96: 65000 | F96: 0 | G96: 557.7 | H96: =D96*E96+F96*G96 -> 65000
B97: 45932 | C97: Juan Manuel Mateos | D97: 1 | E97: 50000 | H97: =D97*E97+F97*G97 -> 50000
B98: 45932 | C98: Federico Martinez | D98: 1 | E98: 50000 | H98: =D98*E98+F98*G98 -> 50000
B99: 45933 | C99: Alexis Marsico | D99: 1 | E99: 50000 | H99: =D99*E99+F99*G99 -> 50000
B100: 45933 | C100: Nicolas Gabriel | D100: 1 | E100: 50000 | H100: =D100*E100+F100*G100 -> 50000
B101: 45933 | C101: Agustin Acosta | D101: 1 | E101: 50000 | F101: 186 | G101: 543.3 | H101: =D101*E101+F101*G101 -> 151053.8
...

Sheet Terciarizados
B2: Terciarizados
J3: =SUBTOTAL(9,J5:J291) -> 623218.9
B4: Fecha | C4: Nombre | D4: Establecimiento | E4: Tipo de Trabajo | F4: Has | G4: Valor | H4: Km | I4: Valor | J4: Total | L4: Terciarizado | M4: Ingreso
B5: 45940 | C5: Colo Moser | D5: El Pampero | E5: Monitoreo de bb y bab | F5: 93 | G5: 2.5 | H5: 72 | I5: 650 | J5: =F5*G5+H5*I5 -> 47032.5 | L5: Colo Moser | M5: =SUMIF(C5:C291,L5,J5:J291) -> 788637.5
B6: 45941 | C6: Damian Diez | D6: Ojo de Agua | E6: Aplicación de cebo | F6: 137 | G6: 4 | H6: 90 | I6: 0.35 | J6: =F6*G6+H6*I6 -> 579.5 | L6: Damian Diez | M6: =SUMIF(C5:C291,L6,J5:J291) -> 1433140.9
B7: 45945 | C7: Damian Diez | D7: Don Gustavo | E7: Aplicación de cebo | F7: 77 | G7: 4 | H7: 370 | I7: 0.35 | J7: =F7*G7+H7*I7 -> 437.5 | L7: Pablo Flesborg | M7: =SUMIF(C5:C291,L7,J5:J291) -> 3102
B8: 45945 | C8: Damian Diez | D8: Macedo | E8: Aplicación de cebo | F8: 36 | G8: 4 | H8: 0 | I8: 0.35 | J8: =F8*G8+H8*I8 -> 144 | M8: =SUMIF(C5:C291,L8,J5:J291) -> 0
B9: 45946 | C9: Damian Diez | D9: San Esteban | E9: Aplicación de cebo | F9: 52 | G9: 4 | H9: 350 | I9: 0.35 | J9: =F9*G9+H9*I9 -> 330.5 | M9: =SUMIF(C5:C291,L9,J5:J291) -> 0
B10: 45949 | C10: Damian Diez | D10: La Alborada | E10: Aplicación de cebo | F10: 107 | G10: 4 | H10: 150 | I10: 0.35 | J10: =F10*G10+H10*I10 -> 480.5 | M10: =SUMIF(C5:C291,L10,J5:J291) -> 0
B11: 45951 | C11: Damian Diez | D11: La Paulina | E11: Aplicación de cebo | F11: 107 | G11: 4 | H11: 260 | I11: 0.35 | J11: =F11*G11+H11*I11 -> 519 | M11: =SUMIF(C5:C291,L11,J5:J291) -> 0
B12: 45953 | C12: Damian Diez | D12: Aitona | E12: Aplicación de cebo | F12: 113 | G12: 4 | H12: 160 | I12: 0.35 | J12: =F12*G12+H12*I12 -> 508 | M12: =SUMIF(C5:C291,L12,J5:J291) -> 0
B13: 45957 | C13: Damian Diez | D13: El Basural | E13: Aplicación de cebo | F13: 65 | G13: 4 | H13: 212 | I13: 0.35 | J13: =F13*G13+H13*I13 -> 334.2 | M13: =SUMIF(C5:C291,L13,J5:J291) -> 0
B14: 45958 | C14: Damian Diez | D14: El Moro Viejo | E14: Aplicación de cebo | F14: 57 | G14: 4 | H14: 156 | I14: 0.35 | J14: =F14*G14+H14*I14 -> 282.6 | M14: =SUMIF(C5:C291,L14,J5:J291) -> 0
B15: 45959 | C15: Damian Diez | D15: La Paulina | E15: Aplicación de cebo | F15: 137 | G15: 4 | H15: 260 | I15: 0.35 | J15: =F15*G15+H15*I15 -> 639 | M15: =SUMIF(C5:C291,L15,J5:J291) -> 0
B16: 45960 | C16: Damian Diez | D16: Los Tulipanes | E16: Aplicación de cebo | F16: 91 | G16: 4 | H16: 180 | I16: 0.35 | J16: =F16*G16+H16*I16 -> 427 | M16: =SUMIF(C5:C291,L16,J5:J291) -> 0
B17: 45960 | C17: Damian Diez | D17: La Mylucha | E17: Aplicación de cebo | F17: 75 | G17: 4 | H17: 40 | I17: 0.35 | J17: =F17*G17+H17*I17 -> 314 | M17: =SUMIF(C5:C291,L17,J5:J291) -> 0
B18: 45963 | C18: Damian Diez | D18: Montiel | E18: Aplicación de cebo | F18: 100 | G18: 4 | H18: 240 | I18: 0.35 | J18: =F18*G18+H18*I18 -> 484 | M18: =SUMIF(C5:C291,L18,J5:J291) -> 0
B19: 45966 | C19: Damian Diez | D19: Las Bagualas | E19: Aplicación de cebo | F19: 118 | G19: 4 | H19: 176 | I19: 0.35 | J19: =F19*G19+H19*I19 -> 533.6 | M19: =SUMIF(C5:C291,L19,J5:J291) -> 0
B20: 45966 | C20: Colo Moser | D20: La Tolderia | E20: Monitoreo de bb y bab | F20: 188 | G20: 2.5 | H20: 118 | I20: 650 | J20: =F20*G20+H20*I20 -> 77170 | M20: =SUMIF(C5:C291,L20,J5:J291) -> 0
B21: 45967 | C21: Damian Diez | D21: La Paulina | E21: Aplicación de cebo | F21: 169 | G21: 4 | H21: 260 | I21: 0.35 | J21: =F21*G21+H21*I21 -> 767 | M21: =SUMIF(C5:C291,L21,J5:J291) -> 0
B22: 45967 | C22: Colo Moser | D22: La Providencia | E22: Aplicación de cebo | F22: 98 | G22: 5 | H22: 340 | I22: 650 | J22: =F22*G22+H22*I22 -> 221490
B23: 45955 | C23: Juan Ignacio Thomas | D23: San Lorenzo | E23: Aplicación de cebo | F23: 45 | G23: 4 | H23: 95 | I23: 0.35 | J23: =F23*G23+H23*I23 -> 213.25
B24: 45957 | C24: Juan Ignacio Thomas | D24: San Lorenzo | E24: Aplicación de cebo | F24: 41 | G24: 4 | H24: 125 | I24: 0.35 | J24: =F24*G24+H24*I24 -> 207.75
B25: 45958 | C25: Juan Ignacio Thomas | D25: Costa del Moro | E25: Monitoreo de bb y bab | F25: 90 | G25: 2.5 | H25: 128 | I25: 0.35 | J25: =F25*G25+H25*I25 -> 269.8
B26: 45959 | C26: Juan Ignacio Thomas | D26: Los Charitos | E26: Aplicación de cebo | F26: 79 | G26: 4 | H26: 194 | I26: 0.35 | J26: =F26*G26+H26*I26 -> 383.9
B27: 45964 | C27: Juan Ignacio Thomas | D27: San Narciso | E27: Aplicación de cebo | F27: 130 | G27: 4 | H27: 146 | I27: 0.35 | J27: =F27*G27+H27*I27 -> 571.1
B28: 45962 | C28: Pablo Flesborg | D28: Tres Marias | E28: Aplicación de cebo | F28: 225 | G28: 3 | H28: 0 | I28: 0.35 | J28: =F28*G28+H28*I28 -> 675
B29: 45962 | C29: Pablo Flesborg | D29: Santa Isabel Cozumel | E29: Aplicación de cebo | F29: 128 | G29: 3 | H29: 0 | I29: 0.35 | J29: =F29*G29+H29*I29 -> 384
B30: 45962 | C30: Pablo Flesborg | D30: El Alivio | E30: Aplicación de cebo | F30: 174 | G30: 3 | H30: 0 | I30: 0.35 | J30: =F30*G30+H30*I30 -> 522
B31: 45975 | C31: Pablo Flesborg | D31: Mallinco | E31: Aplicación de cebo | F31: 108 | G31: 3 | H31: 0 | I31: 0.35 | J31: =F31*G31+H31*I31 -> 324
B32: 45968 | C32: Colo Moser | D32: La Barrancosa | E32: Aplicación de cebo | F32: 115 | G32: 4 | H32: 396 | I32: 650 | J32: =F32*G32+H32*I32 -> 257860
B33: 45969 | C33: Colo Moser | D33: Tres Lagunas | E33: Aplicación de cebo | F33: 35 | G33: 5 | H33: 0 | I33: 650 | J33: =F33*G33+H33*I33 -> 175
... B67: 45992 | C67: Pablo Flesborg | D67: San Francisco Bellocq | E67: Aplicación de cebo | F67: 298 | G67: 3 | H67: 0 | I67: 0.35 | J67: =F67*G67+H67*I67 -> 894
B68: 46037 | C68: Damian Diez | D68: La Margarita | E68: Muestreo de suelo | F68: 7 | G68: 25000 | I68: 0.35 | J68: =F68*G68+H68*I68 -> 175000
B69: 46038 | C69: Damian Diez | D69: La Margarita | E69: Muestreo de suelo | F69: 10 | G69: 25000 | I69: 0.35 | J69: =F69*G69+H69*I69 -> 250000
B70: 46039 | C70: Pablo Flesborg | D70: Mallinco | E70: Aplicación de cebo | F70: 50 | G70: 3 | H70: 0 | I70: 0.35 | J70: =F70*G70+H70*I70 -> 150
J71: =F71*G71+H71*I71 -> 0
J72: =F72*G72+H72*I72 -> 0
J73: =F73*G73+H73*I73 -> 0
J74: =F74*G74+H74*I74 -> 0
J75: =F75*G75+H75*I75 -> 0
J76: =F76*G76+H76*I76 -> 0
J77: =F77*G77+H77*I77 -> 0
J78: =F78*G78+H78*I78 -> 0
J79: =F79*G79+H79*I79 -> 0
J80: =F80*G80+H80*I80 -> 0
J81: =F81*G81+H81*I81 -> 0
J82: =F82*G82+H82*I82 -> 0
... J291: =F291*G291+H291*I291 -> 0
J292: =SUM(J5:J291) -> 2230475.5

Sheet Asignación
B2: Asignación
H3: Despues de impuestos | J3: Asignacion | O3: Asignacion Ingreso
B4: Fecha trabajo | C4: Cliente | D4: Tipo de trabajo | E4: Importe | F4: Movilidad | G4: Impuesto | H4: Importe | I4: Movilidad | J4: Trabajo | K4: Empresa | L4: Movilidad | O4: Paco | P4: Tomas | Q4: Zoom
B5: =IF(Trabajos!B5="","",Trabajos!B5) -> 45909 | C5: =IF(Trabajos!F5="","",Trabajos!F5) -> Espartina S.A. | D5: =IF(Trabajos!D5="","",Trabajos!D5) -> Muestreo de suelos | E5: =IF(Trabajos!J5="","",Trabajos!J5) -> 75816.538 | F5: =IF(Trabajos!O5="","",Trabajos!O5) -> 0 | H5: =IF(Trabajos!H5<>"",E5-E5*G5,"") -> 75816.538 | I5: =IF(Trabajos!H5<>"",F5-F5*G5,"") -> 0 | J5: =IF(Trabajos!H5<>"",H5*0.55,"") -> 41699.096 | K5: =IF(Trabajos!H5<>"",H5*0.45,"") -> 34117.442 | L5: =IF(Trabajos!L5="","",Trabajos!L5) -> Tomas | N5: Trabajo | O5: =IFERROR((J349*Referencias!L8),"") -> 8404906.5 | P5: =IFERROR((J349*Referencias!M8),"") -> 13020344 | Q5: =IFERROR((J349*Referencias!N8),"") -> 84126215
B6: =IF(Trabajos!B6="","",Trabajos!B6) -> 45909 | C6: =IF(Trabajos!F6="","",Trabajos!F6) -> Espartina S.A. | D6: =IF(Trabajos!D6="","",Trabajos!D6) -> Muestreo de suelos | E6: =IF(Trabajos!J6="","",Trabajos!J6) -> 75816.538 | F6: =IF(Trabajos!O6="","",Trabajos!O6) -> 0 | H6: =IF(Trabajos!H6<>"",E6-E6*G6,"") -> 75816.538 | I6: =IF(Trabajos!H6<>"",F6-F6*G6,"") -> 0 | J6: =IF(Trabajos!H6<>"",H6*0.55,"") -> 41699.096 | K6: =IF(Trabajos!H6<>"",H6*0.45,"") -> 34117.442 | L6: =IF(Trabajos!L6="","",Trabajos!L6) -> Tomas | N6: Empresa | O6: =IFERROR((K349*Referencias!Q7),"") -> 43180145 | P6: =IFERROR((K349*Referencias!R7),"") -> 43180145
B7: =IF(Trabajos!B7="","",Trabajos!B7) -> 45909 | C7: =IF(Trabajos!F7="","",Trabajos!F7) -> Espartina S.A. | D7: =IF(Trabajos!D7="","",Trabajos!D7) -> Muestreo de suelos | E7: =IF(Trabajos!J7="","",Trabajos!J7) -> 75816.538 | F7: =IF(Trabajos!O7="","",Trabajos!O7) -> 0 | H7: =IF(Trabajos!H7<>"",E7-E7*G7,"") -> 75816.538 | I7: =IF(Trabajos!H7<>"",F7-F7*G7,"") -> 0 | J7: =IF(Trabajos!H7<>"",H7*0.55,"") -> 41699.096 | K7: =IF(Trabajos!H7<>"",H7*0.45,"") -> 34117.442 | L7: =IF(Trabajos!L7="","",Trabajos!L7) -> Tomas | N7: Viaticos | O7: =IFERROR((SUMIF(L5:L219,O4,I5:I219)),"") -> 5699856.2 | P7: =IFERROR((SUMIF(L5:L219,P4,I5:I219)),"") -> 3665508 | Q7: =IFERROR((SUMIF(L5:L219,Q4,I5:I219)),"") -> 8468296.6
B8: =IF(Trabajos!B8="","",Trabajos!B8) -> 45909 | C8: =IF(Trabajos!F8="","",Trabajos!F8) -> Espartina S.A. | D8: =IF(Trabajos!D8="","",Trabajos!D8) -> Muestreo de suelos | E8: =IF(Trabajos!J8="","",Trabajos!J8) -> 75816.538 | F8: =IF(Trabajos!O8="","",Trabajos!O8) -> 106002.4 | H8: =IF(Trabajos!H8<>"",E8-E8*G8,"") -> 75816.538 | I8: =IF(Trabajos!H8<>"",F8-F8*G8,"") -> 106002.4 | J8: =IF(Trabajos!H8<>"",H8*0.55,"") -> 41699.096 | K8: =IF(Trabajos!H8<>"",H8*0.45,"") -> 34117.442 | L8: =IF(Trabajos!L8="","",Trabajos!L8) -> Tomas | N8: Total | O8: =IFERROR((SUM(O5:O7)+Q5*Referencias!Q7+Q7*Referencias!Q7),"") -> 1.0358216e+08 | P8: =IFERROR((SUM(P5:P7)+Q5*Referencias!R7+Q7*Referencias!R7),"") -> 1.0616325e+08
B9: =IF(Trabajos!B9="","",Trabajos!B9) -> 45911 | C9: =IF(Trabajos!F9="","",Trabajos!F9) -> Espartina S.A. | D9: =IF(Trabajos!D9="","",Trabajos!D9) -> Muestreo de suelos | E9: =IF(Trabajos!J9="","",Trabajos!J9) -> 75816.538 | F9: =IF(Trabajos!O9="","",Trabajos!O9) -> 155547 | H9: =IF(Trabajos!H9<>"",E9-E9*G9,"") -> 75816.538 | I9: =IF(Trabajos!H9<>"",F9-F9*G9,"") -> 155547 | J9: =IF(Trabajos!H9<>"",H9*0.55,"") -> 41699.096 | K9: =IF(Trabajos!H9<>"",H9*0.45,"") -> 34117.442 | L9: =IF(Trabajos!L9="","",Trabajos!L9) -> Tomas | N9: Proporcion | O9: =IFERROR((O8/(O8+P8)),"") -> 0.49384709 | P9: =IFERROR((P8/(O8+P8)),"") -> 0.50615291
B10: =IF(Trabajos!B10="","",Trabajos!B10) -> 45911 | C10: =IF(Trabajos!F10="","",Trabajos!F10) -> Espartina S.A. | D10: =IF(Trabajos!D10="","",Trabajos!D10) -> Muestreo de suelos | E10: =IF(Trabajos!J10="","",Trabajos!J10) -> 75816.538 | F10: =IF(Trabajos!O10="","",Trabajos!O10) -> 0 | H10: =IF(Trabajos!H10<>"",E10-E10*G10,"") -> 75816.538 | I10: =IF(Trabajos!H10<>"",F10-F10*G10,"") -> 0 | J10: =IF(Trabajos!H10<>"",H10*0.55,"") -> 41699.096 | K10: =IF(Trabajos!H10<>"",H10*0.45,"") -> 34117.442 | L10: =IF(Trabajos!L10="","",Trabajos!L10) -> Tomas
B11: =IF(Trabajos!B11="","",Trabajos!B11) -> 45912 | C11: =IF(Trabajos!F11="","",Trabajos!F11) -> Martin Juarez | D11: =IF(Trabajos!D11="","",Trabajos!D11) -> Mapeo Dron | E11: =IF(Trabajos!J11="","",Trabajos!J11) -> 381290 | F11: =IF(Trabajos!O11="","",Trabajos!O11) -> 0 | H11: =IF(Trabajos!H11<>"",E11-E11*G11,"") -> 381290 | I11: =IF(Trabajos!H11<>"",F11-F11*G11,"") -> 0 | J11: =IF(Trabajos!H11<>"",H11*0.55,"") -> 209709.5 | K11: =IF(Trabajos!H11<>"",H11*0.45,"") -> 171580.5 | L11: =IF(Trabajos!L11="","",Trabajos!L11) -> Tomas
B12: =IF(Trabajos!B12="","",Trabajos!B12) -> 45913 | C12: =IF(Trabajos!F12="","",Trabajos!F12) -> Espartina S.A. | D12: =IF(Trabajos!D12="","",Trabajos!D12) -> Monitoreo de bb y bab | E12: =IF(Trabajos!J12="","",Trabajos!J12) -> 355106.25 | F12: =IF(Trabajos!O12="","",Trabajos!O12) -> 209700.4 | H12: =IF(Trabajos!H12<>"",E12-E12*G12,"") -> 355106.25 | I12: =IF(Trabajos!H12<>"",F12-F12*G12,"") -> 209700.4 | J12: =IF(Trabajos!H12<>"",H12*0.55,"") -> 195308.44 | K12: =IF(Trabajos!H12<>"",H12*0.45,"") -> 159797.81 | L12: =IF(Trabajos!L12="","",Trabajos!L12) -> Tomas
B13: =IF(Trabajos!B13="","",Trabajos!B13) -> 45913 | C13: =IF(Trabajos!F13="","",Trabajos!F13) -> Espartina S.A. | D13: =IF(Trabajos!D13="","",Trabajos!D13) -> Monitoreo de bb y bab | E13: =IF(Trabajos!J13="","",Trabajos!J13) -> 574143.75 | F13: =IF(Trabajos!O13="","",Trabajos!O13) -> 195874 | H13: =IF(Trabajos!H13<>"",E13-E13*G13,"") -> 574143.75 | I13: =IF(Trabajos!H13<>"",F13-F13*G13,"") -> 195874 | J13: =IF(Trabajos!H13<>"",H13*0.55,"") -> 315779.06 | K13: =IF(Trabajos!H13<>"",H13*0.45,"") -> 258364.69 | L13: =IF(Trabajos!L13="","",Trabajos!L13) -> Tomas
B14: =IF(Trabajos!B14="","",Trabajos!B14) -> 45913 | C14: =IF(Trabajos!F14="","",Trabajos!F14) -> Espartina S.A. | D14: =IF(Trabajos!D14="","",Trabajos!D14) -> Muestreo de suelos | E14: =IF(Trabajos!J14="","",Trabajos!J14) -> 75816.538 | F14: =IF(Trabajos!O14="","",Trabajos!O14) -> 0 | H14: =IF(Trabajos!H14<>"",E14-E14*G14,"") -> 75816.538 | I14: =IF(Trabajos!H14<>"",F14-F14*G14,"") -> 0 | J14: =IF(Trabajos!H14<>"",H14*0.55,"") -> 41699.096 | K14: =IF(Trabajos!H14<>"",H14*0.45,"") -> 34117.442 | L14: =IF(Trabajos!L14="","",Trabajos!L14) -> Tomas
B15: =IF(Trabajos!B15="","",Trabajos!B15) -> 45913 | C15: =IF(Trabajos!F15="","",Trabajos!F15) -> Espartina S.A. | D15: =IF(Trabajos!D15="","",Trabajos!D15) -> Muestreo de suelos | E15: =IF(Trabajos!J15="","",Trabajos!J15) -> 75816.538 | F15: =IF(Trabajos!O15="","",Trabajos!O15) -> 0 | H15: =IF(Trabajos!H15<>"",E15-E15*G15,"") -> 75816.538 | I15: =IF(Trabajos!H15<>"",F15-F15*G15,"") -> 0 | J15: =IF(Trabajos!H15<>"",H15*0.55,"") -> 41699.096 | K15: =IF(Trabajos!H15<>"",H15*0.45,"") -> 34117.442 | L15: =IF(Trabajos!L15="","",Trabajos!L15) -> Tomas
B16: =IF(Trabajos!B16="","",Trabajos!B16) -> 45914 | C16: =IF(Trabajos!F16="","",Trabajos!F16) -> Espartina S.A. | D16: =IF(Trabajos!D16="","",Trabajos!D16) -> Monitoreo de bb y bab | E16: =IF(Trabajos!J16="","",Trabajos!J16) -> 1257806.2 | F16: =IF(Trabajos!O16="","",Trabajos!O16) -> 99089.2 | H16: =IF(Trabajos!H16<>"",E16-E16*G16,"") -> 1257806.2 | I16: =IF(Trabajos!H16<>"",F16-F16*G16,"") -> 99089.2 | J16: =IF(Trabajos!H16<>"",H16*0.55,"") -> 691793.44 | K16: =IF(Trabajos!H16<>"",H16*0.45,"") -> 566012.81 | L16: =IF(Trabajos!L16="","",Trabajos!L16) -> Tomas
B17: =IF(Trabajos!B17="","",Trabajos!B17) -> 45914 | C17: =IF(Trabajos!F17="","",Trabajos!F17) -> Espartina S.A. | D17: =IF(Trabajos!D17="","",Trabajos!D17) -> Muestreo de suelos | E17: =IF(Trabajos!J17="","",Trabajos!J17) -> 75816.538 | F17: =IF(Trabajos!O17="","",Trabajos!O17) -> 0 | H17: =IF(Trabajos!H17<>"",E17-E17*G17,"") -> 75816.538 | I17: =IF(Trabajos!H17<>"",F17-F17*G17,"") -> 0 | J17: =IF(Trabajos!H17<>"",H17*0.55,"") -> 41699.096 | K17: =IF(Trabajos!H17<>"",H17*0.45,"") -> 34117.442 | L17: =IF(Trabajos!L17="","",Trabajos!L17) -> Tomas
B18: =IF(Trabajos!B18="","",Trabajos!B18) -> 45915 | C18: =IF(Trabajos!F18="","",Trabajos!F18) -> Espartina S.A. | D18: =IF(Trabajos!D18="","",Trabajos!D18) -> Monitoreo de bb y bab | E18: =IF(Trabajos!J18="","",Trabajos!J18) -> 756675 | F18: =IF(Trabajos!O18="","",Trabajos!O18) -> 188960.8 | H18: =IF(Trabajos!H18<>"",E18-E18*G18,"") -> 756675 | I18: =IF(Trabajos!H18<>"",F18-F18*G18,"") -> 188960.8 | J18: =IF(Trabajos!H18<>"",H18*0.55,"") -> 416171.25 | K18: =IF(Trabajos!H18<>"",H18*0.45,"") -> 340503.75 | L18: =IF(Trabajos!L18="","",Trabajos!L18) -> Tomas
B19: =IF(Trabajos!B19="","",Trabajos!B19) -> 45915 | C19: =IF(Trabajos!F19="","",Trabajos!F19) -> Espartina S.A. | D19: =IF(Trabajos!D19="","",Trabajos!D19) -> Muestreo de suelos | E19: =IF(Trabajos!J19="","",Trabajos!J19) -> 75816.538 | F19: =IF(Trabajos!O19="","",Trabajos!O19) -> 0 | H19: =IF(Trabajos!H19<>"",E19-E19*G19,"") -> 75816.538 | I19: =IF(Trabajos!H19<>"",F19-F19*G19,"") -> 0 | J19: =IF(Trabajos!H19<>"",H19*0.55,"") -> 41699.096 | K19: =IF(Trabajos!H19<>"",H19*0.45,"") -> 34117.442 | L19: =IF(Trabajos!L19="","",Trabajos!L19) -> Tomas
B20: =IF(Trabajos!B20="","",Trabajos!B20) -> 45916 | C20: =IF(Trabajos!F20="","",Trabajos!F20) -> Espartina S.A. | D20: =IF(Trabajos!D20="","",Trabajos!D20) -> Monitoreo de bb y bab | E20: =IF(Trabajos!J20="","",Trabajos!J20) -> 552692.53 | F20: =IF(Trabajos!O20="","",Trabajos!O20) -> 234524.5 | H20: =IF(Trabajos!H20<>"",E20-E20*G20,"") -> 552692.53 | I20: =IF(Trabajos!H20<>"",F20-F20*G20,"") -> 234524.5 | J20: =IF(Trabajos!H20<>"",H20*0.55,"") -> 303980.89 | K20: =IF(Trabajos!H20<>"",H20*0.45,"") -> 248711.64 | L20: =IF(Trabajos!L20="","",Trabajos!L20) -> Tomas
B21: =IF(Trabajos!B21="","",Trabajos!B21) -> 45916 | C21: =IF(Trabajos!F21="","",Trabajos!F21) -> Espartina S.A. | D21: =IF(Trabajos!D21="","",Trabajos!D21) -> Muestreo de suelos | E21: =IF(Trabajos!J21="","",Trabajos!J21) -> 75816.538 | F21: =IF(Trabajos!O21="","",Trabajos!O21) -> 0 | H21: =IF(Trabajos!H21<>"",E21-E21*G21,"") -> 75816.538 | I21: =IF(Trabajos!H21<>"",F21-F21*G21,"") -> 0 | J21: =IF(Trabajos!H21<>"",H21*0.55,"") -> 41699.096 | K21: =IF(Trabajos!H21<>"",H21*0.45,"") -> 34117.442 | L21: =IF(Trabajos!L21="","",Trabajos!L21) -> Tomas
... B38: =IF(Trabajos!B38="","",Trabajos!B38) -> 45923 | C38: =IF(Trabajos!F38="","",Trabajos!F38) -> Espartina S.A. | D38: =IF(Trabajos!D38="","",Trabajos!D38) -> Monitoreo de bb y bab | E38: =IF(Trabajos!J38="","",Trabajos!J38) -> 689100.8 | F38: =IF(Trabajos!O38="","",Trabajos!O38) -> 121128 | H38: =IF(Trabajos!H38<>"",E38-E38*G38,"") -> 689100.8 | I38: =IF(Trabajos!H38<>"",F38-F38*G38,"") -> 121128 | J38: =IF(Trabajos!H38<>"",H38*0.55,"") -> 379005.44 | K38: =IF(Trabajos!H38<>"",H38*0.45,"") -> 310095.36 | L38: =IF(Trabajos!L38="","",Trabajos!L38) -> Tomas
B39: =IF(Trabajos!B39="","",Trabajos!B39) -> 45923 | C39: =IF(Trabajos!F39="","",Trabajos!F39) -> Espartina S.A. | D39: =IF(Trabajos!D39="","",Trabajos!D39) -> Monitoreo de bb y bab | E39: =IF(Trabajos!J39="","",Trabajos!J39) -> 451921.92 | F39: =IF(Trabajos!O39="","",Trabajos!O39) -> 122304 | G39: 0.003 | H39: =IF(Trabajos!H39<>"",E39-E39*G39,"") -> 450566.15 | I39: =IF(Trabajos!H39<>"",F39-F39*G39,"") -> 121937.09 | J39: =IF(Trabajos!H39<>"",H39*0.55,"") -> 247811.38 | K39: =IF(Trabajos!H39<>"",H39*0.45,"") -> 202754.77 | L39: =IF(Trabajos!L39="","",Trabajos!L39) -> Tomas
B40: =IF(Trabajos!B40="","",Trabajos!B40) -> 45924 | C40: =IF(Trabajos!F40="","",Trabajos!F40) -> Espartina S.A. | D40: =IF(Trabajos!D40="","",Trabajos!D40) -> Monitoreo de bb y bab | E40: =IF(Trabajos!J40="","",Trabajos!J40) -> 451921.92 | F40: =IF(Trabajos!O40="","",Trabajos!O40) -> 0 | H40: =IF(Trabajos!H40<>"",E40-E40*G40,"") -> 451921.92 | I40: =IF(Trabajos!H40<>"",F40-F40*G40,"") -> 0 | J40: =IF(Trabajos!H40<>"",H40*0.55,"") -> 248557.06 | K40: =IF(Trabajos!H40<>"",H40*0.45,"") -> 203364.86 | L40: =IF(Trabajos!L40="","",Trabajos!L40) -> Tomas
B41: =IF(Trabajos!B41="","",Trabajos!B41) -> 45924 | C41: =IF(Trabajos!F41="","",Trabajos!F41) -> Espartina S.A. | D41: =IF(Trabajos!D41="","",Trabajos!D41) -> Monitoreo de bb y bab | E41: =IF(Trabajos!J41="","",Trabajos!J41) -> 400653 | F41: =IF(Trabajos!O41="","",Trabajos!O41) -> 0 | H41: =IF(Trabajos!H41<>"",E41-E41*G41,"") -> 400653 | I41: =IF(Trabajos!H41<>"",F41-F41*G41,"") -> 0 | J41: =IF(Trabajos!H41<>"",H41*0.55,"") -> 220359.15 | K41: =IF(Trabajos!H41<>"",H41*0.45,"") -> 180293.85 | L41: =IF(Trabajos!L41="","",Trabajos!L41) -> Tomas
B42: =IF(Trabajos!B42="","",Trabajos!B42) -> 45924 | C42: =IF(Trabajos!F42="","",Trabajos!F42) -> Espartina S.A. | D42: =IF(Trabajos!D42="","",Trabajos!D42) -> Monitoreo de bb y bab | E42: =IF(Trabajos!J42="","",Trabajos!J42) -> 397440 | F42: =IF(Trabajos!O42="","",Trabajos!O42) -> 149786 | H42: =IF(Trabajos!H42<>"",E42-E42*G42,"") -> 397440 | I42: =IF(Trabajos!H42<>"",F42-F42*G42,"") -> 149786 | J42: =IF(Trabajos!H42<>"",H42*0.55,"") -> 218592 | K42: =IF(Trabajos!H42<>"",H42*0.45,"") -> 178848 | L42: =IF(Trabajos!L42="","",Trabajos!L42) -> Paco
B43: =IF(Trabajos!B43="","",Trabajos!B43) -> 45924 | C43: =IF(Trabajos!F43="","",Trabajos!F43) -> Espartina S.A. | D43: =IF(Trabajos!D43="","",Trabajos!D43) -> Monitoreo de bb y bab | E43: =IF(Trabajos!J43="","",Trabajos!J43) -> 1176795 | F43: =IF(Trabajos!O43="","",Trabajos!O43) -> 338746.8 | H43: =IF(Trabajos!H43<>"",E43-E43*G43,"") -> 1176795 | I43: =IF(Trabajos!H43<>"",F43-F43*G43,"") -> 338746.8 | J43: =IF(Trabajos!H43<>"",H43*0.55,"") -> 647237.25 | K43: =IF(Trabajos!H43<>"",H43*0.45,"") -> 529557.75 | L43: =IF(Trabajos!L43="","",Trabajos!L43) -> Paco
B44: =IF(Trabajos!B44="","",Trabajos!B44) -> 45925 | C44: =IF(Trabajos!F44="","",Trabajos!F44) -> Espartina S.A. | D44: =IF(Trabajos!D44="","",Trabajos!D44) -> Muestreo de suelos | E44: =IF(Trabajos!J44="","",Trabajos!J44) -> 75816.538 | F44: =IF(Trabajos!O44="","",Trabajos!O44) -> 35280 | H44: =IF(Trabajos!H44<>"",E44-E44*G44,"") -> 75816.538 | I44: =IF(Trabajos!H44<>"",F44-F44*G44,"") -> 35280 | J44: =IF(Trabajos!H44<>"",H44*0.55,"") -> 41699.096 | K44: =IF(Trabajos!H44<>"",H44*0.45,"") -> 34117.442 | L44: =IF(Trabajos!L44="","",Trabajos!L44) -> Zoom
B45: =IF(Trabajos!B45="","",Trabajos!B45) -> 45925 | C45: =IF(Trabajos!F45="","",Trabajos!F45) -> Espartina S.A. | D45: =IF(Trabajos!D45="","",Trabajos!D45) -> Muestreo de suelos | E45: =IF(Trabajos!J45="","",Trabajos!J45) -> 75816.538 | F45: =IF(Trabajos!O45="","",Trabajos!O45) -> 122304 | H45: =IF(Trabajos!H45<>"",E45-E45*G45,"") -> 75816.538 | I45: =IF(Trabajos!H45<>"",F45-F45*G45,"") -> 122304 | J45: =IF(Trabajos!H45<>"",H45*0.55,"") -> 41699.096 | K45: =IF(Trabajos!H45<>"",H45*0.45,"") -> 34117.442 | L45: =IF(Trabajos!L45="","",Trabajos!L45) -> Zoom
B46: =IF(Trabajos!B46="","",Trabajos!B46) -> 45925 | C46: =IF(Trabajos!F46="","",Trabajos!F46) -> Espartina S.A. | D46: =IF(Trabajos!D46="","",Trabajos!D46) -> Monitoreo de bb y bab | E46: =IF(Trabajos!J46="","",Trabajos!J46) -> 458332.16 | F46: =IF(Trabajos!O46="","",Trabajos!O46) -> 0 | H46: =IF(Trabajos!H46<>"",E46-E46*G46,"") -> 458332.16 | I46: =IF(Trabajos!H46<>"",F46-F46*G46,"") -> 0 | J46: =IF(Trabajos!H46<>"",H46*0.55,"") -> 252082.69 | K46: =IF(Trabajos!H46<>"",H46*0.45,"") -> 206249.47 | L46: =IF(Trabajos!L46="","",Trabajos!L46) -> Tomas
B47: =IF(Trabajos!B47="","",Trabajos!B47) -> 45925 | C47: =IF(Trabajos!F47="","",Trabajos!F47) -> Espartina S.A. | D47: =IF(Trabajos!D47="","",Trabajos!D47) -> Monitoreo de bb y bab | E47: =IF(Trabajos!J47="","",Trabajos!J47) -> 429486.08 | F47: =IF(Trabajos!O47="","",Trabajos!O47) -> 91728 | H47: =IF(Trabajos!H47<>"",E47-E47*G47,"") -> 429486.08 | I47: =IF(Trabajos!H47<>"",F47-F47*G47,"") -> 91728 | J47: =IF(Trabajos!H47<>"",H47*0.55,"") -> 236217.34 | K47: =IF(Trabajos!H47<>"",H47*0.45,"") -> 193268.74 | L47: =IF(Trabajos!L47="","",Trabajos!L47) -> Tomas
B48: =IF(Trabajos!B48="","",Trabajos!B48) -> 45925 | C48: =IF(Trabajos!F48="","",Trabajos!F48) -> Cía. de Tierras Sud Argentino S.A. | D48: =IF(Trabajos!D48="","",Trabajos!D48) -> Monitoreo de bb y bab | E48: =IF(Trabajos!J48="","",Trabajos!J48) -> 869400 | F48: =IF(Trabajos!O48="","",Trabajos!O48) -> 32500 | H48: =IF(Trabajos!H48<>"",E48-E48*G48,"") -> 869400 | I48: =IF(Trabajos!H48<>"",F48-F48*G48,"") -> 32500 | J48: =IF(Trabajos!H48<>"",H48*0.55,"") -> 478170 | K48: =IF(Trabajos!H48<>"",H48*0.45,"") -> 391230 | L48: =IF(Trabajos!L48="","",Trabajos!L48) -> Zoom
B49: =IF(Trabajos!B49="","",Trabajos!B49) -> 45925 | C49: =IF(Trabajos!F49="","",Trabajos!F49) -> Espartina S.A. | D49: =IF(Trabajos!D49="","",Trabajos!D49) -> Monitoreo de bb y bab | E49: =IF(Trabajos!J49="","",Trabajos!J49) -> 645840 | F49: =IF(Trabajos!O49="","",Trabajos!O49) -> 138264 | H49: =IF(Trabajos!H49<>"",E49-E49*G49,"") -> 645840 | I49: =IF(Trabajos!H49<>"",F49-F49*G49,"") -> 138264 | J49: =IF(Trabajos!H49<>"",H49*0.55,"") -> 355212 | K49: =IF(Trabajos!H49<>"",H49*0.45,"") -> 290628 | L49: =IF(Trabajos!L49="","",Trabajos!L49) -> Paco
B50: =IF(Trabajos!B50="","",Trabajos!B50) -> 45926 | C50: =IF(Trabajos!F50="","",Trabajos!F50) -> Espartina S.A. | D50: =IF(Trabajos!D50="","",Trabajos!D50) -> Monitoreo de bb y bab | E50: =IF(Trabajos!J50="","",Trabajos!J50) -> 326250 | F50: =IF(Trabajos!O50="","",Trabajos!O50) -> 103951.4 | H50: =IF(Trabajos!H50<>"",E50-E50*G50,"") -> 326250 | I50: =IF(Trabajos!H50<>"",F50-F50*G50,"") -> 103951.4 | J50: =IF(Trabajos!H50<>"",H50*0.55,"") -> 179437.5 | K50: =IF(Trabajos!H50<>"",H50*0.45,"") -> 146812.5 | L50: =IF(Trabajos!L50="","",Trabajos!L50) -> Paco
B51: =IF(Trabajos!B51="","",Trabajos!B51) -> 45926 | C51: =IF(Trabajos!F51="","",Trabajos!F51) -> Espartina S.A. | D51: =IF(Trabajos!D51="","",Trabajos!D51) -> Monitoreo de bb y bab | E51: =IF(Trabajos!J51="","",Trabajos!J51) -> 430650 | F51: =IF(Trabajos!O51="","",Trabajos!O51) -> 134376.2 | H51: =IF(Trabajos!H51<>"",E51-E51*G51,"") -> 430650 | I51: =IF(Trabajos!H51<>"",F51-F51*G51,"") -> 134376.2 | J51: =IF(Trabajos!H51<>"",H51*0.55,"") -> 236857.5 | K51: =IF(Trabajos!H51<>"",H51*0.45,"") -> 193792.5 | L51: =IF(Trabajos!L51="","",Trabajos!L51) -> Paco
... B344: =IF(Trabajos!B344="","",Trabajos!B344) -> 46189 | C344: =IF(Trabajos!F344="","",Trabajos!F344) -> Fernando Pili | D344: =IF(Trabajos!D344="","",Trabajos!D344) -> Mapeo Dron | E344: =IF(Trabajos!J344="","",Trabajos!J344) -> 1056090.8 | F344: =IF(Trabajos!O344="","",Trabajos!O344) -> 0 | H344: =IF(Trabajos!H344<>"",E344-E344*G344,"") -> 1056090.8 | I344: =IF(Trabajos!H344<>"",F344-F344*G344,"") -> 0 | J344: =IF(Trabajos!H344<>"",H344*0.55,"") -> 580849.91 | K344: =IF(Trabajos!H344<>"",H344*0.45,"") -> 475240.84 | L344: =IF(Trabajos!L344="","",Trabajos!L344) -> Paco
B345: =IF(Trabajos!B361="","",Trabajos!B361) -> 46212 | C345: =IF(Trabajos!F361="","",Trabajos!F361) -> Espartina S.A. | D345: =IF(Trabajos!D361="","",Trabajos!D361) -> Muestreo de suelos | E345: =IF(Trabajos!J361="","",Trabajos!J361) -> 74400 | F345: =IF(Trabajos!O361="","",Trabajos!O361) -> 0 | H345: =IF(Trabajos!H361<>"",E345-E345*G345,"") -> 74400 | I345: =IF(Trabajos!H361<>"",F345-F345*G345,"") -> 0 | J345: =IF(Trabajos!H361<>"",H345*0.55,"") -> 40920 | K345: =IF(Trabajos!H361<>"",H345*0.45,"") -> 33480 | L345: =IF(Trabajos!L361="","",Trabajos!L361) -> Tomas
B346: =IF(Trabajos!B362="","",Trabajos!B362) -> 46212 | C346: =IF(Trabajos!F362="","",Trabajos!F362) -> Espartina S.A. | D346: =IF(Trabajos!D362="","",Trabajos!D362) -> Muestreo de suelos | E346: =IF(Trabajos!J362="","",Trabajos!J362) -> 74400 | F346: =IF(Trabajos!O362="","",Trabajos!O362) -> 0 | H346: =IF(Trabajos!H362<>"",E346-E346*G346,"") -> 74400 | I346: =IF(Trabajos!H362<>"",F346-F346*G346,"") -> 0 | J346: =IF(Trabajos!H362<>"",H346*0.55,"") -> 40920 | K346: =IF(Trabajos!H362<>"",H346*0.45,"") -> 33480 | L346: =IF(Trabajos!L362="","",Trabajos!L362) -> Tomas
B347: =IF(Trabajos!B393="","",Trabajos!B393) | C347: =IF(Trabajos!F393="","",Trabajos!F393) | D347: =IF(Trabajos!D393="","",Trabajos!D393) | E347: =IF(Trabajos!J393="","",Trabajos!J393) | F347: =IF(Trabajos!O393="","",Trabajos!O393) | H347: =IF(Trabajos!H393<>"",E347-E347*G347,"") | I347: =IF(Trabajos!H393<>"",F347-F347*G347,"") | J347: =IF(Trabajos!H393<>"",H347*0.55,"") | K347: =IF(Trabajos!H393<>"",H347*0.45,"") | L347: =IF(Trabajos!L393="","",Trabajos!L393)
B348: =IF(Trabajos!B394="","",Trabajos!B394) | C348: =IF(Trabajos!F394="","",Trabajos!F394) | D348: =IF(Trabajos!D394="","",Trabajos!D394) | E348: =IF(Trabajos!J394="","",Trabajos!J394) | F348: =IF(Trabajos!O394="","",Trabajos!O394) | H348: =IF(Trabajos!H394<>"",E348-E348*G348,"") | I348: =IF(Trabajos!H394<>"",F348-F348*G348,"") | J348: =IF(Trabajos!H394<>"",H348*0.55,"") | K348: =IF(Trabajos!H394<>"",H348*0.45,"") | L348: =IF(Trabajos!L394="","",Trabajos!L394)
B349: Total | E349: =SUM(E5:E348) -> 1.9191311e+08 | F349: =SUM(F5:F348) -> 28057097 | H349: =SUM(H5:H348) -> 1.9191176e+08 | I349: =SUM(I5:I348) -> 28056730 | J349: =SUM(J5:J348) -> 1.0555147e+08 | K349: =SUM(K5:K348) -> 86360290

Sheet Asignación 2
B2: Asignación
H3: Despues de impuestos | J3: Asignacion | O3: Asignacion Ingreso
B4: Fecha trabajo | C4: Cliente | D4: Tipo de trabajo | E4: Importe | F4: Movilidad | G4: Impuesto | H4: Importe | I4: Movilidad | J4: Trabajo | K4: Empresa | L4: Movilidad | O4: Paco | P4: Tomas | Q4: Zoom
B5: =IF('Trabajos 2'!B5="","",'Trabajos 2'!B5) -> 45908 | C5: =IF('Trabajos 2'!F5="","",'Trabajos 2'!F5) -> Carlos Fernando Fuertes | D5: =IF('Trabajos 2'!D5="","",'Trabajos 2'!D5) -> Seguimiento de cultivos | E5: =IF('Trabajos 2'!J5="","",'Trabajos 2'!J5) -> 100000 | F5: =IF('Trabajos 2'!O5="","",'Trabajos 2'!O5) -> 78000 | H5: =IF('Trabajos 2'!H5<>"",E5-E5*G5,"") -> 100000 | I5: =IF('Trabajos 2'!H5<>"",F5-F5*G5,"") -> 78000 | J5: =IF('Trabajos 2'!H5<>"",H5*0.55,"") -> 55000 | K5: =IF('Trabajos 2'!H5<>"",H5*0.45,"") -> 45000 | L5: =IF('Trabajos 2'!L5="","",'Trabajos 2'!L5) -> Tomas | N5: Trabajo | O5: =IFERROR((J154*Referencias!L17),"") -> 0 | P5: =IFERROR((J154*Referencias!M17),"") -> 4117225.8 | Q5: =IFERROR((J154*Referencias!N17),"") -> 2917098.2
B6: =IF('Trabajos 2'!B6="","",'Trabajos 2'!B6) -> 45912 | C6: =IF('Trabajos 2'!F6="","",'Trabajos 2'!F6) -> Omar Piaggio | D6: =IF('Trabajos 2'!D6="","",'Trabajos 2'!D6) -> Seguimiento de cultivos | E6: =IF('Trabajos 2'!J6="","",'Trabajos 2'!J6) -> 150000 | F6: =IF('Trabajos 2'!O6="","",'Trabajos 2'!O6) -> 146250 | H6: =IF('Trabajos 2'!H6<>"",E6-E6*G6,"") -> 150000 | I6: =IF('Trabajos 2'!H6<>"",F6-F6*G6,"") -> 146250 | J6: =IF('Trabajos 2'!H6<>"",H6*0.55,"") -> 82500 | K6: =IF('Trabajos 2'!H6<>"",H6*0.45,"") -> 67500 | L6: =IF('Trabajos 2'!L6="","",'Trabajos 2'!L6) -> Tomas | N6: Empresa | O6: =IFERROR((K154*Referencias!Q7),"") -> 2877678 | P6: =IFERROR((K154*Referencias!R7),"") -> 2877678
B7: =IF('Trabajos 2'!B7="","",'Trabajos 2'!B7) -> 45917 | C7: =IF('Trabajos 2'!F7="","",'Trabajos 2'!F7) -> Omar Piaggio | D7: =IF('Trabajos 2'!D7="","",'Trabajos 2'!D7) -> Seguimiento de cultivos | E7: =IF('Trabajos 2'!J7="","",'Trabajos 2'!J7) -> 0 | F7: =IF('Trabajos 2'!O7="","",'Trabajos 2'!O7) -> 146250 | H7: =IF('Trabajos 2'!H7<>"",E7-E7*G7,"") -> 0 | I7: =IF('Trabajos 2'!H7<>"",F7-F7*G7,"") -> 146250 | J7: =IF('Trabajos 2'!H7<>"",H7*0.55,"") -> 0 | K7: =IF('Trabajos 2'!H7<>"",H7*0.45,"") -> 0 | L7: =IF('Trabajos 2'!L7="","",'Trabajos 2'!L7) -> Tomas | N7: Viaticos | O7: =IFERROR((SUMIF(L5:L153,O4,I5:I153)),"") -> 0 | P7: =IFERROR((SUMIF(L5:L153,P4,I5:I153)),"") -> 8184500 | Q7: =IFERROR((SUMIF(L5:L153,Q4,I5:I153)),"") -> 5463063.4
B8: =IF('Trabajos 2'!B8="","",'Trabajos 2'!B8) -> 45926 | C8: =IF('Trabajos 2'!F8="","",'Trabajos 2'!F8) -> Nugas S.A. | D8: =IF('Trabajos 2'!D8="","",'Trabajos 2'!D8) -> Seguimiento de cultivos | E8: =IF('Trabajos 2'!J8="","",'Trabajos 2'!J8) -> 100000 | F8: =IF('Trabajos 2'!O8="","",'Trabajos 2'!O8) -> 104000 | H8: =IF('Trabajos 2'!H8<>"",E8-E8*G8,"") -> 100000 | I8: =IF('Trabajos 2'!H8<>"",F8-F8*G8,"") -> 104000 | J8: =IF('Trabajos 2'!H8<>"",H8*0.55,"") -> 55000 | K8: =IF('Trabajos 2'!H8<>"",H8*0.45,"") -> 45000 | L8: =IF('Trabajos 2'!L8="","",'Trabajos 2'!L8) -> Tomas | N8: Total | O8: =IFERROR((SUM(O5:O7)+Q5*Referencias!Q7+Q7*Referencias!Q7),"") -> 7067758.8 | P8: =IFERROR((SUM(P5:P7)+Q5*Referencias!R7+Q7*Referencias!R7),"") -> 19369485
B9: =IF('Trabajos 2'!B9="","",'Trabajos 2'!B9) -> 45933 | C9: =IF('Trabajos 2'!F9="","",'Trabajos 2'!F9) -> Nugas S.A. | D9: =IF('Trabajos 2'!D9="","",'Trabajos 2'!D9) -> Seguimiento de cultivos | E9: =IF('Trabajos 2'!J9="","",'Trabajos 2'!J9) -> 100000 | F9: =IF('Trabajos 2'!O9="","",'Trabajos 2'!O9) -> 104000 | H9: =IF('Trabajos 2'!H9<>"",E9-E9*G9,"") -> 100000 | I9: =IF('Trabajos 2'!H9<>"",F9-F9*G9,"") -> 104000 | J9: =IF('Trabajos 2'!H9<>"",H9*0.55,"") -> 55000 | K9: =IF('Trabajos 2'!H9<>"",H9*0.45,"") -> 45000 | L9: =IF('Trabajos 2'!L9="","",'Trabajos 2'!L9) -> Zoom | N9: Proporcion | O9: =IFERROR((O8/(O8+P8)),"") -> 0.26734099 | P9: =IFERROR((P8/(O8+P8)),"") -> 0.73265901
B10: =IF('Trabajos 2'!B10="","",'Trabajos 2'!B10) -> 45934 | C10: =IF('Trabajos 2'!F10="","",'Trabajos 2'!F10) -> Omar Piaggio | D10: =IF('Trabajos 2'!D10="","",'Trabajos 2'!D10) -> Seguimiento de cultivos | E10: =IF('Trabajos 2'!J10="","",'Trabajos 2'!J10) -> 150000 | F10: =IF('Trabajos 2'!O10="","",'Trabajos 2'!O10) -> 146250 | H10: =IF('Trabajos 2'!H10<>"",E10-E10*G10,"") -> 150000 | I10: =IF('Trabajos 2'!H10<>"",F10-F10*G10,"") -> 146250 | J10: =IF('Trabajos 2'!H10<>"",H10*0.55,"") -> 82500 | K10: =IF('Trabajos 2'!H10<>"",H10*0.45,"") -> 67500 | L10: =IF('Trabajos 2'!L10="","",'Trabajos 2'!L10) -> Tomas
B11: =IF('Trabajos 2'!B11="","",'Trabajos 2'!B11) -> 45939 | C11: =IF('Trabajos 2'!F11="","",'Trabajos 2'!F11) -> Carlos Fernando Fuertes | D11: =IF('Trabajos 2'!D11="","",'Trabajos 2'!D11) -> Seguimiento de cultivos | E11: =IF('Trabajos 2'!J11="","",'Trabajos 2'!J11) -> 100000 | F11: =IF('Trabajos 2'!O11="","",'Trabajos 2'!O11) -> 78000 | H11: =IF('Trabajos 2'!H11<>"",E11-E11*G11,"") -> 100000 | I11: =IF('Trabajos 2'!H11<>"",F11-F11*G11,"") -> 78000 | J11: =IF('Trabajos 2'!H11<>"",H11*0.55,"") -> 55000 | K11: =IF('Trabajos 2'!H11<>"",H11*0.45,"") -> 45000 | L11: =IF('Trabajos 2'!L11="","",'Trabajos 2'!L11) -> Tomas
B12: =IF('Trabajos 2'!B12="","",'Trabajos 2'!B12) -> 45940 | C12: =IF('Trabajos 2'!F12="","",'Trabajos 2'!F12) -> Nugas S.A. | D12: =IF('Trabajos 2'!D12="","",'Trabajos 2'!D12) -> Seguimiento de cultivos | E12: =IF('Trabajos 2'!J12="","",'Trabajos 2'!J12) -> 100000 | F12: =IF('Trabajos 2'!O12="","",'Trabajos 2'!O12) -> 104000 | H12: =IF('Trabajos 2'!H12<>"",E12-E12*G12,"") -> 100000 | I12: =IF('Trabajos 2'!H12<>"",F12-F12*G12,"") -> 104000 | J12: =IF('Trabajos 2'!H12<>"",H12*0.55,"") -> 55000 | K12: =IF('Trabajos 2'!H12<>"",H12*0.45,"") -> 45000 | L12: =IF('Trabajos 2'!L12="","",'Trabajos 2'!L12) -> Zoom
B13: =IF('Trabajos 2'!B13="","",'Trabajos 2'!B13) -> 45948 | C13: =IF('Trabajos 2'!F13="","",'Trabajos 2'!F13) -> Omar Piaggio | D13: =IF('Trabajos 2'!D13="","",'Trabajos 2'!D13) -> Seguimiento de cultivos | E13: =IF('Trabajos 2'!J13="","",'Trabajos 2'!J13) -> 150000 | F13: =IF('Trabajos 2'!O13="","",'Trabajos 2'!O13) -> 146250 | H13: =IF('Trabajos 2'!H13<>"",E13-E13*G13,"") -> 150000 | I13: =IF('Trabajos 2'!H13<>"",F13-F13*G13,"") -> 146250 | J13: =IF('Trabajos 2'!H13<>"",H13*0.55,"") -> 82500 | K13: =IF('Trabajos 2'!H13<>"",H13*0.45,"") -> 67500 | L13: =IF('Trabajos 2'!L13="","",'Trabajos 2'!L13) -> Tomas
B14: =IF('Trabajos 2'!B14="","",'Trabajos 2'!B14) -> 45950 | C14: =IF('Trabajos 2'!F14="","",'Trabajos 2'!F14) -> Omar Piaggio | D14: =IF('Trabajos 2'!D14="","",'Trabajos 2'!D14) -> Seguimiento de cultivos | E14: =IF('Trabajos 2'!J14="","",'Trabajos 2'!J14) -> 150000 | F14: =IF('Trabajos 2'!O14="","",'Trabajos 2'!O14) -> 146250 | H14: =IF('Trabajos 2'!H14<>"",E14-E14*G14,"") -> 150000 | I14: =IF('Trabajos 2'!H14<>"",F14-F14*G14,"") -> 146250 | J14: =IF('Trabajos 2'!H14<>"",H14*0.55,"") -> 82500 | K14: =IF('Trabajos 2'!H14<>"",H14*0.45,"") -> 67500 | L14: =IF('Trabajos 2'!L14="","",'Trabajos 2'!L14) -> Tomas
B15: =IF('Trabajos 2'!B15="","",'Trabajos 2'!B15) -> 45950 | C15: =IF('Trabajos 2'!F15="","",'Trabajos 2'!F15) -> Nugas S.A. | D15: =IF('Trabajos 2'!D15="","",'Trabajos 2'!D15) -> Seguimiento de cultivos | E15: =IF('Trabajos 2'!J15="","",'Trabajos 2'!J15) -> 100000 | F15: =IF('Trabajos 2'!O15="","",'Trabajos 2'!O15) -> 104000 | H15: =IF('Trabajos 2'!H15<>"",E15-E15*G15,"") -> 100000 | I15: =IF('Trabajos 2'!H15<>"",F15-F15*G15,"") -> 104000 | J15: =IF('Trabajos 2'!H15<>"",H15*0.55,"") -> 55000 | K15: =IF('Trabajos 2'!H15<>"",H15*0.45,"") -> 45000 | L15: =IF('Trabajos 2'!L15="","",'Trabajos 2'!L15) -> Zoom
B16: =IF('Trabajos 2'!B16="","",'Trabajos 2'!B16) -> 45959 | C16: =IF('Trabajos 2'!F16="","",'Trabajos 2'!F16) -> Nugas S.A. | D16: =IF('Trabajos 2'!D16="","",'Trabajos 2'!D16) -> Seguimiento de cultivos | E16: =IF('Trabajos 2'!J16="","",'Trabajos 2'!J16) -> 100000 | F16: =IF('Trabajos 2'!O16="","",'Trabajos 2'!O16) -> 104000 | H16: =IF('Trabajos 2'!H16<>"",E16-E16*G16,"") -> 100000 | I16: =IF('Trabajos 2'!H16<>"",F16-F16*G16,"") -> 104000 | J16: =IF('Trabajos 2'!H16<>"",H16*0.55,"") -> 55000 | K16: =IF('Trabajos 2'!H16<>"",H16*0.45,"") -> 45000 | L16: =IF('Trabajos 2'!L16="","",'Trabajos 2'!L16) -> Zoom
B17: =IF('Trabajos 2'!B17="","",'Trabajos 2'!B17) -> 45967 | C17: =IF('Trabajos 2'!F17="","",'Trabajos 2'!F17) -> Carlos Fernando Fuertes | D17: =IF('Trabajos 2'!D17="","",'Trabajos 2'!D17) -> Seguimiento de cultivos | E17: =IF('Trabajos 2'!J17="","",'Trabajos 2'!J17) -> 100000 | F17: =IF('Trabajos 2'!O17="","",'Trabajos 2'!O17) -> 78000 | H17: =IF('Trabajos 2'!H17<>"",E17-E17*G17,"") -> 100000 | I17: =IF('Trabajos 2'!H17<>"",F17-F17*G17,"") -> 78000 | J17: =IF('Trabajos 2'!H17<>"",H17*0.55,"") -> 55000 | K17: =IF('Trabajos 2'!H17<>"",H17*0.45,"") -> 45000 | L17: =IF('Trabajos 2'!L17="","",'Trabajos 2'!L17) -> Tomas
B18: =IF('Trabajos 2'!B18="","",'Trabajos 2'!B18) -> 45968 | C18: =IF('Trabajos 2'!F18="","",'Trabajos 2'!F18) -> Carlos Fernando Fuertes | D18: =IF('Trabajos 2'!D18="","",'Trabajos 2'!D18) -> Seguimiento de cultivos | E18: =IF('Trabajos 2'!J18="","",'Trabajos 2'!J18) -> 100000 | F18: =IF('Trabajos 2'!O18="","",'Trabajos 2'!O18) -> 78000 | H18: =IF('Trabajos 2'!H18<>"",E18-E18*G18,"") -> 100000 | I18: =IF('Trabajos 2'!H18<>"",F18-F18*G18,"") -> 78000 | J18: =IF('Trabajos 2'!H18<>"",H18*0.55,"") -> 55000 | K18: =IF('Trabajos 2'!H18<>"",H18*0.45,"") -> 45000 | L18: =IF('Trabajos 2'!L18="","",'Trabajos 2'!L18) -> Tomas
B19: =IF('Trabajos 2'!B19="","",'Trabajos 2'!B19) -> 45968 | C19: =IF('Trabajos 2'!F19="","",'Trabajos 2'!F19) -> Nugas S.A. | D19: =IF('Trabajos 2'!D19="","",'Trabajos 2'!D19) -> Seguimiento de cultivos | E19: =IF('Trabajos 2'!J19="","",'Trabajos 2'!J19) -> 100000 | F19: =IF('Trabajos 2'!O19="","",'Trabajos 2'!O19) -> 104000 | H19: =IF('Trabajos 2'!H19<>"",E19-E19*G19,"") -> 100000 | I19: =IF('Trabajos 2'!H19<>"",F19-F19*G19,"") -> 104000 | J19: =IF('Trabajos 2'!H19<>"",H19*0.55,"") -> 55000 | K19: =IF('Trabajos 2'!H19<>"",H19*0.45,"") -> 45000 | L19: =IF('Trabajos 2'!L19="","",'Trabajos 2'!L19) -> Zoom
B20: =IF('Trabajos 2'!B20="","",'Trabajos 2'!B20) -> 45970 | C20: =IF('Trabajos 2'!F20="","",'Trabajos 2'!F20) -> Omar Piaggio | D20: =IF('Trabajos 2'!D20="","",'Trabajos 2'!D20) -> Seguimiento de cultivos | E20: =IF('Trabajos 2'!J20="","",'Trabajos 2'!J20) -> 150000 | F20: =IF('Trabajos 2'!O20="","",'Trabajos 2'!O20) -> 146250 | H20: =IF('Trabajos 2'!H20<>"",E20-E20*G20,"") -> 150000 | I20: =IF('Trabajos 2'!H20<>"",F20-F20*G20,"") -> 146250 | J20: =IF('Trabajos 2'!H20<>"",H20*0.55,"") -> 82500 | K20: =IF('Trabajos 2'!H20<>"",H20*0.45,"") -> 67500 | L20: =IF('Trabajos 2'!L20="","",'Trabajos 2'!L20) -> Tomas
B21: =IF('Trabajos 2'!B21="","",'Trabajos 2'!B21) -> 45971 | C21: =IF('Trabajos 2'!F21="","",'Trabajos 2'!F21) -> Carlos Fernando Fuertes | D21: =IF('Trabajos 2'!D21="","",'Trabajos 2'!D21) -> Seguimiento de cultivos | E21: =IF('Trabajos 2'!J21="","",'Trabajos 2'!J21) -> 100000 | F21: =IF('Trabajos 2'!O21="","",'Trabajos 2'!O21) -> 78000 | H21: =IF('Trabajos 2'!H21<>"",E21-E21*G21,"") -> 100000 | I21: =IF('Trabajos 2'!H21<>"",F21-F21*G21,"") -> 78000 | J21: =IF('Trabajos 2'!H21<>"",H21*0.55,"") -> 55000 | K21: =IF('Trabajos 2'!H21<>"",H21*0.45,"") -> 45000 | L21: =IF('Trabajos 2'!L21="","",'Trabajos 2'!L21) -> Tomas
... B153: =IF('Trabajos 2'!B153="","",'Trabajos 2'!B153) | C153: =IF('Trabajos 2'!F153="","",'Trabajos 2'!F153) | D153: =IF('Trabajos 2'!D153="","",'Trabajos 2'!D153) | E153: =IF('Trabajos 2'!J153="","",'Trabajos 2'!J153) | F153: =IF('Trabajos 2'!O153="","",'Trabajos 2'!O153) | H153: =IF('Trabajos 2'!H153<>"",E153-E153*G153,"") | I153: =IF('Trabajos 2'!H153<>"",F153-F153*G153,"") | J153: =IF('Trabajos 2'!H153<>"",H153*0.55,"") | K153: =IF('Trabajos 2'!H153<>"",H153*0.45,"") | L153: =IF('Trabajos 2'!L153="","",'Trabajos 2'!L153)
B154: Total | E154: =SUM(E5:E153) -> 12789680 | F154: =SUM(F5:F153) -> 13647563 | H154: =SUM(H5:H153) -> 12789680 | I154: =SUM(I5:I153) -> 13647563 | J154: =SUM(J5:J153) -> 7034324 | K154: =SUM(K5:K153) -> 5755356

Sheet Facturacion
B2: Detalle Trabajos
B4: Fecha | C4: Cliente | D4: Tipo de trabajo | E4: Campo | F4: Superficie | G4: Precio | H4: Subtotal | I4: Distancia | J4: Precio | K4: Subtotal | L4: Importe
B5: =IF(Trabajos!B5="","",Trabajos!B5) -> 45909 | C5: =IF(Trabajos!F5="","",Trabajos!F5) -> Espartina S.A. | D5: =IF(Trabajos!D5="","",Trabajos!D5) -> Muestreo de suelos | E5: =IF(Trabajos!G5="","",Trabajos!G5) -> El Casalito | F5: =IF(Trabajos!H5="","",Trabajos!H5) -> 80 | G5: =IF(Trabajos!I5="","",Trabajos!I5) -> 947.70673 | H5: =IF(Trabajos!J5="","",Trabajos!J5) -> 75816.538 | I5: =IF(Trabajos!M5="","",Trabajos!M5) -> 0 | J5: =IF(Trabajos!N5="","",Trabajos!N5) -> 576.1 | K5: =IF(Trabajos!O5="","",Trabajos!O5) -> 0 | L5: =IF(Trabajos!P5="","",Trabajos!P5) -> 75816.538
B6: =IF(Trabajos!B6="","",Trabajos!B6) -> 45909 | C6: =IF(Trabajos!F6="","",Trabajos!F6) -> Espartina S.A. | D6: =IF(Trabajos!D6="","",Trabajos!D6) -> Muestreo de suelos | E6: =IF(Trabajos!G6="","",Trabajos!G6) -> Las Bagualas | F6: =IF(Trabajos!H6="","",Trabajos!H6) -> 80 | G6: =IF(Trabajos!I6="","",Trabajos!I6) -> 947.70673 | H6: =IF(Trabajos!J6="","",Trabajos!J6) -> 75816.538 | I6: =IF(Trabajos!M6="","",Trabajos!M6) -> 0 | J6: =IF(Trabajos!N6="","",Trabajos!N6) -> 576.1 | K6: =IF(Trabajos!O6="","",Trabajos!O6) -> 0 | L6: =IF(Trabajos!P6="","",Trabajos!P6) -> 75816.538
B7: =IF(Trabajos!B7="","",Trabajos!B7) -> 45909 | C7: =IF(Trabajos!F7="","",Trabajos!F7) -> Espartina S.A. | D7: =IF(Trabajos!D7="","",Trabajos!D7) -> Muestreo de suelos | E7: =IF(Trabajos!G7="","",Trabajos!G7) -> San Marcos | F7: =IF(Trabajos!H7="","",Trabajos!H7) -> 80 | G7: =IF(Trabajos!I7="","",Trabajos!I7) -> 947.70673 | H7: =IF(Trabajos!J7="","",Trabajos!J7) -> 75816.538 | I7: =IF(Trabajos!M7="","",Trabajos!M7) -> 0 | J7: =IF(Trabajos!N7="","",Trabajos!N7) -> 576.1 | K7: =IF(Trabajos!O7="","",Trabajos!O7) -> 0 | L7: =IF(Trabajos!P7="","",Trabajos!P7) -> 75816.538
B8: =IF(Trabajos!B8="","",Trabajos!B8) -> 45909 | C8: =IF(Trabajos!F8="","",Trabajos!F8) -> Espartina S.A. | D8: =IF(Trabajos!D8="","",Trabajos!D8) -> Muestreo de suelos | E8: =IF(Trabajos!G8="","",Trabajos!G8) -> Los Tulipanes | F8: =IF(Trabajos!H8="","",Trabajos!H8) -> 80 | G8: =IF(Trabajos!I8="","",Trabajos!I8) -> 947.70673 | H8: =IF(Trabajos!J8="","",Trabajos!J8) -> 75816.538 | I8: =IF(Trabajos!M8="","",Trabajos!M8) -> 184 | J8: =IF(Trabajos!N8="","",Trabajos!N8) -> 576.1 | K8: =IF(Trabajos!O8="","",Trabajos!O8) -> 106002.4 | L8: =IF(Trabajos!P8="","",Trabajos!P8) -> 181818.94
B9: =IF(Trabajos!B9="","",Trabajos!B9) -> 45911 | C9: =IF(Trabajos!F9="","",Trabajos!F9) -> Espartina S.A. | D9: =IF(Trabajos!D9="","",Trabajos!D9) -> Muestreo de suelos | E9: =IF(Trabajos!G9="","",Trabajos!G9) -> La Paz | F9: =IF(Trabajos!H9="","",Trabajos!H9) -> 80 | G9: =IF(Trabajos!I9="","",Trabajos!I9) -> 947.70673 | H9: =IF(Trabajos!J9="","",Trabajos!J9) -> 75816.538 | I9: =IF(Trabajos!M9="","",Trabajos!M9) -> 270 | J9: =IF(Trabajos!N9="","",Trabajos!N9) -> 576.1 | K9: =IF(Trabajos!O9="","",Trabajos!O9) -> 155547 | L9: =IF(Trabajos!P9="","",Trabajos!P9) -> 231363.54
B10: =IF(Trabajos!B10="","",Trabajos!B10) -> 45911 | C10: =IF(Trabajos!F10="","",Trabajos!F10) -> Espartina S.A. | D10: =IF(Trabajos!D10="","",Trabajos!D10) -> Muestreo de suelos | E10: =IF(Trabajos!G10="","",Trabajos!G10) -> Bella Vista | F10: =IF(Trabajos!H10="","",Trabajos!H10) -> 80 | G10: =IF(Trabajos!I10="","",Trabajos!I10) -> 947.70673 | H10: =IF(Trabajos!J10="","",Trabajos!J10) -> 75816.538 | I10: =IF(Trabajos!M10="","",Trabajos!M10) -> 0 | J10: =IF(Trabajos!N10="","",Trabajos!N10) -> 576.1 | K10: =IF(Trabajos!O10="","",Trabajos!O10) -> 0 | L10: =IF(Trabajos!P10="","",Trabajos!P10) -> 75816.538
B11: =IF(Trabajos!B11="","",Trabajos!B11) -> 45912 | C11: =IF(Trabajos!F11="","",Trabajos!F11) -> Martin Juarez | D11: =IF(Trabajos!D11="","",Trabajos!D11) -> Mapeo Dron | E11: =IF(Trabajos!G11="","",Trabajos!G11) -> La Juana | F11: =IF(Trabajos!H11="","",Trabajos!H11) -> 50 | G11: =IF(Trabajos!I11="","",Trabajos!I11) -> 7625.8 | H11: =IF(Trabajos!J11="","",Trabajos!J11) -> 381290 | I11: =IF(Trabajos!M11="","",Trabajos!M11) -> 0 | J11: =IF(Trabajos!N11="","",Trabajos!N11) -> 650 | K11: =IF(Trabajos!O11="","",Trabajos!O11) -> 0 | L11: =IF(Trabajos!P11="","",Trabajos!P11) -> 381290
B12: =IF(Trabajos!B12="","",Trabajos!B12) -> 45913 | C12: =IF(Trabajos!F12="","",Trabajos!F12) -> Espartina S.A. | D12: =IF(Trabajos!D12="","",Trabajos!D12) -> Monitoreo de bb y bab | E12: =IF(Trabajos!G12="","",Trabajos!G12) -> Don Gustavo | F12: =IF(Trabajos!H12="","",Trabajos!H12) -> 107 | G12: =IF(Trabajos!I12="","",Trabajos!I12) -> 3318.75 | H12: =IF(Trabajos!J12="","",Trabajos!J12) -> 355106.25 | I12: =IF(Trabajos!M12="","",Trabajos!M12) -> 364 | J12: =IF(Trabajos!N12="","",Trabajos!N12) -> 576.1 | K12: =IF(Trabajos!O12="","",Trabajos!O12) -> 209700.4 | L12: =IF(Trabajos!P12="","",Trabajos!P12) -> 564806.65
B13: =IF(Trabajos!B13="","",Trabajos!B13) -> 45913 | C13: =IF(Trabajos!F13="","",Trabajos!F13) -> Espartina S.A. | D13: =IF(Trabajos!D13="","",Trabajos!D13) -> Monitoreo de bb y bab | E13: =IF(Trabajos!G13="","",Trabajos!G13) -> San Luciano | F13: =IF(Trabajos!H13="","",Trabajos!H13) -> 173 | G13: =IF(Trabajos!I13="","",Trabajos!I13) -> 3318.75 | H13: =IF(Trabajos!J13="","",Trabajos!J13) -> 574143.75 | I13: =IF(Trabajos!M13="","",Trabajos!M13) -> 340 | J13: =IF(Trabajos!N13="","",Trabajos!N13) -> 576.1 | K13: =IF(Trabajos!O13="","",Trabajos!O13) -> 195874 | L13: =IF(Trabajos!P13="","",Trabajos!P13) -> 770017.75
B14: =IF(Trabajos!B14="","",Trabajos!B14) -> 45913 | C14: =IF(Trabajos!F14="","",Trabajos!F14) -> Espartina S.A. | D14: =IF(Trabajos!D14="","",Trabajos!D14) -> Muestreo de suelos | E14: =IF(Trabajos!G14="","",Trabajos!G14) -> Don Gustavo | F14: =IF(Trabajos!H14="","",Trabajos!H14) -> 80 | G14: =IF(Trabajos!I14="","",Trabajos!I14) -> 947.70673 | H14: =IF(Trabajos!J14="","",Trabajos!J14) -> 75816.538 | I14: =IF(Trabajos!M14="","",Trabajos!M14) -> 0 | J14: =IF(Trabajos!N14="","",Trabajos!N14) -> 576.1 | K14: =IF(Trabajos!O14="","",Trabajos!O14) -> 0 | L14: =IF(Trabajos!P14="","",Trabajos!P14) -> 75816.538
B15: =IF(Trabajos!B15="","",Trabajos!B15) -> 45913 | C15: =IF(Trabajos!F15="","",Trabajos!F15) -> Espartina S.A. | D15: =IF(Trabajos!D15="","",Trabajos!D15) -> Muestreo de suelos | E15: =IF(Trabajos!G15="","",Trabajos!G15) -> San Luciano | F15: =IF(Trabajos!H15="","",Trabajos!H15) -> 80 | G15: =IF(Trabajos!I15="","",Trabajos!I15) -> 947.70673 | H15: =IF(Trabajos!J15="","",Trabajos!J15) -> 75816.538 | I15: =IF(Trabajos!M15="","",Trabajos!M15) -> 0 | J15: =IF(Trabajos!N15="","",Trabajos!N15) -> 576.1 | K15: =IF(Trabajos!O15="","",Trabajos!O15) -> 0 | L15: =IF(Trabajos!P15="","",Trabajos!P15) -> 75816.538
B16: =IF(Trabajos!B16="","",Trabajos!B16) -> 45914 | C16: =IF(Trabajos!F16="","",Trabajos!F16) -> Espartina S.A. | D16: =IF(Trabajos!D16="","",Trabajos!D16) -> Monitoreo de bb y bab | E16: =IF(Trabajos!G16="","",Trabajos!G16) -> Santa Ana Cobo | F16: =IF(Trabajos!H16="","",Trabajos!H16) -> 379 | G16: =IF(Trabajos!I16="","",Trabajos!I16) -> 3318.75 | H16: =IF(Trabajos!J16="","",Trabajos!J16) -> 1257806.2 | I16: =IF(Trabajos!M16="","",Trabajos!M16) -> 172 | J16: =IF(Trabajos!N16="","",Trabajos!N16) -> 576.1 | K16: =IF(Trabajos!O16="","",Trabajos!O16) -> 99089.2 | L16: =IF(Trabajos!P16="","",Trabajos!P16) -> 1356895.4
... B394: =IF(Trabajos!B394="","",Trabajos!B394) | C394: =IF(Trabajos!F394="","",Trabajos!F394) | D394: =IF(Trabajos!D394="","",Trabajos!D394) | E394: =IF(Trabajos!G394="","",Trabajos!G394) | F394: =IF(Trabajos!H394="","",Trabajos!H394) | G394: =IF(Trabajos!I394="","",Trabajos!I394) | H394: =IF(Trabajos!J394="","",Trabajos!J394) | I394: =IF(Trabajos!M394="","",Trabajos!M394) | J394: =IF(Trabajos!N394="","",Trabajos!N394) | K394: =IF(Trabajos!O394="","",Trabajos!O394) | L394: =IF(Trabajos!P394="","",Trabajos!P394)
B395: Total | F395: =SUBTOTAL(9,F5:F394) -> 57801 | I395: =SUBTOTAL(9,I5:I394) -> 46207 | L395: =SUBTOTAL(9,L5:L394) -> 2.2427234e+08

Sheet Facturacion 2
B2: Detalle Trabajos
B4: Fecha | C4: Cliente | D4: Tipo de trabajo | E4: Campo | F4: Dias | G4: Precio | H4: Subtotal | I4: Distancia | J4: Precio | K4: Subtotal | L4: Importe
B5: =IF('Trabajos 2'!B5="","",'Trabajos 2'!B5) -> 45908 | C5: =IF('Trabajos 2'!F5="","",'Trabajos 2'!F5) -> Carlos Fernando Fuertes | D5: =IF('Trabajos 2'!D5="","",'Trabajos 2'!D5) -> Seguimiento de cultivos | E5: =IF('Trabajos 2'!G5="","",'Trabajos 2'!G5) -> La Tolderia | F5: =IF('Trabajos 2'!H5="","",'Trabajos 2'!H5) -> 0.5 | G5: =IF('Trabajos 2'!I5="","",'Trabajos 2'!I5) -> 200000 | H5: =IF('Trabajos 2'!J5="","",'Trabajos 2'!J5) -> 100000 | I5: =IF('Trabajos 2'!M5="","",'Trabajos 2'!M5) -> 120 | J5: =IF('Trabajos 2'!N5="","",'Trabajos 2'!N5) -> 650 | K5: =IF('Trabajos 2'!O5="","",'Trabajos 2'!O5) -> 78000 | L5: =IF('Trabajos 2'!P5="","",'Trabajos 2'!P5) -> 178000
B6: =IF('Trabajos 2'!B6="","",'Trabajos 2'!B6) -> 45912 | C6: =IF('Trabajos 2'!F6="","",'Trabajos 2'!F6) -> Omar Piaggio | D6: =IF('Trabajos 2'!D6="","",'Trabajos 2'!D6) -> Seguimiento de cultivos | E6: =IF('Trabajos 2'!G6="","",'Trabajos 2'!G6) -> Costa del Moro | F6: =IF('Trabajos 2'!H6="","",'Trabajos 2'!H6) -> 1 | G6: =IF('Trabajos 2'!I6="","",'Trabajos 2'!I6) -> 150000 | H6: =IF('Trabajos 2'!J6="","",'Trabajos 2'!J6) -> 150000 | I6: =IF('Trabajos 2'!M6="","",'Trabajos 2'!M6) -> 225 | J6: =IF('Trabajos 2'!N6="","",'Trabajos 2'!N6) -> 650 | K6: =IF('Trabajos 2'!O6="","",'Trabajos 2'!O6) -> 146250 | L6: =IF('Trabajos 2'!P6="","",'Trabajos 2'!P6) -> 296250
B7: =IF('Trabajos 2'!B7="","",'Trabajos 2'!B7) -> 45917 | C7: =IF('Trabajos 2'!F7="","",'Trabajos 2'!F7) -> Omar Piaggio | D7: =IF('Trabajos 2'!D7="","",'Trabajos 2'!D7) -> Seguimiento de cultivos | E7: =IF('Trabajos 2'!G7="","",'Trabajos 2'!G7) -> Costa del Moro | F7: =IF('Trabajos 2'!H7="","",'Trabajos 2'!H7) -> 0 | G7: =IF('Trabajos 2'!I7="","",'Trabajos 2'!I7) -> 150000 | H7: =IF('Trabajos 2'!J7="","",'Trabajos 2'!J7) -> 0 | I7: =IF('Trabajos 2'!M7="","",'Trabajos 2'!M7) -> 225 | J7: =IF('Trabajos 2'!N7="","",'Trabajos 2'!N7) -> 650 | K7: =IF('Trabajos 2'!O7="","",'Trabajos 2'!O7) -> 146250 | L7: =IF('Trabajos 2'!P7="","",'Trabajos 2'!P7) -> 146250
B8: =IF('Trabajos 2'!B8="","",'Trabajos 2'!B8) -> 45926 | C8: =IF('Trabajos 2'!F8="","",'Trabajos 2'!F8) -> Nugas S.A. | D8: =IF('Trabajos 2'!D8="","",'Trabajos 2'!D8) -> Seguimiento de cultivos | E8: =IF('Trabajos 2'!G8="","",'Trabajos 2'!G8) -> La Alborada | F8: =IF('Trabajos 2'!H8="","",'Trabajos 2'!H8) -> 0.5 | G8: =IF('Trabajos 2'!I8="","",'Trabajos 2'!I8) -> 200000 | H8: =IF('Trabajos 2'!J8="","",'Trabajos 2'!J8) -> 100000 | I8: =IF('Trabajos 2'!M8="","",'Trabajos 2'!M8) -> 160 | J8: =IF('Trabajos 2'!N8="","",'Trabajos 2'!N8) -> 650 | K8: =IF('Trabajos 2'!O8="","",'Trabajos 2'!O8) -> 104000 | L8: =IF('Trabajos 2'!P8="","",'Trabajos 2'!P8) -> 204000
B9: =IF('Trabajos 2'!B9="","",'Trabajos 2'!B9) -> 45933 | C9: =IF('Trabajos 2'!F9="","",'Trabajos 2'!F9) -> Nugas S.A. | D9: =IF('Trabajos 2'!D9="","",'Trabajos 2'!D9) -> Seguimiento de cultivos | E9: =IF('Trabajos 2'!G9="","",'Trabajos 2'!G9) -> La Alborada | F9: =IF('Trabajos 2'!H9="","",'Trabajos 2'!H9) -> 0.5 | G9: =IF('Trabajos 2'!I9="","",'Trabajos 2'!I9) -> 200000 | H9: =IF('Trabajos 2'!J9="","",'Trabajos 2'!J9) -> 100000 | I9: =IF('Trabajos 2'!M9="","",'Trabajos 2'!M9) -> 160 | J9: =IF('Trabajos 2'!N9="","",'Trabajos 2'!N9) -> 650 | K9: =IF('Trabajos 2'!O9="","",'Trabajos 2'!O9) -> 104000 | L9: =IF('Trabajos 2'!P9="","",'Trabajos 2'!P9) -> 204000
B10: =IF('Trabajos 2'!B10="","",'Trabajos 2'!B10) -> 45934 | C10: =IF('Trabajos 2'!F10="","",'Trabajos 2'!F10) -> Omar Piaggio | D10: =IF('Trabajos 2'!D10="","",'Trabajos 2'!D10) -> Seguimiento de cultivos | E10: =IF('Trabajos 2'!G10="","",'Trabajos 2'!G10) -> Costa del Moro | F10: =IF('Trabajos 2'!H10="","",'Trabajos 2'!H10) -> 1 | G10: =IF('Trabajos 2'!I10="","",'Trabajos 2'!I10) -> 150000 | H10: =IF('Trabajos 2'!J10="","",'Trabajos 2'!J10) -> 150000 | I10: =IF('Trabajos 2'!M10="","",'Trabajos 2'!M10) -> 225 | J10: =IF('Trabajos 2'!N10="","",'Trabajos 2'!N10) -> 650 | K10: =IF('Trabajos 2'!O10="","",'Trabajos 2'!O10) -> 146250 | L10: =IF('Trabajos 2'!P10="","",'Trabajos 2'!P10) -> 296250
B11: =IF('Trabajos 2'!B11="","",'Trabajos 2'!B11) -> 45939 | C11: =IF('Trabajos 2'!F11="","",'Trabajos 2'!F11) -> Carlos Fernando Fuertes | D11: =IF('Trabajos 2'!D11="","",'Trabajos 2'!D11) -> Seguimiento de cultivos | E11: =IF('Trabajos 2'!G11="","",'Trabajos 2'!G11) -> La Tolderia | F11: =IF('Trabajos 2'!H11="","",'Trabajos 2'!H11) -> 0.5 | G11: =IF('Trabajos 2'!I11="","",'Trabajos 2'!I11) -> 200000 | H11: =IF('Trabajos 2'!J11="","",'Trabajos 2'!J11) -> 100000 | I11: =IF('Trabajos 2'!M11="","",'Trabajos 2'!M11) -> 120 | J11: =IF('Trabajos 2'!N11="","",'Trabajos 2'!N11) -> 650 | K11: =IF('Trabajos 2'!O11="","",'Trabajos 2'!O11) -> 78000 | L11: =IF('Trabajos 2'!P11="","",'Trabajos 2'!P11) -> 178000
B12: =IF('Trabajos 2'!B12="","",'Trabajos 2'!B12) -> 45940 | C12: =IF('Trabajos 2'!F12="","",'Trabajos 2'!F12) -> Nugas S.A. | D12: =IF('Trabajos 2'!D12="","",'Trabajos 2'!D12) -> Seguimiento de cultivos | E12: =IF('Trabajos 2'!G12="","",'Trabajos 2'!G12) -> La Alborada | F12: =IF('Trabajos 2'!H12="","",'Trabajos 2'!H12) -> 0.5 | G12: =IF('Trabajos 2'!I12="","",'Trabajos 2'!I12) -> 200000 | H12: =IF('Trabajos 2'!J12="","",'Trabajos 2'!J12) -> 100000 | I12: =IF('Trabajos 2'!M12="","",'Trabajos 2'!M12) -> 160 | J12: =IF('Trabajos 2'!N12="","",'Trabajos 2'!N12) -> 650 | K12: =IF('Trabajos 2'!O12="","",'Trabajos 2'!O12) -> 104000 | L12: =IF('Trabajos 2'!P12="","",'Trabajos 2'!P12) -> 204000
B13: =IF('Trabajos 2'!B13="","",'Trabajos 2'!B13) -> 45948 | C13: =IF('Trabajos 2'!F13="","",'Trabajos 2'!F13) -> Omar Piaggio | D13: =IF('Trabajos 2'!D13="","",'Trabajos 2'!D13) -> Seguimiento de cultivos | E13: =IF('Trabajos 2'!G13="","",'Trabajos 2'!G13) -> Costa del Moro | F13: =IF('Trabajos 2'!H13="","",'Trabajos 2'!H13) -> 1 | G13: =IF('Trabajos 2'!I13="","",'Trabajos 2'!I13) -> 150000 | H13: =IF('Trabajos 2'!J13="","",'Trabajos 2'!J13) -> 150000 | I13: =IF('Trabajos 2'!M13="","",'Trabajos 2'!M13) -> 225 | J13: =IF('Trabajos 2'!N13="","",'Trabajos 2'!N13) -> 650 | K13: =IF('Trabajos 2'!O13="","",'Trabajos 2'!O13) -> 146250 | L13: =IF('Trabajos 2'!P13="","",'Trabajos 2'!P13) -> 296250
B14: =IF('Trabajos 2'!B14="","",'Trabajos 2'!B14) -> 45950 | C14: =IF('Trabajos 2'!F14="","",'Trabajos 2'!F14) -> Omar Piaggio | D14: =IF('Trabajos 2'!D14="","",'Trabajos 2'!D14) -> Seguimiento de cultivos | E14: =IF('Trabajos 2'!G14="","",'Trabajos 2'!G14) -> Costa del Moro | F14: =IF('Trabajos 2'!H14="","",'Trabajos 2'!H14) -> 1 | G14: =IF('Trabajos 2'!I14="","",'Trabajos 2'!I14) -> 150000 | H14: =IF('Trabajos 2'!J14="","",'Trabajos 2'!J14) -> 150000 | I14: =IF('Trabajos 2'!M14="","",'Trabajos 2'!M14) -> 225 | J14: =IF('Trabajos 2'!N14="","",'Trabajos 2'!N14) -> 650 | K14: =IF('Trabajos 2'!O14="","",'Trabajos 2'!O14) -> 146250 | L14: =IF('Trabajos 2'!P14="","",'Trabajos 2'!P14) -> 296250
B15: =IF('Trabajos 2'!B15="","",'Trabajos 2'!B15) -> 45950 | C15: =IF('Trabajos 2'!F15="","",'Trabajos 2'!F15) -> Nugas S.A. | D15: =IF('Trabajos 2'!D15="","",'Trabajos 2'!D15) -> Seguimiento de cultivos | E15: =IF('Trabajos 2'!G15="","",'Trabajos 2'!G15) -> La Alborada | F15: =IF('Trabajos 2'!H15="","",'Trabajos 2'!H15) -> 0.5 | G15: =IF('Trabajos 2'!I15="","",'Trabajos 2'!I15) -> 200000 | H15: =IF('Trabajos 2'!J15="","",'Trabajos 2'!J15) -> 100000 | I15: =IF('Trabajos 2'!M15="","",'Trabajos 2'!M15) -> 160 | J15: =IF('Trabajos 2'!N15="","",'Trabajos 2'!N15) -> 650 | K15: =IF('Trabajos 2'!O15="","",'Trabajos 2'!O15) -> 104000 | L15: =IF('Trabajos 2'!P15="","",'Trabajos 2'!P15) -> 204000
B16: =IF('Trabajos 2'!B16="","",'Trabajos 2'!B16) -> 45959 | C16: =IF('Trabajos 2'!F16="","",'Trabajos 2'!F16) -> Nugas S.A. | D16: =IF('Trabajos 2'!D16="","",'Trabajos 2'!D16) -> Seguimiento de cultivos | E16: =IF('Trabajos 2'!G16="","",'Trabajos 2'!G16) -> La Alborada | F16: =IF('Trabajos 2'!H16="","",'Trabajos 2'!H16) -> 0.5 | G16: =IF('Trabajos 2'!I16="","",'Trabajos 2'!I16) -> 200000 | H16: =IF('Trabajos 2'!J16="","",'Trabajos 2'!J16) -> 100000 | I16: =IF('Trabajos 2'!M16="","",'Trabajos 2'!M16) -> 160 | J16: =IF('Trabajos 2'!N16="","",'Trabajos 2'!N16) -> 650 | K16: =IF('Trabajos 2'!O16="","",'Trabajos 2'!O16) -> 104000 | L16: =IF('Trabajos 2'!P16="","",'Trabajos 2'!P16) -> 204000
... B114: =IF('Trabajos 2'!B114="","",'Trabajos 2'!B114) | C114: =IF('Trabajos 2'!F114="","",'Trabajos 2'!F114) | D114: =IF('Trabajos 2'!D114="","",'Trabajos 2'!D114) | E114: =IF('Trabajos 2'!G114="","",'Trabajos 2'!G114) | F114: =IF('Trabajos 2'!H114="","",'Trabajos 2'!H114) | G114: =IF('Trabajos 2'!I114="","",'Trabajos 2'!I114) | H114: =IF('Trabajos 2'!J114="","",'Trabajos 2'!J114) | I114: =IF('Trabajos 2'!M114="","",'Trabajos 2'!M114) | J114: =IF('Trabajos 2'!N114="","",'Trabajos 2'!N114) | K114: =IF('Trabajos 2'!O114="","",'Trabajos 2'!O114) | L114: =IF('Trabajos 2'!P114="","",'Trabajos 2'!P114)
B115: =IF('Trabajos 2'!B114="","",'Trabajos 2'!B114) | C115: =IF('Trabajos 2'!F115="","",'Trabajos 2'!F115) | D115: =IF('Trabajos 2'!D115="","",'Trabajos 2'!D115) | E115: =IF('Trabajos 2'!G115="","",'Trabajos 2'!G115) | F115: =IF('Trabajos 2'!H115="","",'Trabajos 2'!H115) | G115: =IF('Trabajos 2'!I115="","",'Trabajos 2'!I115) | H115: =IF('Trabajos 2'!J115="","",'Trabajos 2'!J115) | I115: =IF('Trabajos 2'!M115="","",'Trabajos 2'!M115) | J115: =IF('Trabajos 2'!N115="","",'Trabajos 2'!N115) | K115: =IF('Trabajos 2'!O115="","",'Trabajos 2'!O115) | L115: =IF('Trabajos 2'!P115="","",'Trabajos 2'!P115)
B116: =IF('Trabajos 2'!B115="","",'Trabajos 2'!B115) | C116: =IF('Trabajos 2'!F116="","",'Trabajos 2'!F116) | D116: =IF('Trabajos 2'!D116="","",'Trabajos 2'!D116) | E116: =IF('Trabajos 2'!G116="","",'Trabajos 2'!G116) | F116: =IF('Trabajos 2'!H116="","",'Trabajos 2'!H116) | G116: =IF('Trabajos 2'!I116="","",'Trabajos 2'!I116) | H116: =IF('Trabajos 2'!J116="","",'Trabajos 2'!J116) | I116: =IF('Trabajos 2'!M116="","",'Trabajos 2'!M116) | J116: =IF('Trabajos 2'!N116="","",'Trabajos 2'!N116) | K116: =IF('Trabajos 2'!O116="","",'Trabajos 2'!O116) | L116: =IF('Trabajos 2'!P116="","",'Trabajos 2'!P116)
B117: =IF('Trabajos 2'!B116="","",'Trabajos 2'!B116) | C117: =IF('Trabajos 2'!F117="","",'Trabajos 2'!F117) | D117: =IF('Trabajos 2'!D117="","",'Trabajos 2'!D117) | E117: =IF('Trabajos 2'!G117="","",'Trabajos 2'!G117) | F117: =IF('Trabajos 2'!H117="","",'Trabajos 2'!H117) | G117: =IF('Trabajos 2'!I117="","",'Trabajos 2'!I117) | H117: =IF('Trabajos 2'!J117="","",'Trabajos 2'!J117) | I117: =IF('Trabajos 2'!M117="","",'Trabajos 2'!M117) | J117: =IF('Trabajos 2'!N117="","",'Trabajos 2'!N117) | K117: =IF('Trabajos 2'!O117="","",'Trabajos 2'!O117) | L117: =IF('Trabajos 2'!P117="","",'Trabajos 2'!P117)
B118: =IF('Trabajos 2'!B117="","",'Trabajos 2'!B117) | C118: =IF('Trabajos 2'!F118="","",'Trabajos 2'!F118) | D118: =IF('Trabajos 2'!D118="","",'Trabajos 2'!D118) | E118: =IF('Trabajos 2'!G118="","",'Trabajos 2'!G118) | F118: =IF('Trabajos 2'!H118="","",'Trabajos 2'!H118) | G118: =IF('Trabajos 2'!I118="","",'Trabajos 2'!I118) | H118: =IF('Trabajos 2'!J118="","",'Trabajos 2'!J118) | I118: =IF('Trabajos 2'!M118="","",'Trabajos 2'!M118) | J118: =IF('Trabajos 2'!N118="","",'Trabajos 2'!N118) | K118: =IF('Trabajos 2'!O118="","",'Trabajos 2'!O118) | L118: =IF('Trabajos 2'!P118="","",'Trabajos 2'!P118)
B119: =IF('Trabajos 2'!B118="","",'Trabajos 2'!B118) | C119: =IF('Trabajos 2'!F119="","",'Trabajos 2'!F119) | D119: =IF('Trabajos 2'!D119="","",'Trabajos 2'!D119) | E119: =IF('Trabajos 2'!G119="","",'Trabajos 2'!G119) | F119: =IF('Trabajos 2'!H119="","",'Trabajos 2'!H119) | G119: =IF('Trabajos 2'!I119="","",'Trabajos 2'!I119) | H119: =IF('Trabajos 2'!J119="","",'Trabajos 2'!J119) | I119: =IF('Trabajos 2'!M119="","",'Trabajos 2'!M119) | J119: =IF('Trabajos 2'!N119="","",'Trabajos 2'!N119) | K119: =IF('Trabajos 2'!O119="","",'Trabajos 2'!O119) | L119: =IF('Trabajos 2'!P119="","",'Trabajos 2'!P119)
B120: =IF('Trabajos 2'!B119="","",'Trabajos 2'!B119) | C120: =IF('Trabajos 2'!F120="","",'Trabajos 2'!F120) | D120: =IF('Trabajos 2'!D120="","",'Trabajos 2'!D120) | E120: =IF('Trabajos 2'!G120="","",'Trabajos 2'!G120) | F120: =IF('Trabajos 2'!H120="","",'Trabajos 2'!H120) | G120: =IF('Trabajos 2'!I120="","",'Trabajos 2'!I120) | H120: =IF('Trabajos 2'!J120="","",'Trabajos 2'!J120) | I120: =IF('Trabajos 2'!M120="","",'Trabajos 2'!M120) | J120: =IF('Trabajos 2'!N120="","",'Trabajos 2'!N120) | K120: =IF('Trabajos 2'!O120="","",'Trabajos 2'!O120) | L120: =IF('Trabajos 2'!P120="","",'Trabajos 2'!P120)
B121: =IF('Trabajos 2'!B120="","",'Trabajos 2'!B120) | C121: =IF('Trabajos 2'!F121="","",'Trabajos 2'!F121) | D121: =IF('Trabajos 2'!D121="","",'Trabajos 2'!D121) | E121: =IF('Trabajos 2'!G121="","",'Trabajos 2'!G121) | F121: =IF('Trabajos 2'!H121="","",'Trabajos 2'!H121) | G121: =IF('Trabajos 2'!I121="","",'Trabajos 2'!I121) | H121: =IF('Trabajos 2'!J121="","",'Trabajos 2'!J121) | I121: =IF('Trabajos 2'!M121="","",'Trabajos 2'!M121) | J121: =IF('Trabajos 2'!N121="","",'Trabajos 2'!N121) | K121: =IF('Trabajos 2'!O121="","",'Trabajos 2'!O121) | L121: =IF('Trabajos 2'!P121="","",'Trabajos 2'!P121)
B122: =IF('Trabajos 2'!B121="","",'Trabajos 2'!B121) | C122: =IF('Trabajos 2'!F122="","",'Trabajos 2'!F122) | D122: =IF('Trabajos 2'!D122="","",'Trabajos 2'!D122) | E122: =IF('Trabajos 2'!G122="","",'Trabajos 2'!G122) | F122: =IF('Trabajos 2'!H122="","",'Trabajos 2'!H122) | G122: =IF('Trabajos 2'!I122="","",'Trabajos 2'!I122) | H122: =IF('Trabajos 2'!J122="","",'Trabajos 2'!J122) | I122: =IF('Trabajos 2'!M122="","",'Trabajos 2'!M122) | J122: =IF('Trabajos 2'!N122="","",'Trabajos 2'!N122) | K122: =IF('Trabajos 2'!O122="","",'Trabajos 2'!O122) | L122: =IF('Trabajos 2'!P122="","",'Trabajos 2'!P122)
B123: =IF('Trabajos 2'!B122="","",'Trabajos 2'!B122) | C123: =IF('Trabajos 2'!F123="","",'Trabajos 2'!F123) | D123: =IF('Trabajos 2'!D123="","",'Trabajos 2'!D123) | E123: =IF('Trabajos 2'!G123="","",'Trabajos 2'!G123) | F123: =IF('Trabajos 2'!H123="","",'Trabajos 2'!H123) | G123: =IF('Trabajos 2'!I123="","",'Trabajos 2'!I123) | H123: =IF('Trabajos 2'!J123="","",'Trabajos 2'!J123) | I123: =IF('Trabajos 2'!M123="","",'Trabajos 2'!M123) | J123: =IF('Trabajos 2'!N123="","",'Trabajos 2'!N123) | K123: =IF('Trabajos 2'!O123="","",'Trabajos 2'!O123) | L123: =IF('Trabajos 2'!P123="","",'Trabajos 2'!P123)
B124: =IF('Trabajos 2'!B123="","",'Trabajos 2'!B123) | C124: =IF('Trabajos 2'!F124="","",'Trabajos 2'!F124) | D124: =IF('Trabajos 2'!D124="","",'Trabajos 2'!D124) | E124: =IF('Trabajos 2'!G124="","",'Trabajos 2'!G124) | F124: =IF('Trabajos 2'!H124="","",'Trabajos 2'!H124) | G124: =IF('Trabajos 2'!I124="","",'Trabajos 2'!I124) | H124: =IF('Trabajos 2'!J124="","",'Trabajos 2'!J124) | I124: =IF('Trabajos 2'!M124="","",'Trabajos 2'!M124) | J124: =IF('Trabajos 2'!N124="","",'Trabajos 2'!N124) | K124: =IF('Trabajos 2'!O124="","",'Trabajos 2'!O124) | L124: =IF('Trabajos 2'!P124="","",'Trabajos 2'!P124)
B125: =IF('Trabajos 2'!B124="","",'Trabajos 2'!B124) | C125: =IF('Trabajos 2'!F125="","",'Trabajos 2'!F125) | D125: =IF('Trabajos 2'!D125="","",'Trabajos 2'!D125) | E125: =IF('Trabajos 2'!G125="","",'Trabajos 2'!G125) | F125: =IF('Trabajos 2'!H125="","",'Trabajos 2'!H125) | G125: =IF('Trabajos 2'!I125="","",'Trabajos 2'!I125) | H125: =IF('Trabajos 2'!J125="","",'Trabajos 2'!J125) | I125: =IF('Trabajos 2'!M125="","",'Trabajos 2'!M125) | J125: =IF('Trabajos 2'!N125="","",'Trabajos 2'!N125) | K125: =IF('Trabajos 2'!O125="","",'Trabajos 2'!O125) | L125: =IF('Trabajos 2'!P125="","",'Trabajos 2'!P125)
B126: =IF('Trabajos 2'!B125="","",'Trabajos 2'!B125) | C126: =IF('Trabajos 2'!F126="","",'Trabajos 2'!F126) | D126: =IF('Trabajos 2'!D126="","",'Trabajos 2'!D126) | E126: =IF('Trabajos 2'!G126="","",'Trabajos 2'!G126) | F126: =IF('Trabajos 2'!H126="","",'Trabajos 2'!H126) | G126: =IF('Trabajos 2'!I126="","",'Trabajos 2'!I126) | H126: =IF('Trabajos 2'!J126="","",'Trabajos 2'!J126) | I126: =IF('Trabajos 2'!M126="","",'Trabajos 2'!M126) | J126: =IF('Trabajos 2'!N126="","",'Trabajos 2'!N126) | K126: =IF('Trabajos 2'!O126="","",'Trabajos 2'!O126) | L126: =IF('Trabajos 2'!P126="","",'Trabajos 2'!P126)
... B128: =IF('Trabajos 2'!B127="","",'Trabajos 2'!B127) | C128: =IF('Trabajos 2'!F128="","",'Trabajos 2'!F128) | D128: =IF('Trabajos 2'!D128="","",'Trabajos 2'!D128) | E128: =IF('Trabajos 2'!G128="","",'Trabajos 2'!G128) | F128: =IF('Trabajos 2'!H128="","",'Trabajos 2'!H128) | G128: =IF('Trabajos 2'!I128="","",'Trabajos 2'!I128) | H128: =IF('Trabajos 2'!J128="","",'Trabajos 2'!J128) | I128: =IF('Trabajos 2'!M128="","",'Trabajos 2'!M128) | J128: =IF('Trabajos 2'!N128="","",'Trabajos 2'!N128) | K128: =IF('Trabajos 2'!O128="","",'Trabajos 2'!O128) | L128: =IF('Trabajos 2'!P128="","",'Trabajos 2'!P128)
B129: =IF('Trabajos 2'!B129="","",'Trabajos 2'!B129) | C129: =IF('Trabajos 2'!F129="","",'Trabajos 2'!F129) | D129: =IF('Trabajos 2'!D129="","",'Trabajos 2'!D129) | E129: =IF('Trabajos 2'!G129="","",'Trabajos 2'!G129) | F129: =IF('Trabajos 2'!H129="","",'Trabajos 2'!H129) | G129: =IF('Trabajos 2'!I129="","",'Trabajos 2'!I129) | H129: =IF('Trabajos 2'!J129="","",'Trabajos 2'!J129) | I129: =IF('Trabajos 2'!M129="","",'Trabajos 2'!M129) | J129: =IF('Trabajos 2'!N129="","",'Trabajos 2'!N129) | K129: =IF('Trabajos 2'!O129="","",'Trabajos 2'!O129) | L129: =IF('Trabajos 2'!P129="","",'Trabajos 2'!P129)
B130: =IF('Trabajos 2'!B130="","",'Trabajos 2'!B130) | C130: =IF('Trabajos 2'!F130="","",'Trabajos 2'!F130) | D130: =IF('Trabajos 2'!D130="","",'Trabajos 2'!D130) | E130: =IF('Trabajos 2'!G130="","",'Trabajos 2'!G130) | F130: =IF('Trabajos 2'!H130="","",'Trabajos 2'!H130) | G130: =IF('Trabajos 2'!I130="","",'Trabajos 2'!I130) | H130: =IF('Trabajos 2'!J130="","",'Trabajos 2'!J130) | I130: =IF('Trabajos 2'!M130="","",'Trabajos 2'!M130) | J130: =IF('Trabajos 2'!N130="","",'Trabajos 2'!N130) | K130: =IF('Trabajos 2'!O130="","",'Trabajos 2'!O130) | L130: =IF('Trabajos 2'!P130="","",'Trabajos 2'!P130)
B131: =IF('Trabajos 2'!B131="","",'Trabajos 2'!B131) | C131: =IF('Trabajos 2'!F131="","",'Trabajos 2'!F131) | D131: =IF('Trabajos 2'!D131="","",'Trabajos 2'!D131) | E131: =IF('Trabajos 2'!G131="","",'Trabajos 2'!G131) | F131: =IF('Trabajos 2'!H131="","",'Trabajos 2'!H131) | G131: =IF('Trabajos 2'!I131="","",'Trabajos 2'!I131) | H131: =IF('Trabajos 2'!J131="","",'Trabajos 2'!J131) | I131: =IF('Trabajos 2'!M131="","",'Trabajos 2'!M131) | J131: =IF('Trabajos 2'!N131="","",'Trabajos 2'!N131) | K131: =IF('Trabajos 2'!O131="","",'Trabajos 2'!O131) | L131: =IF('Trabajos 2'!P131="","",'Trabajos 2'!P131)
B132: =IF('Trabajos 2'!B132="","",'Trabajos 2'!B132) | C132: =IF('Trabajos 2'!F132="","",'Trabajos 2'!F132) | D132: =IF('Trabajos 2'!D132="","",'Trabajos 2'!D132) | E132: =IF('Trabajos 2'!G132="","",'Trabajos 2'!G132) | F132: =IF('Trabajos 2'!H132="","",'Trabajos 2'!H132) | G132: =IF('Trabajos 2'!I132="","",'Trabajos 2'!I132) | H132: =IF('Trabajos 2'!J132="","",'Trabajos 2'!J132) | I132: =IF('Trabajos 2'!M132="","",'Trabajos 2'!M132) | J132: =IF('Trabajos 2'!N132="","",'Trabajos 2'!N132) | K132: =IF('Trabajos 2'!O132="","",'Trabajos 2'!O132) | L132: =IF('Trabajos 2'!P132="","",'Trabajos 2'!P132)
B133: =IF('Trabajos 2'!B133="","",'Trabajos 2'!B133) | C133: =IF('Trabajos 2'!F133="","",'Trabajos 2'!F133) | D133: =IF('Trabajos 2'!D133="","",'Trabajos 2'!D133) | E133: =IF('Trabajos 2'!G133="","",'Trabajos 2'!G133) | F133: =IF('Trabajos 2'!H133="","",'Trabajos 2'!H133) | G133: =IF('Trabajos 2'!I133="","",'Trabajos 2'!I133) | H133: =IF('Trabajos 2'!J133="","",'Trabajos 2'!J133) | I133: =IF('Trabajos 2'!M133="","",'Trabajos 2'!M133) | J133: =IF('Trabajos 2'!N133="","",'Trabajos 2'!N133) | K133: =IF('Trabajos 2'!O133="","",'Trabajos 2'!O133) | L133: =IF('Trabajos 2'!P133="","",'Trabajos 2'!P133)
B134: =IF('Trabajos 2'!B134="","",'Trabajos 2'!B134) | C134: =IF('Trabajos 2'!F134="","",'Trabajos 2'!F134) | D134: =IF('Trabajos 2'!D134="","",'Trabajos 2'!D134) | E134: =IF('Trabajos 2'!G134="","",'Trabajos 2'!G134) | F134: =IF('Trabajos 2'!H134="","",'Trabajos 2'!H134) | G134: =IF('Trabajos 2'!I134="","",'Trabajos 2'!I134) | H134: =IF('Trabajos 2'!J134="","",'Trabajos 2'!J134) | I134: =IF('Trabajos 2'!M134="","",'Trabajos 2'!M134) | J134: =IF('Trabajos 2'!N134="","",'Trabajos 2'!N134) | K134: =IF('Trabajos 2'!O134="","",'Trabajos 2'!O134) | L134: =IF('Trabajos 2'!P134="","",'Trabajos 2'!P134)
B135: =IF('Trabajos 2'!B135="","",'Trabajos 2'!B135) | C135: =IF('Trabajos 2'!F135="","",'Trabajos 2'!F135) | D135: =IF('Trabajos 2'!D135="","",'Trabajos 2'!D135) | E135: =IF('Trabajos 2'!G135="","",'Trabajos 2'!G135) | F135: =IF('Trabajos 2'!H135="","",'Trabajos 2'!H135) | G135: =IF('Trabajos 2'!I135="","",'Trabajos 2'!I135) | H135: =IF('Trabajos 2'!J135="","",'Trabajos 2'!J135) | I135: =IF('Trabajos 2'!M135="","",'Trabajos 2'!M135) | J135: =IF('Trabajos 2'!N135="","",'Trabajos 2'!N135) | K135: =IF('Trabajos 2'!O135="","",'Trabajos 2'!O135) | L135: =IF('Trabajos 2'!P135="","",'Trabajos 2'!P135)
B136: =IF('Trabajos 2'!B136="","",'Trabajos 2'!B136) | C136: =IF('Trabajos 2'!F136="","",'Trabajos 2'!F136) | D136: =IF('Trabajos 2'!D136="","",'Trabajos 2'!D136) | E136: =IF('Trabajos 2'!G136="","",'Trabajos 2'!G136) | F136: =IF('Trabajos 2'!H136="","",'Trabajos 2'!H136) | G136: =IF('Trabajos 2'!I136="","",'Trabajos 2'!I136) | H136: =IF('Trabajos 2'!J136="","",'Trabajos 2'!J136) | I136: =IF('Trabajos 2'!M136="","",'Trabajos 2'!M136) | J136: =IF('Trabajos 2'!N136="","",'Trabajos 2'!N136) | K136: =IF('Trabajos 2'!O136="","",'Trabajos 2'!O136) | L136: =IF('Trabajos 2'!P136="","",'Trabajos 2'!P136)
B137: =IF('Trabajos 2'!B137="","",'Trabajos 2'!B137) | C137: =IF('Trabajos 2'!F137="","",'Trabajos 2'!F137) | D137: =IF('Trabajos 2'!D137="","",'Trabajos 2'!D137) | E137: =IF('Trabajos 2'!G137="","",'Trabajos 2'!G137) | F137: =IF('Trabajos 2'!H137="","",'Trabajos 2'!H137) | G137: =IF('Trabajos 2'!I137="","",'Trabajos 2'!I137) | H137: =IF('Trabajos 2'!J137="","",'Trabajos 2'!J137) | I137: =IF('Trabajos 2'!M137="","",'Trabajos 2'!M137) | J137: =IF('Trabajos 2'!N137="","",'Trabajos 2'!N137) | K137: =IF('Trabajos 2'!O137="","",'Trabajos 2'!O137) | L137: =IF('Trabajos 2'!P137="","",'Trabajos 2'!P137)
B138: =IF('Trabajos 2'!B138="","",'Trabajos 2'!B138) | C138: =IF('Trabajos 2'!F138="","",'Trabajos 2'!F138) | D138: =IF('Trabajos 2'!D138="","",'Trabajos 2'!D138) | E138: =IF('Trabajos 2'!G138="","",'Trabajos 2'!G138) | F138: =IF('Trabajos 2'!H138="","",'Trabajos 2'!H138) | G138: =IF('Trabajos 2'!I138="","",'Trabajos 2'!I138) | H138: =IF('Trabajos 2'!J138="","",'Trabajos 2'!J138) | I138: =IF('Trabajos 2'!M138="","",'Trabajos 2'!M138) | J138: =IF('Trabajos 2'!N138="","",'Trabajos 2'!N138) | K138: =IF('Trabajos 2'!O138="","",'Trabajos 2'!O138) | L138: =IF('Trabajos 2'!P138="","",'Trabajos 2'!P138)
B139: =IF('Trabajos 2'!B139="","",'Trabajos 2'!B139) | C139: =IF('Trabajos 2'!F139="","",'Trabajos 2'!F139) | D139: =IF('Trabajos 2'!D139="","",'Trabajos 2'!D139) | E139: =IF('Trabajos 2'!G139="","",'Trabajos 2'!G139) | F139: =IF('Trabajos 2'!H139="","",'Trabajos 2'!H139) | G139: =IF('Trabajos 2'!I139="","",'Trabajos 2'!I139) | H139: =IF('Trabajos 2'!J139="","",'Trabajos 2'!J139) | I139: =IF('Trabajos 2'!M139="","",'Trabajos 2'!M139) | J139: =IF('Trabajos 2'!N139="","",'Trabajos 2'!N139) | K139: =IF('Trabajos 2'!O139="","",'Trabajos 2'!O139) | L139: =IF('Trabajos 2'!P139="","",'Trabajos 2'!P139)
B140: =IF('Trabajos 2'!B140="","",'Trabajos 2'!B140) | C140: =IF('Trabajos 2'!F140="","",'Trabajos 2'!F140) | D140: =IF('Trabajos 2'!D140="","",'Trabajos 2'!D140) | E140: =IF('Trabajos 2'!G140="","",'Trabajos 2'!G140) | F140: =IF('Trabajos 2'!H140="","",'Trabajos 2'!H140) | G140: =IF('Trabajos 2'!I140="","",'Trabajos 2'!I140) | H140: =IF('Trabajos 2'!J140="","",'Trabajos 2'!J140) | I140: =IF('Trabajos 2'!M140="","",'Trabajos 2'!M140) | J140: =IF('Trabajos 2'!N140="","",'Trabajos 2'!N140) | K140: =IF('Trabajos 2'!O140="","",'Trabajos 2'!O140) | L140: =IF('Trabajos 2'!P140="","",'Trabajos 2'!P140)
... B152: =IF('Trabajos 2'!B152="","",'Trabajos 2'!B152) | C152: =IF('Trabajos 2'!F152="","",'Trabajos 2'!F152) | D152: =IF('Trabajos 2'!D152="","",'Trabajos 2'!D152) | E152: =IF('Trabajos 2'!G152="","",'Trabajos 2'!G152) | F152: =IF('Trabajos 2'!H152="","",'Trabajos 2'!H152) | G152: =IF('Trabajos 2'!I152="","",'Trabajos 2'!I152) | H152: =IF('Trabajos 2'!J152="","",'Trabajos 2'!J152) | I152: =IF('Trabajos 2'!M152="","",'Trabajos 2'!M152) | J152: =IF('Trabajos 2'!N152="","",'Trabajos 2'!N152) | K152: =IF('Trabajos 2'!O152="","",'Trabajos 2'!O152) | L152: =IF('Trabajos 2'!P152="","",'Trabajos 2'!P152)
B153: Total | F153: =SUBTOTAL(9,F5:F152) -> 80.3 | I153: =SUBTOTAL(9,I5:I152) -> 18828 | L153: =SUBTOTAL(9,L5:L152) -> 26437243

Sheet IVA
B2: IVA
B4: Gastos - Credito Fiscal | E4: Ingresos - Debito Fiscal | I4: Saldo IVA | M4: Saldo
B6: Fecha | C6: Importe | E6: Fecha | F6: Importe | G6: Cobrado | I6: Fecha | J6: Importe | K6: Pagado | M6: Persona | N6: Importe
J7: =SUMIFS($C$7:$C$135,$B$7:$B$135,">="&Referencias!W5,$B$7:$B$135,"<="&Referencias!X5)-SUMIFS($F$7:$F$135,$E$7:$E$135,">="&Referencias!W5,$E$7:$E$135,"<="&Referencias!X5) -> 0 | M7: Tomas | N7: =SUMIF(G7:G135,M7,F7:F135)+SUMIF(K7:K11,M7,J7:J11) -> 0
J8: =SUMIFS($C$7:$C$135,$B$7:$B$135,">="&Referencias!W6,$B$7:$B$135,"<="&Referencias!X6)-SUMIFS($F$7:$F$135,$E$7:$E$135,">="&Referencias!W6,$E$7:$E$135,"<="&Referencias!X6) -> 0 | M8: Paco | N8: =SUMIF(G7:G135,M8,F7:F135)+SUMIF(K7:K11,M8,J7:J11) -> 0
J9: =SUMIFS($C$7:$C$135,$B$7:$B$135,">="&Referencias!W7,$B$7:$B$135,"<="&Referencias!X7)-SUMIFS($F$7:$F$135,$E$7:$E$135,">="&Referencias!W7,$E$7:$E$135,"<="&Referencias!X7) -> 0
J10: =SUMIFS($C$7:$C$135,$B$7:$B$135,">="&Referencias!W8,$B$7:$B$135,"<="&Referencias!X8)-SUMIFS($F$7:$F$135,$E$7:$E$135,">="&Referencias!W8,$E$7:$E$135,"<="&Referencias!X8) -> 0
J11: =SUMIFS($C$7:$C$135,$B$7:$B$135,">="&Referencias!W9,$B$7:$B$135,"<="&Referencias!X9)-SUMIFS($F$7:$F$135,$E$7:$E$135,">="&Referencias!W9,$E$7:$E$135,"<="&Referencias!X9) -> 0

Sheet Referencias
B2: Referencias
B4: Codigo Clientes | E4: Codigo Trabajos | H4: Codigo Vehiculos | K4: Asignacion Trabajo | Q4: Asignacion Empresa | T4: Asignacion Gastos | W4: Fechas
W5: 44287 | X5: 44316
B6: Código | C6: Cliente | E6: Código | F6: Trabajo | H6: Código | I6: Vehiculo | L6: Paco | M6: Tomas | N6: Zoom | O6: Total | Q6: Paco | R6: Tomas | T6: Paco | U6: Tomas | W6: 44317 | X6: 44347
B7: 1 | C7: Daniel Lanz | E7: 1 | F7: Muestreo de suelos | H7: 1 | I7: Tomas | K7: Hectareas | L7: =Trabajos!R395 -> 3704 | M7: =Trabajos!S395 -> 5738 | N7: =Trabajos!T395 -> 37074 | O7: =SUM(L7:N7) -> 46516 | Q7: 0.5 | R7: 0.5 | T7: 0.5 | U7: 0.5 | W7: 44348 | X7: 44377
B8: 2 | C8: Land Management | E8: 2 | F8: Monitoreo de bb y bab | H8: 2 | I8: Paco | K8: Proporcion | L8: =IFERROR((L7/O7),"") -> 0.079628515 | M8: =IFERROR((M7/O7),"") -> 0.1233554 | N8: =IFERROR((N7/O7),"") -> 0.79701608 | W8: 44378 | X8: 44408
B9: 3 | C9: Martin Santamaria | E9: 3 | F9: Aplicación de cebos | H9: 3 | I9: Zoom | W9: 44409 | X9: 44439
B10: 4 | C10: Purtierra | E10: 4 | F10: Seguimiento de cultivos | W10: 44440 | X10: 44469
B11: 5 | C11: Cofina Agro | E11: 5 | F11: Control de cosecha | W11: 44470 | X11: 44500
B12: 6 | C12: La Nany S.A. | E12: 6 | F12: Control de carga
B13: 7 | C13: Agrar del Sur | E13: 7 | F13: Cuantificacion pasturas | K13: Asignacion Trabajo | W13: 44501 | X13: 44530
B14: 8 | C14: Baltan Agropecuaria | E14: 8 | F14: Seguimiento NDVI | W14: 44531 | X14: 44561
B15: 9 | C15: Alberto Oscar Moran | E15: 9 | F15: Ambientacion NDVI | L15: Paco | M15: Tomas | N15: Zoom | O15: Total | W15: 44562 | X15: 44592
B16: 10 | C16: Tibus S.A. | E16: 10 | F16: Mapeo Dron | K16: Dias | L16: ='Trabajos 2'!R157 -> 0 | M16: ='Trabajos 2'!S157 -> 47 | N16: ='Trabajos 2'!T157 -> 33.3 | O16: =SUM(L16:N16) -> 80.3 | W16: 44593 | X16: 44620
B17: 11 | C17: Carlos Fernando Fuertes | E17: 11 | F17: Charlas | K17: Proporcion | L17: =IFERROR((L16/O16),"") -> 0 | M17: =IFERROR((M16/O16),"") -> 0.58530511 | N17: =IFERROR((N16/O16),"") -> 0.41469489 | W17: 44621 | X17: 44651
B18: 12 | C18: Miron y Alfonso/Iocco Palladino
B19: 13 | C19: Los Tuelches
B20: 14 | C20: Nueva Huella S.R.L.
B21: 15 | C21: Lucrecia Casa
B22: 16 | C22: Mariano Alfonso
B23: 17 | C23: Campo Maipu S.A.
B24: 18 | C24: Cosechas del Sur S.R.L.
B25: 19 | C25: Raul Maitia
B26: 20 | C26: Juan Carlos Rey
B27: 21 | C27: Piray Mini
B28: 22 | C28: Domingo Massigoge
B29: 23 | C29: Esteban Dominguez
... B138: 132 | C138: Tres Mil Tres S.A.
